Workbook
Name Accesories_citel: OFFSET(Items!#REF!,,,COUNTA(#REF!))
Name BATTERY_TYPE: OFFSET(Items!#REF!,,,COUNTA(#REF!))
Name BYD_Lithium: Items!$AN$205:$AN$212
Name BYD_Solar_Panel: Items!$AN$242:$AN$243
Name CLIENT_info: OFFSET('Customer Base'!#REF!,,,COUNTA('Customer Base'!#REF!))
Name CurrentUser: #REF!
Name Deye: Items!$AN$77:$AN$83
Name EasySolar: Items!$AN$62
Name EasySolar_II: Items!$AN$64:$AN$66
Name Eco: Items!$AN$117:$AN$118
Name Freedom_Won: Items!#REF!
Name Galvo: Items!$AN$103:$AN$105
Name Gen_24_Primo: Items!$AN$122:$AN$124
Name Gen_24_Symo: Items!$AN$125:$AN$132
Name GX_MONITORING: OFFSET(Items!#REF!,,,COUNTA(#REF!))
Name Hoppecke_Lead_Acid: Items!$AN$234:$AN$236
Name Hoppecke_OPzS: Items!#REF!
Name Hoppecke_OPzV: Items!$AN$233:$AN$233
Name Huawei: Items!$AN$86:$AN$94
Name Huawei_Lithium: Items!$AN$217:$AN$219
Name JA_Solar_Panel: Items!#REF!
Name Jinko_Lithium: Items!$AN$215
Name Jinko_Solar_Panel: Items!$AN$245
Name LIST_OF_INVERTER_INVERTER: OFFSET(Items!$C$5,,,COUNTA(Items!$C:$C))
Name MPPT: OFFSET(#REF!,,,COUNTA(#REF!))
Name Multiplus: Items!$AN$26:$AN$45
Name Multiplus_II: Items!$AN$47:$AN$53
Name Multiplus_II_GX: Items!$AN$54:$AN$55
Name Phocos_B: Items!$AN$72
Name Phocos_H: Items!$AN$69:$AN$71
Name Phoenix: Items!$AN$6:$AN$24
Name Primo: Items!$AN$106:$AN$108
Name Quantity: OFFSET(#REF!,,,COUNTA(#REF!))
Name Quattro: Items!$AN$57:$AN$60
Name Select_Location: OFFSET('Customer Base'!#REF!,,,COUNTA('Customer Base'!#REF!))
Name Select_Solar_Panel_Type: OFFSET(Items!#REF!,,,COUNTA(#REF!))
Name Sharp_Solar_Panel: Items!$AN$249:$AN$249
Name SheetNames: OFFSET(#REF!,,,COUNTA(#REF!))
Name SHUNTS__FUSES_AND_FUSE_HOLDERS: OFFSET(Items!#REF!,,,COUNTA(#REF!))
Name Symo: Items!$AN$109:$AN$116
Name Tauro: Items!$AN$119:$AN$120
Name TOP_DC_AND_AC_SOLAR_CABLE: OFFSET(Items!$M$4,,,COUNTA(#REF!))
Name Victron_AGM: Items!$AN$221:$AN$231
Name VICTRON_CABLES: OFFSET(Items!#REF!,,,COUNTA(#REF!))
Name Victron_Gel: Items!$AN$232:$AN$232
Name Victron_Lead_Carbon: Items!#REF!
Name VICTRON_SMART_MPPT_SOLAR_CHARGE_CONTROLLERS: OFFSET(#REF!,,,COUNTA(#REF!))
Name Victron_Solar_Panel: Items!$AN$251:$AN$254

Sheet Items
J1: Retail | K1: Number of Strings (Total): | L1: =IF(NOW()>INVOICE!Q13,"",IF(AND('Customer Base'!D7<>"Grid-Tied",'Customer Base'!D7<>"Backup",SUM('Client List'!EE477:EE491)<>0),('Client List'!EE474*'Client List'!EC474),0)+IF(AND('Customer Base'!D7<>"Grid-Tied",'Customer Base'!D7<>"Backup",SUM('Client List'!EE477:EE491)<>0),('Client List'!IM474*'Client List'!IK474),0)+IF(AND('Customer Base'!D7<>"Grid-Tied",'Customer Base'!D7<>"Backup",AND(SUM('Client List'!EE477:EE491)=0,'Client List'!EC474>0)),1,0)+IFERROR(L5,0)) -> 2 | M1: Number of Panels per String: | N1: =IFERROR('Client List'!AC493,IF(AND('Customer Base'!D7<>"Backup",SUMPRODUCT(A6:A132,AP6:AP132)>0),SUM(A242:A254)/L5,0)) -> 4 | AX1: Inverter Capacity | AY1: Multiplus | AZ1: 48/3000/35-50 | BA1: 1 | BB1: =INDEX(AM6:AM284,MATCH(AZ1,AN6:AN284,0)) -> 3 | BC1: kVA | BD1: =INDEX(AQ6:AQ284,MATCH(AZ1,AN6:AN284,0)) -> 48 | BE1: V System
A2: {=INDEX(A6:A549,SMALL(IF(A6:A549<>"",ROW(A6:A549)-MIN(ROW(A6:A549))+1),2))} -> 2 | B2: 2 | J2: Super Dealer | K2: Currency | L2: 600 | M2: Hotel Price + Feeding Per night | P2: ="Exchange Rate: USD 1 = GH₵ "&'Customer Base'!J5 -> Exchange Rate: USD 1 = GH₵ 16.7 | BB2: =INDEX(AM6:AM284,MATCH(AZ4,AN6:AN284,0)) -> 0.555 | BC2: kW | BD2: =INDEX(AQ6:AQ284,MATCH(AZ4,AN6:AN284,0)) -> 49.72 | BE2: Voc
C3: Select items | D3: Retail with Tax | E3: Super Dealer with Tax | F3: End User (USD) | G3: End User (GHC) | H3: SuperDealer (USD) | I3: SuperDealer (GHC) | K3: GH₵ | L3: 35 | M3: GH₵/l | AT3: =IF(SUM(AT6:AT13539)>0,SUBTOTAL(109,(AT6:AT939)),"") -> 2 | AU3: =IF(SUM(AU6:AU13539)>0,SUBTOTAL(109,(AU6:AU939)),"") -> 1 | AV3: =IF(SUM(AV6:AV13539)>0,SUBTOTAL(109,(AV6:AV939)),"") -> 3 | AX3: Battery | AY3: Jinko_Lithium | AZ3: 4.8kWh | BA3: 1 | BB3: =INDEX(AM6:AM284,MATCH(AZ3,AN6:AN284,0)) -> 4.8 | BC3: kWh | BD3: =IF(AND(BD1=12,BC4<0.22,(BD2*ROUNDUP(BC4/BB2,0))<75),75,IF(AND(BD1=12,BC4<0.22,(BD2*ROUNDUP(BC4/BB2,0))/2<75),75,IF(AND(BD1=24,BC4<0.44,(BD2*ROUNDUP(BC4/BB2,0))<75),75,IF(AND(BD1=24,BC4<0.44,(BD2*ROUNDUP(BC4/BB2,0))/2<75),75,IF(AND(BD1=12,BC4<0.7,(BD2*ROUNDUP(BC4/BB2,0))<100),100,IF(AND(BD1=12,BC4<0.7,(BD2*ROUNDUP(BC4/BB2,0))/2<100),100,IF(AND(BD1=24,BC4<1.4,(BD2*ROUNDUP(BC4/BB2,0))<100),100,IF(AND(BD1=24,BC4<1.4,(BD2*ROUNDUP(BC4/BB2,0))/2<100),100,IF(AND(BD1=48,BC4<1.16,(BD2*ROUNDUP(BC4/BB2,0))<100),100,IF(AND(BD1=48,BC4<1.16,(BD2*ROUNDUP(BC4/BB2,0))/2<100),100,IF(AND(BD1=12,BC4<1.45,(BD2*ROUNDUP(BC4/BB2,0))<150),150,IF(AND(BD1=12,BC4<1.45,(BD2*ROUNDUP(BC4/BB2,0))/2<150),150,IF(AND(BD1=24,BC4<4.35,(BD2*ROUNDUP(BC4/BB2,0))<150),150,IF(AND(BD1=24,BC4<4.35,(BD2*ROUNDUP(BC4/BB2,0))/2<150),150,IF(AND(BD1=48,BC4<5.8,(BD2*ROUNDUP(BC4/BB2,0))<150),150,IF(AND(BD1=48,BC4<5.8,(BD2*ROUNDUP(BC4/BB2,0))/2<150),150)))))))))))))))) -> 150 | BE3: V Mppt | BF3: =IF(AND(BD1=12,BB4<0.22),75,IF(AND(BD1=24,BB4<0.44),75,IF(AND(BD1=12,BB4<0.7),100,IF(AND(BD1=24,BB4<1.4),100,IF(AND(BD1=48,BB4<1.16),100,IF(AND(BD1=12,BB4<1.45),150,IF(AND(BD1=24,BB4<4.35),150,IF(AND(BD1=48,BB4<5.8),150,IF(BB4>=5.8,IF(ROUNDUP(MOD(BB4,5.8)/BB2,0)>0,150)))))))))) -> 100 | BG3: =IF(BG4=0,"",IF(AND(BD1=12,BG4<0.22),75,IF(AND(BD1=24,BG4<0.44),75,IF(AND(BD1=12,BG4<0.7),100,IF(AND(BD1=24,BG4<1.4),100,IF(AND(BD1=48,BG4<1.16),100,IF(AND(BD1=12,BG4<1.45),150,IF(AND(BD1=24,BG4<4.35),150,IF(AND(BD1=48,BG4<5.8),150))))))))) | BI3: =ROUNDDOWN(BI4/(ROUNDDOWN(BF3/BD2,0)),0) -> 3 | BJ3: =(ROUNDDOWN(BF3/BD2,0)) -> 2
K4: USD | L4: 10 | M4: km/l | AX4: Solar Panels | AY4: JA_Solar_Panel | AZ4: 555W Mono | BA4: =IF(AND(ROUNDUP(BC4/BB2,0)*BD2>BD3,AND(MOD(ROUNDUP(BC4/BB2,0),3)<>0,MOD(ROUNDUP(BC4/BB2,0),2)<>0)),EVEN(ROUNDUP(BC4/BB2,0)),ROUNDUP(BC4/BB2,0)) -> 6 | BB4: =SUMPRODUCT(AV242:AV254,AM242:AM254)*0.8 -> 0 | BC4: =(BA1*(0.5*BB1/0.8))+(BA3*(BB3/0.8/5)) -> 3.075 | BD4: =ROUNDUP(BC4/BB2,0) -> 6 | BG4: =(BA4-BJ4)*BB2 -> 0 | BH4: =ROUNDUP(MOD(BB4,5.8)/BB2,0) -> 0 | BI4: =BA4-BH4 -> 6 | BJ4: =ROUNDDOWN(BI4/(ROUNDDOWN(BF3/BD2,0)),0)*(ROUNDDOWN(BF3/BD2,0)) -> 6 | BK4: =BA4-BJ4 -> 0 | BL4: ='Customer Base'!$J$9*1000*0.8/$BO$4 -> 3.5068966 | BM4: =MOD('Customer Base'!$J$9*1000*0.8,$BO4) -> 588 | BN4: 20 | BO4: 1160
C5: Victron Inverters | K5: Number of Strings (Non-Victron MPPT): | L5: =IF('Customer Base'!D7<>"Mini-Grid",ROUNDUP(SUM(A242:A254)*(SUMPRODUCT(A242:A254,AQ242:AQ254)/SUM(A242:A254))/(SUMPRODUCT(A6:A132,AP6:AP132)/'Customer Base'!D15),0),IF('Customer Base'!D7="Mini-Grid",ROUNDUP(ROUNDDOWN(PRODUCT('Customer Base'!F14:F15,1000/0.8)/'Customer Base'!D26,0)*(SUMPRODUCT(A242:A254,AQ242:AQ254)/SUM(A242:A254))/(SUMPRODUCT(A6:A132,AP6:AP132)/'Customer Base'!F15),0),0)) -> #DIV/0! | N5: Quantity | O5: =IF('Customer Base'!$I$15="MANUAL",IF(B5<>"",C5,""),IF('Customer Base'!$I$15="AUTOMATE",IF(A5<>"",C5,""),"")) | P5: Description | Q5: Delivery | R5: Payment | S5: Validity | T5: Warranty | U5: System Design | AR5: type | AS5: Phase | AT5: Auto | AU5: Manual | AZ5: Inverter List | BA5: Inverter Capacity | BB5: System Voltage | BC5: Battery List | BD5: Battery Capacity | BE5: Solar Panel List | BL5: ='Customer Base'!$J$9*1000*0.8/$BO$5 -> 2.034 | BM5: =MOD('Customer Base'!$J$9*1000*0.8,$BO5) -> 68 | BN5: 35 | BO5: 2000
A6: =IF(AND('Customer Base'!D$8=12,'Customer Base'!D$13="Victron",'Customer Base'!E$13="Phoenix",'Customer Base'!D$14>0,'Customer Base'!D$14<=0.25),'Customer Base'!D$15,IF(AND('Customer Base'!D$7="Mini-Grid",'Customer Base'!D$8=12,'Customer Base'!F$13="Victron",'Customer Base'!F$14>0,'Customer Base'!F$14<=0.25),'Customer Base'!F$15,"")) | C6: Victron Phoenix Inverter 12/250 230V VE.Direct UK | D6: 97.52 | E6: 91.854 | F6: =$D6/1.219 -> 80 | G6: =IFERROR(ROUNDUP(F6*'Customer Base'!$J$5,2),0) -> 1336 | H6: =$E6/1.219 -> 75.351928 | I6: =IFERROR(ROUNDUP(H6*'Customer Base'!$J$5,2),0) -> 1258.38 | J6: =ROUNDUP((M6/$L$4)*$L$3*3,-1) -> 320 | K6: Greater Accra Region | L6: =J6/'Customer Base'!$J$5 -> 19.161677 | M6: 30 | N6: 1 | O6: =IF('Customer Base'!$I$15="MANUAL",IF(B6<>"",C6,""),IF('Customer Base'!$I$15="AUTOMATE",IF(A6<>"",C6,""),"")) | P6: ="TURNKEY SUPPLY AND INSTALLATION OF "&INVOICE!#REF!&"KWP GRID-CONNECTED SOLAR SYSTEM" -> #REF! | Q6: Delivery: Immediate upon confirmation of payment | R6: Payment: 100% Payment with order | S6: Validity: 1 week from date of invoice | T6: Warranty: 10 years for battery, 5 years for inverter and accessories, 10 years for solar panels | U6: System Design: Hybrid Solar system to supply power to residential facility | W6: DISPLAY TAX | AD6: TINO SOLUTIONS BANKS ACCOUNT DETAILS | AM6: 0.25 | AN6: 12/250 | AO6: =IF('Customer Base'!$I$15="MANUAL",IFERROR(AM6*B6,""),IF('Customer Base'!$I$15="AUTOMATE",IFERROR(AM6*A6,""),"")) | AQ6: 12 | AR6: Phoenix | AS6: 1 | AT6: =IF(AND(AR6=$AY$1,$AZ$1=AN6),BA$1,"") | AV6: =IF(AU6<>"",AU6,AT6) | AX6: =IF(SUMPRODUCT(AS6:AS195,AV6:AV195)>=3,3,1) -> 1 | AZ6: {=INDEX(AR$6:AR$132,MATCH(0,COUNTIF($AZ$5:AZ5,AR$6:AR$132),0))} -> Phoenix | BA6: {=INDEX(AM$6:AM$161,MATCH(0,COUNTIF($BA$5:BA5,AM$6:AM$161),0))} -> 0.25 | BB6: {=INDEX(AQ$6:AQ$161,MATCH(0,COUNTIF($BB$5:BB5,AQ$6:AQ$161),0))} -> 12 | BC6: {=INDEX(AR$205:AR$236,MATCH(0,COUNTIF($BC$5:BC5,AR$205:AR$236),0))} -> BYD_Lithium | BE6: {=INDEX(AR$242:AR$254,MATCH(0,COUNTIF($BE$5:BE5,AR$242:AR$254),0))} -> BYD_Solar_Panel | BL6: ='Customer Base'!$J$9*1000*0.8/$BO$6 -> 1.5646154 | BM6: =MOD('Customer Base'!$J$9*1000*0.8,$BO6) -> 1468 | BN6: 45 | BO6: 2600
A7: =IF(AND('Customer Base'!D$8=12,'Customer Base'!D$13="Victron",'Customer Base'!E$13="Phoenix",'Customer Base'!D$14>0.25,'Customer Base'!D$14<=0.375),'Customer Base'!D$15,IF(AND('Customer Base'!D$7="Mini-Grid",'Customer Base'!D$8=12,'Customer Base'!F$13="Victron",'Customer Base'!F$14>0.25,'Customer Base'!F$14<=0.375),'Customer Base'!F$15,"")) | C7: Victron Phoenix Inverter 12/375 230V VE.Direct UK | D7: 126.42 | E7: 119.07 | F7: =$D7/1.219 -> 103.70796 | G7: =IFERROR(ROUNDUP(F7*'Customer Base'!$J$5,2),0) -> 1731.93 | H7: =$E7/1.219 -> 97.678425 | I7: =IFERROR(ROUNDUP(H7*'Customer Base'!$J$5,2),0) -> 1631.23 | J7: =ROUNDUP((M7/$L$4)*$L$3*3,-1) -> 320 | K7: Accra | L7: =J7/'Customer Base'!$J$5 -> 19.161677 | M7: 30 | N7: 2 | O7: =IF('Customer Base'!$I$15="MANUAL",IF(B7<>"",C7,""),IF('Customer Base'!$I$15="AUTOMATE",IF(A7<>"",C7,""),"")) | P7: SOLAR SYSTEM COMPONENTS COST | Q7: Delivery: Within 30 days after receipt of Purchase Order | R7: Payment: 70% Payment with order, 30% Payment upon system Commissioning | S7: Validity: 2 weeks from date of invoice | T7: Warranty: 1 year for battery, 5 years for inverter and accessories, 10 years for solar panels | U7: System Design: Hybrid Solar system to supply power to commercial facility | W7: DO NOT DISPLAY TAX | AD7: BANK NAME | AE7: CEDIS | AF7: DOLLAR | AG7: ACCOUNT NAME | AJ7: BRANCH | AM7: 0.375 | AN7: 12/375 | AO7: =IF('Customer Base'!$I$15="MANUAL",IFERROR(AM7*B7,""),IF('Customer Base'!$I$15="AUTOMATE",IFERROR(AM7*A7,""),"")) | AQ7: 12 | AR7: Phoenix | AS7: 1 | AT7: =IF(AND(AR7=$AY$1,$AZ$1=AN7),BA$1,"") | AU7: 1 | AV7: =IF(AU7<>"",AU7,AT7) -> 1 | AZ7: {=INDEX(AR$6:AR$132,MATCH(0,COUNTIF($AZ$5:AZ6,AR$6:AR$132),0))} -> 0 | BA7: {=INDEX(AM$6:AM$161,MATCH(0,COUNTIF($BA$5:BA6,AM$6:AM$161),0))} -> 0.375 | BB7: {=INDEX(AQ$6:AQ$161,MATCH(0,COUNTIF($BB$5:BB6,AQ$6:AQ$161),0))} -> 24 | BC7: {=INDEX(AR$205:AR$236,MATCH(0,COUNTIF($BC$5:BC6,AR$205:AR$236),0))} -> 0 | BD7: {=INDEX(AM$205:AM$236,MATCH(0,COUNTIF($BD$5:BD5,AM$205:AM$236),0))} -> 4 | BE7: {=INDEX(AR$242:AR$254,MATCH(0,COUNTIF($BE$5:BE6,AR$242:AR$254),0))} -> 0 | BL7: ='Customer Base'!$J$9*1000*0.8/$BO$7 -> 1.1825581 | BM7: =MOD('Customer Base'!$J$9*1000*0.8,$BO7) -> 628 | BN7: 60 | BO7: 3440
A8: =IF(AND('Customer Base'!D$8=12,'Customer Base'!D$13="Victron",'Customer Base'!E$13="Phoenix",'Customer Base'!D$14>0.375,'Customer Base'!D$14<=0.5),'Customer Base'!D$15,IF(AND('Customer Base'!D$7="Mini-Grid",'Customer Base'!D$8=12,'Customer Base'!F$13="Victron",'Customer Base'!F$14>0.375,'Customer Base'!F$14<=0.5),'Customer Base'!F$15,"")) | C8: Victron Phoenix Inverter 12/500 230V VE.Direct UK | D8: 158.03 | E8: 148.846 | F8: =$D8/1.219 -> 129.63905 | G8: =IFERROR(ROUNDUP(F8*'Customer Base'!$J$5,2),0) -> 2164.98 | H8: =$E8/1.219 -> 122.105 | I8: =IFERROR(ROUNDUP(H8*'Customer Base'!$J$5,2),0) -> 2039.16 | J8: =ROUNDUP((M8/$L$4)*$L$3*3,-1) -> 320 | K8: Tema | L8: =J8/'Customer Base'!$J$5 -> 19.161677 | M8: 30 | N8: 3 | O8: =IF('Customer Base'!$I$15="MANUAL",IF(B8<>"",C8,""),IF('Customer Base'!$I$15="AUTOMATE",IF(A8<>"",C8,""),"")) | P8: DATA LOGGER RENTAL | Q8: Delivery: Within 90 days after receipt of Purchase Order | S8: Validity: 30 days from date of invoice | T8: Warranty: 5 years for inverter and accessories, 10 years for solar panels | U8: System Design: Grid-tied solar system for commercial facility | AD8: Bank Name: ACCESS BANK (GHANA) PLC | AE8: Account No: 0200223082501 (GHS) | AF8: Account No: 0201013082501 (USD) | AG8: Account Name: Tino Solutions Limited | AH8: Swift Code: ABNGGHACXXX | AI8: Sort Code: 280114 | AJ8: Bank Branch: Abeka Lapaz | AM8: 0.5 | AN8: 12/500 | AO8: =IF('Customer Base'!$I$15="MANUAL",IFERROR(AM8*B8,""),IF('Customer Base'!$I$15="AUTOMATE",IFERROR(AM8*A8,""),"")) | AQ8: 12 | AR8: Phoenix | AS8: 1 | AT8: =IF(AND(AR8=$AY$1,$AZ$1=AN8),BA$1,"") | AV8: =IF(AU8<>"",AU8,AT8) | AZ8: {=INDEX(AR$6:AR$132,MATCH(0,COUNTIF($AZ$5:AZ7,AR$6:AR$132),0))} -> Multiplus | BA8: {=INDEX(AM$6:AM$161,MATCH(0,COUNTIF($BA$5:BA7,AM$6:AM$161),0))} -> 0.5 | BB8: {=INDEX(AQ$6:AQ$161,MATCH(0,COUNTIF($BB$5:BB7,AQ$6:AQ$161),0))} -> 48 | BC8: {=INDEX(AR$205:AR$236,MATCH(0,COUNTIF($BC$5:BC7,AR$205:AR$236),0))} -> Jinko_Lithium | BD8: {=INDEX(AM$205:AM$236,MATCH(0,COUNTIF($BD$5:BD7,AM$205:AM$236),0))} -> 5 | BE8: {=INDEX(AR$242:AR$254,MATCH(0,COUNTIF($BE$5:BE7,AR$242:AR$254),0))} -> Jinko_Solar_Panel | BL8: ='Customer Base'!$J$9*1000*0.8/$BO$8 -> 1.017 | BM8: =MOD('Customer Base'!$J$9*1000*0.8,$BO8) -> 68 | BN8: 70 | BO8: 4000
A9: =IF(AND('Customer Base'!D$8=12,'Customer Base'!D$13="Victron",'Customer Base'!E$13="Phoenix",'Customer Base'!D$14>0.5,'Customer Base'!D$14<=0.8),'Customer Base'!D$15,IF(AND('Customer Base'!D$7="Mini-Grid",'Customer Base'!D$8=12,'Customer Base'!F$13="Victron",'Customer Base'!F$14>0.5,'Customer Base'!F$14<=0.8),'Customer Base'!F$15,"")) | C9: Victron Phoenix Inverter 12/800 230V VE.Direct UK | D9: 256.46 | E9: 241.542 | F9: =$D9/1.219 -> 210.38556 | G9: =IFERROR(ROUNDUP(F9*'Customer Base'!$J$5,2),0) -> 3513.44 | H9: =$E9/1.219 -> 198.14766 | I9: =IFERROR(ROUNDUP(H9*'Customer Base'!$J$5,2),0) -> 3309.07 | J9: =ROUNDUP((M9/$L$4)*$L$3*3,-1) -> 2400 | K9: Western Region | L9: =J9/'Customer Base'!$J$5 -> 143.71257 | M9: 228 | N9: 4 | O9: =IF('Customer Base'!$I$15="MANUAL",IF(B9<>"",C9,""),IF('Customer Base'!$I$15="AUTOMATE",IF(A9<>"",C9,""),"")) | P9: DATA LOGGER RENTAL FROM 13-05-2022 TO 20-05-2022 | Q9: Delivery: Inverter is currently available. Batteries will be available by end of February | S9: Validity: 90 days from date of invoice | T9: Warranty: 2 Years for lead-acid batteries | U9: System Design: Grid-tied solar system for industrifal facility | W9: RESIDENTIAL | AD9: Bank Name: STANDARD CHARTERED BANK GHANA LIMITED | AE9: Account No: 0100106241600 (GHS) | AF9: Account No: 8701506241600 (USD) | AG9: Account Name: Tino Solutions Limited | AH9: Swift Code: SCBLGHACXXX | AI9: Sort Code: 020127 | AJ9: Bank Branch: Achimota Mall | AM9: 0.8 | AN9: 12/800 | AO9: =IF('Customer Base'!$I$15="MANUAL",IFERROR(AM9*B9,""),IF('Customer Base'!$I$15="AUTOMATE",IFERROR(AM9*A9,""),"")) | AQ9: 12 | AR9: Phoenix | AS9: 1 | AT9: =IF(AND(AR9=$AY$1,$AZ$1=AN9),BA$1,"") | AV9: =IF(AU9<>"",AU9,AT9) | AZ9: {=INDEX(AR$6:AR$132,MATCH(0,COUNTIF($AZ$5:AZ8,AR$6:AR$132),0))} -> Multiplus_II | BA9: {=INDEX(AM$6:AM$161,MATCH(0,COUNTIF($BA$5:BA8,AM$6:AM$161),0))} -> 0.8 | BB9: {=INDEX(AQ$6:AQ$161,MATCH(0,COUNTIF($BB$5:BB8,AQ$6:AQ$161),0))} -> 0 | BC9: {=INDEX(AR$205:AR$236,MATCH(0,COUNTIF($BC$5:BC8,AR$205:AR$236),0))} -> Huawei_Lithium | BD9: {=INDEX(AM$205:AM$236,MATCH(0,COUNTIF($BD$5:BD8,AM$205:AM$236),0))} -> 0 | BE9: {=INDEX(AR$242:AR$254,MATCH(0,COUNTIF($BE$5:BE8,AR$242:AR$254),0))} -> JA_Solar_Panel | BL9: ='Customer Base'!$J$9*1000*0.8/$BO$9 -> 0.83020408 | BM9: =MOD('Customer Base'!$J$9*1000*0.8,$BO9) -> 4068 | BN9: 85 | BO9: 4900
C10: Victron Phoenix Inverter 12/1200 230V VE.Direct UK | D10: 338.63 | E10: 318.946 | F10: =$D10/1.219 -> 277.79327 | G10: =IFERROR(ROUNDUP(F10*'Customer Base'!$J$5,2),0) -> 4639.15 | H10: =$E10/1.219 -> 261.64561 | I10: =IFERROR(ROUNDUP(H10*'Customer Base'!$J$5,2),0) -> 4369.49 | J10: =ROUNDUP((M10/$L$4)*$L$3*3,-1) -> 2400 | K10: Takoradi | L10: =J10/'Customer Base'!$J$5 -> 143.71257 | M10: 228 | N10: 5 | O10: =IF('Customer Base'!$I$15="MANUAL",IF(B10<>"",C10,""),IF('Customer Base'!$I$15="AUTOMATE",IF(A10<>"",C10,""),"")) | P10: VICTRON HYBRID SOLAR SYSTEM | U10: System Design: System Components for Installation by client | W10: NON-RESIDENTIAL | AD10: Bank Name: ZENITH BANK (GH) LTD | AE10: Account No: 6010184886 (GHS) | AF10: Account No: 6040100024 (USD) | AG10: Account Name: Tino Solutions Limited | AH10: Swift Code: ZEBLGHACXXX | AI10: Sort Code: 120101 | AJ10: Bank Branch: Premier Towers | AM10: 1.2 | AN10: 12/1200 VE.Direct | AO10: =IF('Customer Base'!$I$15="MANUAL",IFERROR(AM10*B10,""),IF('Customer Base'!$I$15="AUTOMATE",IFERROR(AM10*A10,""),"")) -> 0 | AQ10: 12 | AR10: Phoenix | AS10: 1 | AT10: =IF(AND(AR10=$AY$1,$AZ$1=AN10),BA$1,"") | AV10: =IF(AU10<>"",AU10,AT10) | AZ10: {=INDEX(AR$6:AR$132,MATCH(0,COUNTIF($AZ$5:AZ9,AR$6:AR$132),0))} -> Multiplus_II_GX | BA10: {=INDEX(AM$6:AM$161,MATCH(0,COUNTIF($BA$5:BA9,AM$6:AM$161),0))} -> 1.2 | BB10: {=INDEX(AQ$6:AQ$161,MATCH(0,COUNTIF($BB$5:BB9,AQ$6:AQ$161),0))} -> Grid-Tied | BC10: {=INDEX(AR$205:AR$236,MATCH(0,COUNTIF($BC$5:BC9,AR$205:AR$236),0))} -> Victron_AGM | BD10: {=INDEX(AM$205:AM$236,MATCH(0,COUNTIF($BD$5:BD9,AM$205:AM$236),0))} -> 15.4 | BE10: {=INDEX(AR$242:AR$254,MATCH(0,COUNTIF($BE$5:BE9,AR$242:AR$254),0))} -> Sharp_Solar_Panel | BL10: ='Customer Base'!$J$9*1000*0.8/$BO$10 -> 0.70137931 | BM10: =MOD('Customer Base'!$J$9*1000*0.8,$BO10) -> 4068 | BN10: 100 | BO10: 5800
C11: Victron Phoenix Inverter 24/250 230V VE.Direct UK | D11: 95.52 | E11: 91.85 | F11: =$D11/1.219 -> 78.359311 | G11: =IFERROR(ROUNDUP(F11*'Customer Base'!$J$5,2),0) -> 1308.61 | H11: =$E11/1.219 -> 75.348646 | I11: =IFERROR(ROUNDUP(H11*'Customer Base'!$J$5,2),0) -> 1258.33 | J11: =ROUNDUP((M11/$L$4)*$L$3*3,-1) -> 2400 | K11: Secondi | L11: =J11/'Customer Base'!$J$5 -> 143.71257 | M11: 228 | N11: 6 | O11: =IF('Customer Base'!$I$15="MANUAL",IF(B11<>"",C11,""),IF('Customer Base'!$I$15="AUTOMATE",IF(A11<>"",C11,""),"")) | P11: VICTRON OFF-GRID SOLAR SYSTEM | U11: System Design: System Upgrade | W11: SLT LV | AD11: Bank Name: UNITED BANK FOR AFRICA (GHANA) LTD | AE11: Account No: 00101312003503 (GHS) | AF11: Account No: 00101312002230 (USD) | AG11: Account Name: Tino Solutions Limited | AH11: Swift Code: STBGGHACXXX | AI11: Sort Code: 060101 | AJ11: Bank Branch: Heritage Tower | AM11: 0.25 | AN11: 24/250 | AO11: =IF('Customer Base'!$I$15="MANUAL",IFERROR(AM11*B11,""),IF('Customer Base'!$I$15="AUTOMATE",IFERROR(AM11*A11,""),"")) -> 0 | AQ11: 24 | AR11: Phoenix | AS11: 1 | AT11: =IF(AND(AR11=$AY$1,$AZ$1=AN11),BA$1,"") | AV11: =IF(AU11<>"",AU11,AT11) | AZ11: {=INDEX(AR$6:AR$132,MATCH(0,COUNTIF($AZ$5:AZ10,AR$6:AR$132),0))} -> Quattro | BA11: {=INDEX(AM$6:AM$161,MATCH(0,COUNTIF($BA$5:BA10,AM$6:AM$161),0))} -> 1.6 | BC11: {=INDEX(AR$205:AR$236,MATCH(0,COUNTIF($BC$5:BC10,AR$205:AR$236),0))} -> Victron_Gel | BD11: {=INDEX(AM$205:AM$236,MATCH(0,COUNTIF($BD$5:BD10,AM$205:AM$236),0))} -> 2.56 | BE11: {=INDEX(AR$242:AR$254,MATCH(0,COUNTIF($BE$5:BE10,AR$242:AR$254),0))} -> Victron_Solar_Panel
C12: Victron Phoenix Inverter 24/375 230V VE.Direct UK | D12: 126.42 | E12: 119.07 | F12: =$D12/1.219 -> 103.70796 | G12: =IFERROR(ROUNDUP(F12*'Customer Base'!$J$5,2),0) -> 1731.93 | H12: =$E12/1.219 -> 97.678425 | I12: =IFERROR(ROUNDUP(H12*'Customer Base'!$J$5,2),0) -> 1631.23 | J12: =ROUNDUP((M12/$L$4)*$L$3*3,-1) -> 8510 | K12: Upper East Region | L12: =J12/'Customer Base'!$J$5 -> 509.58084 | M12: 810 | N12: 7 | O12: =IF('Customer Base'!$I$15="MANUAL",IF(B12<>"",C12,""),IF('Customer Base'!$I$15="AUTOMATE",IF(A12<>"",C12,""),"")) | P12: GRID TIED SOLAR SYSTEM | U12: System Design: Solar System Relocation | W12: SLT MV | AD12: Bank Name: CONSOLIDATED BANK GHANA LTD | AE12: Account No: 0111302717161 (GHS) | AF12: Account No: 0111302717162 (USD) | AG12: Account Name: Tino Solutions Limited | AH12: Swift Code: CBGHGHACXXX | AI12: Sort Code: 340147 | AJ12: Bank Branch: Oxford Street Branch | AM12: 0.375 | AN12: 24/375 | AO12: =IF('Customer Base'!$I$15="MANUAL",IFERROR(AM12*B12,""),IF('Customer Base'!$I$15="AUTOMATE",IFERROR(AM12*A12,""),"")) -> 0 | AQ12: 24 | AR12: Phoenix | AS12: 1 | AT12: =IF(AND(AR12=$AY$1,$AZ$1=AN12),BA$1,"") | AV12: =IF(AU12<>"",AU12,AT12) | AZ12: {=INDEX(AR$6:AR$132,MATCH(0,COUNTIF($AZ$5:AZ11,AR$6:AR$132),0))} -> EasySolar | BA12: {=INDEX(AM$6:AM$161,MATCH(0,COUNTIF($BA$5:BA11,AM$6:AM$161),0))} -> 2 | BC12: {=INDEX(AR$205:AR$236,MATCH(0,COUNTIF($BC$5:BC11,AR$205:AR$236),0))} -> Hoppecke_OPzV | BD12: {=INDEX(AM$205:AM$236,MATCH(0,COUNTIF($BD$5:BD11,AM$205:AM$236),0))} -> 4.8 | BL12: =MIN(BL4:BL10) -> 0.70137931 | BM12: =MAX(BM4:BM10) -> 4068
A13: =IF(AND('Customer Base'!D$8=24,'Customer Base'!D$13="Victron",'Customer Base'!E$13="Phoenix",'Customer Base'!D$14>0,'Customer Base'!D$14<=0.5),'Customer Base'!D$15,IF(AND('Customer Base'!D$7="Mini-Grid",'Customer Base'!D$8=24,'Customer Base'!F$13="Victron",'Customer Base'!F$14>0,'Customer Base'!F$14<=0.5),'Customer Base'!F$15,"")) | C13: Victron Phoenix Inverter 24/500 230V VE.Direct UK | D13: 158.03 | E13: 148.85 | F13: =$D13/1.219 -> 129.63905 | G13: =IFERROR(ROUNDUP(F13*'Customer Base'!$J$5,2),0) -> 2164.98 | H13: =$E13/1.219 -> 122.10829 | I13: =IFERROR(ROUNDUP(H13*'Customer Base'!$J$5,2),0) -> 2039.21 | J13: =ROUNDUP((M13/$L$4)*$L$3*3,-1) -> 8510 | K13: Bolgatanga | L13: =J13/'Customer Base'!$J$5 -> 509.58084 | M13: 810 | N13: 8 | O13: =IF('Customer Base'!$I$15="MANUAL",IF(B13<>"",C13,""),IF('Customer Base'!$I$15="AUTOMATE",IF(A13<>"",C13,""),"")) | P13: TROUBLESHOOTING OF FAULT ON SOLAR SYSTEM | U13: System Design: Solar System Relocation and Upgrade | W13: SLT HV | AD13: Bank Name: ECOBANK (GH) LTD | AE13: Account No: 1441002237313 (GHS) | AF13: Account No: 3441002198840 (USD) | AG13: Account Name: Tino Solutions Limited | AH13: Swift Code: ECOCGHACXXX | AI13: Sort Code: 130111 | AJ13: Bank Branch: Abeka Lapaz | AM13: 0.5 | AN13: 24/500 | AO13: =IF('Customer Base'!$I$15="MANUAL",IFERROR(AM13*B13,""),IF('Customer Base'!$I$15="AUTOMATE",IFERROR(AM13*A13,""),"")) | AQ13: 24 | AR13: Phoenix | AS13: 1 | AT13: =IF(AND(AR13=$AY$1,$AZ$1=AN13),BA$1,"") | AV13: =IF(AU13<>"",AU13,AT13) | AZ13: {=INDEX(AR$6:AR$132,MATCH(0,COUNTIF($AZ$5:AZ12,AR$6:AR$132),0))} -> EasySolar_II | BA13: {=INDEX(AM$6:AM$161,MATCH(0,COUNTIF($BA$5:BA12,AM$6:AM$161),0))} -> 3 | BC13: {=INDEX(AR$205:AR$236,MATCH(0,COUNTIF($BC$5:BC12,AR$205:AR$236),0))} -> Hoppecke_Lead_Acid | BD13: {=INDEX(AM$205:AM$236,MATCH(0,COUNTIF($BD$5:BD12,AM$205:AM$236),0))} -> 0.096
A14: =IF(AND('Customer Base'!D$8=24,'Customer Base'!D$13="Victron",'Customer Base'!E$13="Phoenix",'Customer Base'!D$14>0.5,'Customer Base'!D$14<=0.8),'Customer Base'!D$15,IF(AND('Customer Base'!D$7="Mini-Grid",'Customer Base'!D$8=24,'Customer Base'!F$13="Victron",'Customer Base'!F$14>0.5,'Customer Base'!F$14<=0.8),'Customer Base'!F$15,"")) | C14: Victron Phoenix Inverter 24/800 230V VE.Direct UK | D14: 256.46 | E14: 241.54 | F14: =$D14/1.219 -> 210.38556 | G14: =IFERROR(ROUNDUP(F14*'Customer Base'!$J$5,2),0) -> 3513.44 | H14: =$E14/1.219 -> 198.14602 | I14: =IFERROR(ROUNDUP(H14*'Customer Base'!$J$5,2),0) -> 3309.04 | J14: =ROUNDUP((M14/$L$4)*$L$3*3,-1) -> 900 | K14: Eastern Region | L14: =J14/'Customer Base'!$J$5 -> 53.892216 | M14: 85 | N14: 9 | O14: =IF('Customer Base'!$I$15="MANUAL",IF(B14<>"",C14,""),IF('Customer Base'!$I$15="AUTOMATE",IF(A14<>"",C14,""),"")) | P14: SOLAR SYSTEM UPGRADE | U14: System Design: Removal and Reinstallation of Solar System | W14: SLT Steel Companies | AD14: Bank Name: FIDELITY BANK GHANA LIMITED | AE14: Account No: 1050028224118 (GHS) | AF14: Account No: 1951028224113 (USD) | AG14: Account Name: Tino Solutions Limited | AH14: Swift Code: FBLIGHACXXX | AI14: Sort Code: 240118 | AJ14: Bank Branch: Adenta | AM14: 0.8 | AN14: 24/800 | AO14: =IF('Customer Base'!$I$15="MANUAL",IFERROR(AM14*B14,""),IF('Customer Base'!$I$15="AUTOMATE",IFERROR(AM14*A14,""),"")) | AQ14: 24 | AR14: Phoenix | AS14: 1 | AT14: =IF(AND(AR14=$AY$1,$AZ$1=AN14),BA$1,"") | AV14: =IF(AU14<>"",AU14,AT14) | AZ14: {=INDEX(AR$6:AR$132,MATCH(0,COUNTIF($AZ$5:AZ13,AR$6:AR$132),0))} -> Phocos_H | BA14: {=INDEX(AM$6:AM$161,MATCH(0,COUNTIF($BA$5:BA13,AM$6:AM$161),0))} -> 5 | BC14: {=INDEX(AR$205:AR$236,MATCH(0,COUNTIF($BC$5:BC13,AR$205:AR$236),0))} -> #N/A | BD14: {=INDEX(AM$205:AM$236,MATCH(0,COUNTIF($BD$5:BD13,AM$205:AM$236),0))} -> 0.168 | BN14: =VLOOKUP(BL12,BL4:BO10,3,FALSE) -> 100 | BO14: =VLOOKUP(BM12,BM4:BO10,2,FALSE) -> 85
C15: Victron Phoenix Inverter 24/1200 230V VE.Direct UK | D15: 338.63 | E15: 318.95 | F15: =$D15/1.219 -> 277.79327 | G15: =IFERROR(ROUNDUP(F15*'Customer Base'!$J$5,2),0) -> 4639.15 | H15: =$E15/1.219 -> 261.64889 | I15: =IFERROR(ROUNDUP(H15*'Customer Base'!$J$5,2),0) -> 4369.54 | J15: =ROUNDUP((M15/$L$4)*$L$3*3,-1) -> 900 | K15: Koforidua | L15: =J15/'Customer Base'!$J$5 -> 53.892216 | M15: 85 | N15: 10 | O15: =IF('Customer Base'!$I$15="MANUAL",IF(B15<>"",C15,""),IF('Customer Base'!$I$15="AUTOMATE",IF(A15<>"",C15,""),"")) | P15: SOLAR SYSTEM RELOCATION | U15: System Design: Solar system to supply power to residential facility | W15: SLT HV Mines | AD15: Bank Name: CAL BANK GHANA LIMITED | AE15: Account No: 1400007916096 (GHS) | AF15: Account No: 14000079000234 (USD) | AG15: Account Name: Tino Solutions Limited | AH15: Swift Code: ACCCGHACXXX | AI15: Sort Code: 140101 | AJ15: Bank Branch: Independence Avenue | AM15: 1.2 | AN15: 24/1200 | AO15: =IF('Customer Base'!$I$15="MANUAL",IFERROR(AM15*B15,""),IF('Customer Base'!$I$15="AUTOMATE",IFERROR(AM15*A15,""),"")) -> 0 | AQ15: 24 | AR15: Phoenix | AS15: 1 | AT15: =IF(AND(AR15=$AY$1,$AZ$1=AN15),BA$1,"") | AV15: =IF(AU15<>"",AU15,AT15) | AZ15: {=INDEX(AR$6:AR$132,MATCH(0,COUNTIF($AZ$5:AZ14,AR$6:AR$132),0))} -> Phocos_B | BA15: {=INDEX(AM$6:AM$161,MATCH(0,COUNTIF($BA$5:BA14,AM$6:AM$161),0))} -> 0 | BC15: {=INDEX(AR$205:AR$236,MATCH(0,COUNTIF($BC$5:BC14,AR$205:AR$236),0))} -> #N/A | BD15: {=INDEX(AM$205:AM$236,MATCH(0,COUNTIF($BD$5:BD14,AM$205:AM$236),0))} -> 0.264
C16: Victron Phoenix Inverter 48/250 230V VE.Direct UK | D16: 95.52 | E16: 91.854 | F16: =$D16/1.219 -> 78.359311 | G16: =IFERROR(ROUNDUP(F16*'Customer Base'!$J$5,2),0) -> 1308.61 | H16: =$E16/1.219 -> 75.351928 | I16: =IFERROR(ROUNDUP(H16*'Customer Base'!$J$5,2),0) -> 1258.38 | J16: =ROUNDUP((M16/$L$4)*$L$3*3,-1) -> 1200 | K16: Central Region | L16: =J16/'Customer Base'!$J$5 -> 71.856287 | M16: 114 | N16: 11 | O16: =IF('Customer Base'!$I$15="MANUAL",IF(B16<>"",C16,""),IF('Customer Base'!$I$15="AUTOMATE",IF(A16<>"",C16,""),"")) | P16: REMOVAL OF SOLAR SYSTEM COMPONENTS AND REINSTALLATION | AD16: Bank Name: ABSA BANK GHANA LIMITED | AE16: Account No: 0000001075713 (GHS) | AF16: Account No: 0000001504475 (USD) | AG16: Account Name: Tino Solutions Limited | AH16: Swift Code: BARCGHACXXX | AI16: Sort Code: 030114 | AJ16: Bank Branch: Ring Road Central | AM16: 0.25 | AN16: 48/250 | AO16: =IF('Customer Base'!$I$15="MANUAL",IFERROR(AM16*B16,""),IF('Customer Base'!$I$15="AUTOMATE",IFERROR(AM16*A16,""),"")) -> 0 | AQ16: 48 | AR16: Phoenix | AS16: 1 | AT16: =IF(AND(AR16=$AY$1,$AZ$1=AN16),BA$1,"") | AV16: =IF(AU16<>"",AU16,AT16) | AZ16: {=INDEX(AR$6:AR$132,MATCH(0,COUNTIF($AZ$5:AZ15,AR$6:AR$132),0))} -> Deye | BA16: {=INDEX(AM$6:AM$161,MATCH(0,COUNTIF($BA$5:BA15,AM$6:AM$161),0))} -> 6 | BC16: {=INDEX(AR$205:AR$236,MATCH(0,COUNTIF($BC$5:BC15,AR$205:AR$236),0))} -> #N/A | BD16: {=INDEX(AM$205:AM$236,MATCH(0,COUNTIF($BD$5:BD15,AM$205:AM$236),0))} -> 0.456
C17: Victron Phoenix Inverter 48/375 230V VE.Direct UK | D17: 126.42 | E17: 119.07 | F17: =$D17/1.219 -> 103.70796 | G17: =IFERROR(ROUNDUP(F17*'Customer Base'!$J$5,2),0) -> 1731.93 | H17: =$E17/1.219 -> 97.678425 | I17: =IFERROR(ROUNDUP(H17*'Customer Base'!$J$5,2),0) -> 1631.23 | J17: =ROUNDUP((M17/$L$4)*$L$3*3,-1) -> 1200 | K17: Cape Coast | L17: =J17/'Customer Base'!$J$5 -> 71.856287 | M17: 114 | N17: 12 | O17: =IF('Customer Base'!$I$15="MANUAL",IF(B17<>"",C17,""),IF('Customer Base'!$I$15="AUTOMATE",IF(A17<>"",C17,""),"")) | P17: DECOMMISSIONING OF SOLAR SYSTEM | AM17: 0.375 | AN17: 48/375 | AO17: =IF('Customer Base'!$I$15="MANUAL",IFERROR(AM17*B17,""),IF('Customer Base'!$I$15="AUTOMATE",IFERROR(AM17*A17,""),"")) -> 0 | AQ17: 48 | AR17: Phoenix | AS17: 1 | AT17: =IF(AND(AR17=$AY$1,$AZ$1=AN17),BA$1,"") | AV17: =IF(AU17<>"",AU17,AT17) | AZ17: {=INDEX(AR$6:AR$132,MATCH(0,COUNTIF($AZ$5:AZ16,AR$6:AR$132),0))} -> Huawei | BA17: {=INDEX(AM$6:AM$161,MATCH(0,COUNTIF($BA$5:BA16,AM$6:AM$161),0))} -> 8 | BD17: {=INDEX(AM$205:AM$236,MATCH(0,COUNTIF($BD$5:BD16,AM$205:AM$236),0))} -> 0.72
A18: =IF(AND('Customer Base'!D$8=48,'Customer Base'!D$13="Victron",'Customer Base'!E$13="Phoenix",'Customer Base'!D$14>0,'Customer Base'!D$14<=0.5),'Customer Base'!D$15,IF(AND('Customer Base'!D$7="Mini-Grid",'Customer Base'!D$8=48,'Customer Base'!F$13="Victron",'Customer Base'!F$14>0,'Customer Base'!F$14<=0.5),'Customer Base'!F$15,"")) | C18: Victron Phoenix Inverter 48/500 230V VE.Direct UK | D18: 158.03 | E18: 148.846 | F18: =$D18/1.219 -> 129.63905 | G18: =IFERROR(ROUNDUP(F18*'Customer Base'!$J$5,2),0) -> 2164.98 | H18: =$E18/1.219 -> 122.105 | I18: =IFERROR(ROUNDUP(H18*'Customer Base'!$J$5,2),0) -> 2039.16 | J18: =ROUNDUP((M18/$L$4)*$L$3*3,-1) -> 2840 | K18: Ashanti Region | L18: =J18/'Customer Base'!$J$5 -> 170.05988 | M18: 270 | N18: 13 | O18: =IF('Customer Base'!$I$15="MANUAL",IF(B18<>"",C18,""),IF('Customer Base'!$I$15="AUTOMATE",IF(A18<>"",C18,""),"")) | P18: MAINTENANCE OF SOLAR SYSTEM | AM18: 0.5 | AN18: 48/500 | AO18: =IF('Customer Base'!$I$15="MANUAL",IFERROR(AM18*B18,""),IF('Customer Base'!$I$15="AUTOMATE",IFERROR(AM18*A18,""),"")) | AQ18: 48 | AR18: Phoenix | AS18: 1 | AT18: =IF(AND(AR18=$AY$1,$AZ$1=AN18),BA$1,"") | AV18: =IF(AU18<>"",AU18,AT18) | AZ18: {=INDEX(AR$6:AR$132,MATCH(0,COUNTIF($AZ$5:AZ17,AR$6:AR$132),0))} -> Galvo | BA18: {=INDEX(AM$6:AM$161,MATCH(0,COUNTIF($BA$5:BA17,AM$6:AM$161),0))} -> 10 | BD18: {=INDEX(AM$205:AM$236,MATCH(0,COUNTIF($BD$5:BD17,AM$205:AM$236),0))} -> 1.08 | BM18: =MIN(BN14:BO14) -> 85
A19: =IF(AND('Customer Base'!D$8=48,'Customer Base'!D$13="Victron",'Customer Base'!E$13="Phoenix",'Customer Base'!D$14>0.5,'Customer Base'!D$14<=0.8),'Customer Base'!D$15,IF(AND('Customer Base'!D$7="Mini-Grid",'Customer Base'!D$8=48,'Customer Base'!F$13="Victron",'Customer Base'!F$14>0.5,'Customer Base'!F$14<=0.8),'Customer Base'!F$15,"")) | C19: Victron Phoenix Inverter 48/800 230V VE.Direct UK | D19: 256.46 | E19: 241.542 | F19: =$D19/1.219 -> 210.38556 | G19: =IFERROR(ROUNDUP(F19*'Customer Base'!$J$5,2),0) -> 3513.44 | H19: =$E19/1.219 -> 198.14766 | I19: =IFERROR(ROUNDUP(H19*'Customer Base'!$J$5,2),0) -> 3309.07 | J19: =ROUNDUP((M19/$L$4)*$L$3*3,-1) -> 2840 | K19: Kumasi | L19: =J19/'Customer Base'!$J$5 -> 170.05988 | M19: 270 | N19: 14 | O19: =IF('Customer Base'!$I$15="MANUAL",IF(B19<>"",C19,""),IF('Customer Base'!$I$15="AUTOMATE",IF(A19<>"",C19,""),"")) | P19: SOLAR SYSTEM SUPPORT SERVICE | AM19: 0.8 | AN19: 48/800 | AO19: =IF('Customer Base'!$I$15="MANUAL",IFERROR(AM19*B19,""),IF('Customer Base'!$I$15="AUTOMATE",IFERROR(AM19*A19,""),"")) | AQ19: 48 | AR19: Phoenix | AS19: 1 | AT19: =IF(AND(AR19=$AY$1,$AZ$1=AN19),BA$1,"") | AV19: =IF(AU19<>"",AU19,AT19) | AZ19: {=INDEX(AR$6:AR$132,MATCH(0,COUNTIF($AZ$5:AZ18,AR$6:AR$132),0))} -> Primo | BA19: {=INDEX(AM$6:AM$161,MATCH(0,COUNTIF($BA$5:BA18,AM$6:AM$161),0))} -> 15 | BD19: {=INDEX(AM$205:AM$236,MATCH(0,COUNTIF($BD$5:BD18,AM$205:AM$236),0))} -> 1.32
A20: =IF(AND('Customer Base'!D$8=48,'Customer Base'!D$13="Victron",'Customer Base'!E$13="Phoenix",'Customer Base'!D$14>0.8,'Customer Base'!D$14<=1.2),'Customer Base'!D$15,IF(AND('Customer Base'!D$7="Mini-Grid",'Customer Base'!D$8=48,'Customer Base'!F$13="Victron",'Customer Base'!F$14>0.8,'Customer Base'!F$14<=1.2),'Customer Base'!F$15,"")) | C20: Victron Phoenix Inverter 48/1200 230V VE.Direct UK | D20: 338.63 | E20: 318.946 | F20: =$D20/1.219 -> 277.79327 | G20: =IFERROR(ROUNDUP(F20*'Customer Base'!$J$5,2),0) -> 4639.15 | H20: =$E20/1.219 -> 261.64561 | I20: =IFERROR(ROUNDUP(H20*'Customer Base'!$J$5,2),0) -> 4369.49 | J20: =ROUNDUP((M20/$L$4)*$L$3*3,-1) -> 1950 | K20: Volta Region | L20: =J20/'Customer Base'!$J$5 -> 116.76647 | M20: 185 | N20: 15 | O20: =IF('Customer Base'!$I$15="MANUAL",IF(B20<>"",C20,""),IF('Customer Base'!$I$15="AUTOMATE",IF(A20<>"",C20,""),"")) | P20: SYSTEM COMPONENT COSTS | AM20: 1.2 | AN20: 48/1200 | AO20: =IF('Customer Base'!$I$15="MANUAL",IFERROR(AM20*B20,""),IF('Customer Base'!$I$15="AUTOMATE",IFERROR(AM20*A20,""),"")) | AQ20: 48 | AR20: Phoenix | AS20: 1 | AT20: =IF(AND(AR20=$AY$1,$AZ$1=AN20),BA$1,"") | AV20: =IF(AU20<>"",AU20,AT20) | AZ20: {=INDEX(AR$6:AR$132,MATCH(0,COUNTIF($AZ$5:AZ19,AR$6:AR$132),0))} -> Symo | BA20: {=INDEX(AM$6:AM$161,MATCH(0,COUNTIF($BA$5:BA19,AM$6:AM$161),0))} -> 16 | BD20: {=INDEX(AM$205:AM$236,MATCH(0,COUNTIF($BD$5:BD19,AM$205:AM$236),0))} -> 2.64
A21: =IF(AND('Customer Base'!D$8=48,'Customer Base'!D$13="Victron",'Customer Base'!E$13="Phoenix",'Customer Base'!D$14>1.2,'Customer Base'!D$14<=1.6),'Customer Base'!D$15,IF(AND('Customer Base'!D$7="Mini-Grid",'Customer Base'!D$8=48,'Customer Base'!F$13="Victron",'Customer Base'!F$14>1.2,'Customer Base'!F$14<=1.6),'Customer Base'!F$15,"")) | C21: Victron Phoenix Inverter 48/1600 230V Smart | D21: 544.52 | E21: 512.86 | F21: =$D21/1.219 -> 446.69401 | G21: =IFERROR(ROUNDUP(F21*'Customer Base'!$J$5,2),0) -> 7459.79 | H21: =$E21/1.219 -> 420.7219 | I21: =IFERROR(ROUNDUP(H21*'Customer Base'!$J$5,2),0) -> 7026.06 | J21: =ROUNDUP((M21/$L$4)*$L$3*3,-1) -> 1950 | K21: Ho | L21: =J21/'Customer Base'!$J$5 -> 116.76647 | M21: 185 | N21: 16 | O21: =IF('Customer Base'!$I$15="MANUAL",IF(B21<>"",C21,""),IF('Customer Base'!$I$15="AUTOMATE",IF(A21<>"",C21,""),"")) | P21: BACKUP SYSTEM | AM21: 1.6 | AN21: 48/1600 | AO21: =IF('Customer Base'!$I$15="MANUAL",IFERROR(AM21*B21,""),IF('Customer Base'!$I$15="AUTOMATE",IFERROR(AM21*A21,""),"")) | AQ21: 48 | AR21: Phoenix | AS21: 1 | AT21: =IF(AND(AR21=$AY$1,$AZ$1=AN21),BA$1,"") | AV21: =IF(AU21<>"",AU21,AT21) | AZ21: {=INDEX(AR$6:AR$132,MATCH(0,COUNTIF($AZ$5:AZ20,AR$6:AR$132),0))} -> Eco | BA21: {=INDEX(AM$6:AM$161,MATCH(0,COUNTIF($BA$5:BA20,AM$6:AM$161),0))} -> 12 | BD21: {=INDEX(AM$205:AM$236,MATCH(0,COUNTIF($BD$5:BD20,AM$205:AM$236),0))} -> 2.4
A22: =IF(AND('Customer Base'!D$8=48,'Customer Base'!D$13="Victron",'Customer Base'!E$13="Phoenix",'Customer Base'!D$14>1.6,'Customer Base'!D$14<=2),'Customer Base'!D$15,IF(AND('Customer Base'!D$7="Mini-Grid",'Customer Base'!D$8=48,'Customer Base'!F$13="Victron",'Customer Base'!F$14>1.6,'Customer Base'!F$14<=2),'Customer Base'!F$15,"")) | C22: Victron Phoenix Inverter 48/2000 230V Smart | D22: 649.27 | E22: 611.518 | F22: =$D22/1.219 -> 532.6251 | G22: =IFERROR(ROUNDUP(F22*'Customer Base'!$J$5,2),0) -> 8894.84 | H22: =$E22/1.219 -> 501.65546 | I22: =IFERROR(ROUNDUP(H22*'Customer Base'!$J$5,2),0) -> 8377.65 | J22: =ROUNDUP((M22/$L$4)*$L$3*3,-1) -> 7480 | K22: Upper West Region | L22: =J22/'Customer Base'!$J$5 -> 447.90419 | M22: 712 | N22: 17 | O22: =IF('Customer Base'!$I$15="MANUAL",IF(B22<>"",C22,""),IF('Customer Base'!$I$15="AUTOMATE",IF(A22<>"",C22,""),"")) | P22: SOLAR STREET LIGHTS | AM22: 2 | AN22: 48/2000 | AO22: =IF('Customer Base'!$I$15="MANUAL",IFERROR(AM22*B22,""),IF('Customer Base'!$I$15="AUTOMATE",IFERROR(AM22*A22,""),"")) | AQ22: 48 | AR22: Phoenix | AS22: 1 | AT22: =IF(AND(AR22=$AY$1,$AZ$1=AN22),BA$1,"") | AV22: =IF(AU22<>"",AU22,AT22) | AZ22: {=INDEX(AR$6:AR$132,MATCH(0,COUNTIF($AZ$5:AZ21,AR$6:AR$132),0))} -> Verto | BA22: {=INDEX(AM$6:AM$161,MATCH(0,COUNTIF($BA$5:BA21,AM$6:AM$161),0))} -> 20 | BD22: {=INDEX(AM$205:AM$236,MATCH(0,COUNTIF($BD$5:BD21,AM$205:AM$236),0))} -> 26.3
A23: =IF(AND('Customer Base'!D$8=48,'Customer Base'!D$13="Victron",'Customer Base'!E$13="Phoenix",'Customer Base'!D$14>2,'Customer Base'!D$14<=3),'Customer Base'!D$15,IF(AND('Customer Base'!D$7="Mini-Grid",'Customer Base'!D$8=48,'Customer Base'!F$13="Victron",'Customer Base'!F$14>2,'Customer Base'!F$14<=3),'Customer Base'!F$15,"")) | C23: Victron Phoenix Inverter 48/3000 230V Smart | D23: 921.95 | E23: 868.352 | F23: =$D23/1.219 -> 756.31665 | G23: =IFERROR(ROUNDUP(F23*'Customer Base'!$J$5,2),0) -> 12630.49 | H23: =$E23/1.219 -> 712.34783 | I23: =IFERROR(ROUNDUP(H23*'Customer Base'!$J$5,2),0) -> 11896.21 | J23: =ROUNDUP((M23/$L$4)*$L$3*3,-1) -> 7480 | K23: Wa | L23: =J23/'Customer Base'!$J$5 -> 447.90419 | M23: 712 | N23: 18 | O23: =IF('Customer Base'!$I$15="MANUAL",IF(B23<>"",C23,""),IF('Customer Base'!$I$15="AUTOMATE",IF(A23<>"",C23,""),"")) | P23: SOLAR DC WATER PUMP PROJECT | AM23: 3 | AN23: 48/3000 | AO23: =IF('Customer Base'!$I$15="MANUAL",IFERROR(AM23*B23,""),IF('Customer Base'!$I$15="AUTOMATE",IFERROR(AM23*A23,""),"")) | AQ23: 48 | AR23: Phoenix | AS23: 1 | AT23: =IF(AND(AR23=$AY$1,$AZ$1=AN23),BA$1,"") | AV23: =IF(AU23<>"",AU23,AT23) | AZ23: {=INDEX(AR$6:AR$132,MATCH(0,COUNTIF($AZ$5:AZ22,AR$6:AR$132),0))} -> Tauro | BA23: {=INDEX(AM$6:AM$161,MATCH(0,COUNTIF($BA$5:BA22,AM$6:AM$161),0))} -> 30 | BD23: {=INDEX(AM$205:AM$236,MATCH(0,COUNTIF($BD$5:BD22,AM$205:AM$236),0))} -> 1.2
A24: =IF(AND('Customer Base'!D$8=48,'Customer Base'!D$13="Victron",'Customer Base'!E$13="Phoenix",'Customer Base'!D$14>3,'Customer Base'!D$14<=5),'Customer Base'!D$15,IF(AND('Customer Base'!D$7="Mini-Grid",'Customer Base'!D$8=48,'Customer Base'!F$13="Victron",'Customer Base'!F$14>3,'Customer Base'!F$14<=5),'Customer Base'!F$15,"")) | C24: Victron Phoenix Inverter 48/5000 230V Smart | D24: 1381.59 | E24: 1301.265 | F24: =$D24/1.219 -> 1133.3798 | G24: =IFERROR(ROUNDUP(F24*'Customer Base'!$J$5,2),0) -> 18927.45 | H24: =$E24/1.219 -> 1067.4856 | I24: =IFERROR(ROUNDUP(H24*'Customer Base'!$J$5,2),0) -> 17827.02 | J24: =ROUNDUP((M24/$L$4)*$L$3*3,-1) -> 4200 | K24: Bono Region | L24: =J24/'Customer Base'!$J$5 -> 251.49701 | M24: 400 | N24: 19 | O24: =IF('Customer Base'!$I$15="MANUAL",IF(B24<>"",C24,""),IF('Customer Base'!$I$15="AUTOMATE",IF(A24<>"",C24,""),"")) | AM24: 5 | AN24: 48/5000 | AO24: =IF('Customer Base'!$I$15="MANUAL",IFERROR(AM24*B24,""),IF('Customer Base'!$I$15="AUTOMATE",IFERROR(AM24*A24,""),"")) | AQ24: 48 | AR24: Phoenix | AS24: 1 | AT24: =IF(AND(AR24=$AY$1,$AZ$1=AN24),BA$1,"") | AV24: =IF(AU24<>"",AU24,AT24) | AZ24: {=INDEX(AR$6:AR$132,MATCH(0,COUNTIF($AZ$5:AZ23,AR$6:AR$132),0))} -> Gen_24_Primo | BA24: {=INDEX(AM$6:AM$161,MATCH(0,COUNTIF($BA$5:BA23,AM$6:AM$161),0))} -> 40 | BD24: {=INDEX(AM$205:AM$236,MATCH(0,COUNTIF($BD$5:BD23,AM$205:AM$236),0))} -> 1.8
F25: =$D25/1.219 -> 0 | G25: =IFERROR(ROUNDUP(F25*'Customer Base'!$J$5,2),0) -> 0 | H25: =$E25/1.219 -> 0 | I25: =IFERROR(ROUNDUP(H25*'Customer Base'!$J$5,2),0) -> 0 | J25: =ROUNDUP((M25/$L$4)*$L$3*3,-1) -> 4200 | K25: Sunyani | L25: =J25/'Customer Base'!$J$5 -> 251.49701 | M25: 400 | N25: 20 | O25: =IF('Customer Base'!$I$15="MANUAL",IF(B25<>"",C25,""),IF('Customer Base'!$I$15="AUTOMATE",IF(A25<>"",C25,""),"")) | AO25: =IF('Customer Base'!$I$15="MANUAL",IFERROR(AM25*B25,""),IF('Customer Base'!$I$15="AUTOMATE",IFERROR(AM25*A25,""),"")) -> 0 | AT25: =IF(AND(AR25=$AY$1,$AZ$1=AN25),BA$1,"") | AV25: =IF(AU25<>"",AU25,AT25) | BA25: {=INDEX(AM$6:AM$161,MATCH(0,COUNTIF($BA$5:BA24,AM$6:AM$161),0))} -> 50 | BD25: {=INDEX(AM$205:AM$236,MATCH(0,COUNTIF($BD$5:BD24,AM$205:AM$236),0))} -> 3
A26: =IF(AND('Customer Base'!D$8=12,'Customer Base'!D$13="Victron",'Customer Base'!E$13="Multiplus",'Customer Base'!D$14>0,'Customer Base'!D$14<=0.5),'Customer Base'!D$15,IF(AND('Customer Base'!D$7="Mini-Grid",'Customer Base'!D$8=12,'Customer Base'!F$13="Victron",'Customer Base'!F$14>0,'Customer Base'!F$14<=0.5),'Customer Base'!F$15,"")) | C26: Victron MultiPlus 12/500/20-16 230V VE.Bus | D26: 261.87 | E26: 246.645 | F26: =$D26/1.219 -> 214.82363 | G26: =IFERROR(ROUNDUP(F26*'Customer Base'!$J$5,2),0) -> 3587.56 | H26: =$E26/1.219 -> 202.33388 | I26: =IFERROR(ROUNDUP(H26*'Customer Base'!$J$5,2),0) -> 3378.98 | J26: =ROUNDUP((M26/$L$4)*$L$3*3,-1) -> 4070 | K26: Ahafo Region | L26: =J26/'Customer Base'!$J$5 -> 243.71257 | M26: 387 | N26: 21 | O26: =IF('Customer Base'!$I$15="MANUAL",IF(B26<>"",C26,""),IF('Customer Base'!$I$15="AUTOMATE",IF(A26<>"",C26,""),"")) | AM26: 0.5 | AN26: 12/500 | AO26: =IF('Customer Base'!$I$15="MANUAL",IFERROR(AM26*B26,""),IF('Customer Base'!$I$15="AUTOMATE",IFERROR(AM26*A26,""),"")) | AQ26: 12 | AR26: Multiplus | AS26: 1 | AT26: =IF(AND(AR26=$AY$1,$AZ$1=AN26),BA$1,"") | AV26: =IF(AU26<>"",AU26,AT26) | AW26: 20 | BA26: {=INDEX(AM$6:AM$161,MATCH(0,COUNTIF($BA$5:BA25,AM$6:AM$161),0))} -> 8.2 | BD26: {=INDEX(AM$205:AM$236,MATCH(0,COUNTIF($BD$5:BD25,AM$205:AM$236),0))} -> #N/A
A27: =IF(AND('Customer Base'!D$8=12,'Customer Base'!D$13="Victron",'Customer Base'!E$13="Multiplus",'Customer Base'!D$14>0.5,'Customer Base'!D$14<=0.8),'Customer Base'!D$15,IF(AND('Customer Base'!D$7="Mini-Grid",'Customer Base'!D$8=12,'Customer Base'!F$13="Victron",'Customer Base'!F$14>0.5,'Customer Base'!F$14<=0.8),'Customer Base'!F$15,"")) | C27: Victron MultiPlus 12/800/35-16 230V VE.Bus | D27: 307.91 | E27: 290.012 | F27: =$D27/1.219 -> 252.59229 | G27: =IFERROR(ROUNDUP(F27*'Customer Base'!$J$5,2),0) -> 4218.3 | H27: =$E27/1.219 -> 237.90976 | I27: =IFERROR(ROUNDUP(H27*'Customer Base'!$J$5,2),0) -> 3973.1 | J27: =ROUNDUP((M27/$L$4)*$L$3*3,-1) -> 4070 | K27: Goaso | L27: =J27/'Customer Base'!$J$5 -> 243.71257 | M27: 387 | N27: 22 | O27: =IF('Customer Base'!$I$15="MANUAL",IF(B27<>"",C27,""),IF('Customer Base'!$I$15="AUTOMATE",IF(A27<>"",C27,""),"")) | AM27: 0.8 | AN27: 12/800 | AO27: =IF('Customer Base'!$I$15="MANUAL",IFERROR(AM27*B27,""),IF('Customer Base'!$I$15="AUTOMATE",IFERROR(AM27*A27,""),"")) | AQ27: 12 | AR27: Multiplus | AS27: 1 | AT27: =IF(AND(AR27=$AY$1,$AZ$1=AN27),BA$1,"") | AV27: =IF(AU27<>"",AU27,AT27) | AW27: 35 | BA27: {=INDEX(AM$6:AM$161,MATCH(0,COUNTIF($BA$5:BA26,AM$6:AM$161),0))} -> 25 | BD27: {=INDEX(AM$205:AM$236,MATCH(0,COUNTIF($BD$5:BD26,AM$205:AM$236),0))} -> #N/A
A28: =IF(AND('Customer Base'!D$8=12,'Customer Base'!D$13="Victron",'Customer Base'!E$13="Multiplus",'Customer Base'!D$14>0.8,'Customer Base'!D$14<=1.2),'Customer Base'!D$15,IF(AND('Customer Base'!D$7="Mini-Grid",'Customer Base'!D$8=12,'Customer Base'!F$13="Victron",'Customer Base'!F$14>0.8,'Customer Base'!F$14<=1.2),'Customer Base'!F$15,"")) | C28: Victron MultiPlus 12/1200/50-16 230V VE.Bus | D28: 429.83 | E28: 404.838 | F28: =$D28/1.219 -> 352.6087 | G28: =IFERROR(ROUNDUP(F28*'Customer Base'!$J$5,2),0) -> 5888.57 | H28: =$E28/1.219 -> 332.10664 | I28: =IFERROR(ROUNDUP(H28*'Customer Base'!$J$5,2),0) -> 5546.19 | J28: =ROUNDUP((M28/$L$4)*$L$3*3,-1) -> 3590 | K28: Oti Region | L28: =J28/'Customer Base'!$J$5 -> 214.97006 | M28: 341 | N28: 23 | O28: =IF('Customer Base'!$I$15="MANUAL",IF(B28<>"",C28,""),IF('Customer Base'!$I$15="AUTOMATE",IF(A28<>"",C28,""),"")) | AM28: 1.2 | AN28: 12/1200 | AO28: =IF('Customer Base'!$I$15="MANUAL",IFERROR(AM28*B28,""),IF('Customer Base'!$I$15="AUTOMATE",IFERROR(AM28*A28,""),"")) | AQ28: 12 | AR28: Multiplus | AS28: 1 | AT28: =IF(AND(AR28=$AY$1,$AZ$1=AN28),BA$1,"") | AV28: =IF(AU28<>"",AU28,AT28) | AW28: 50 | BA28: {=INDEX(AM$6:AM$161,MATCH(0,COUNTIF($BA$5:BA27,AM$6:AM$161),0))} -> 27 | BD28: {=INDEX(AM$205:AM$236,MATCH(0,COUNTIF($BD$5:BD27,AM$205:AM$236),0))} -> #N/A
C29: Victron MultiPlus 12/1600/70-16 230V VE.Bus | D29: 488.51 | E29: 460.112 | F29: =$D29/1.219 -> 400.74651 | G29: =IFERROR(ROUNDUP(F29*'Customer Base'!$J$5,2),0) -> 6692.47 | H29: =$E29/1.219 -> 377.45037 | I29: =IFERROR(ROUNDUP(H29*'Customer Base'!$J$5,2),0) -> 6303.43 | J29: =ROUNDUP((M29/$L$4)*$L$3*3,-1) -> 3590 | K29: Dambai | L29: =J29/'Customer Base'!$J$5 -> 214.97006 | M29: 341 | N29: 24 | O29: =IF('Customer Base'!$I$15="MANUAL",IF(B29<>"",C29,""),IF('Customer Base'!$I$15="AUTOMATE",IF(A29<>"",C29,""),"")) | P29: ="Backup System with "&'Customer Base'!$J$7&"kVA inverter, "&'Customer Base'!$J$8&"kWh Battery, "&"and Remote Monitoring" -> Backup System with 5kVA inverter, 10kWh Battery, and Remote Monitoring | AM29: 1.6 | AN29: 12/1600 | AO29: =IF('Customer Base'!$I$15="MANUAL",IFERROR(AM29*B29,""),IF('Customer Base'!$I$15="AUTOMATE",IFERROR(AM29*A29,""),"")) -> 0 | AQ29: 12 | AR29: Multiplus | AS29: 1 | AT29: =IF(AND(AR29=$AY$1,$AZ$1=AN29),BA$1,"") | AV29: =IF(AU29<>"",AU29,AT29) | AW29: 70 | BA29: {=INDEX(AM$6:AM$161,MATCH(0,COUNTIF($BA$5:BA28,AM$6:AM$161),0))} -> 33.3 | BD29: {=INDEX(AM$205:AM$236,MATCH(0,COUNTIF($BD$5:BD28,AM$205:AM$236),0))} -> #N/A
C30: Victron MultiPlus 12/2000/80-32 230V VE.Bus | D30: 544.51 | E30: 512.86 | F30: =$D30/1.219 -> 446.68581 | G30: =IFERROR(ROUNDUP(F30*'Customer Base'!$J$5,2),0) -> 7459.66 | H30: =$E30/1.219 -> 420.7219 | I30: =IFERROR(ROUNDUP(H30*'Customer Base'!$J$5,2),0) -> 7026.06 | J30: =ROUNDUP((M30/$L$4)*$L$3*3,-1) -> 4180 | K30: Bono East Region | L30: =J30/'Customer Base'!$J$5 -> 250.2994 | M30: 398 | N30: 25 | O30: =IF('Customer Base'!$I$15="MANUAL",IF(B30<>"",C30,""),IF('Customer Base'!$I$15="AUTOMATE",IF(A30<>"",C30,""),"")) | P30: ="Grid-Tied Solar System with "&'Customer Base'!$J$7&"kVA inverter, "&'Customer Base'!$J$9&"kWp Solar Panels and Remote Monitoring" -> Grid-Tied Solar System with 5kVA inverter, 5.085kWp Solar Panels and Remote Monitoring | AM30: 2 | AN30: 12/2000 | AO30: =IF('Customer Base'!$I$15="MANUAL",IFERROR(AM30*B30,""),IF('Customer Base'!$I$15="AUTOMATE",IFERROR(AM30*A30,""),"")) -> 0 | AQ30: 12 | AR30: Multiplus | AS30: 1 | AT30: =IF(AND(AR30=$AY$1,$AZ$1=AN30),BA$1,"") | AV30: =IF(AU30<>"",AU30,AT30) | AW30: 80 | BA30: {=INDEX(AM$6:AM$161,MATCH(0,COUNTIF($BA$5:BA29,AM$6:AM$161),0))} -> 100 | BD30: {=INDEX(AM$205:AM$236,MATCH(0,COUNTIF($BD$5:BD29,AM$205:AM$236),0))} -> #N/A
A31: =IF(AND('Customer Base'!D$8=24,'Customer Base'!D$13="Victron",'Customer Base'!E$13="Multiplus",'Customer Base'!D$14>0,'Customer Base'!D$14<=0.5),'Customer Base'!D$15,IF(AND('Customer Base'!D$7="Mini-Grid",'Customer Base'!D$8=24,'Customer Base'!F$13="Victron",'Customer Base'!F$14>0,'Customer Base'!F$14<=0.5),'Customer Base'!F$15,"")) | C31: Victron MultiPlus 24/500/20-16 230V VE.Bus | D31: 261 | E31: 246.645 | F31: =$D31/1.219 -> 214.10993 | G31: =IFERROR(ROUNDUP(F31*'Customer Base'!$J$5,2),0) -> 3575.64 | H31: =$E31/1.219 -> 202.33388 | I31: =IFERROR(ROUNDUP(H31*'Customer Base'!$J$5,2),0) -> 3378.98 | J31: =ROUNDUP((M31/$L$4)*$L$3*3,-1) -> 4180 | K31: Techiman | L31: =J31/'Customer Base'!$J$5 -> 250.2994 | M31: 398 | N31: 26 | O31: =IF('Customer Base'!$I$15="MANUAL",IF(B31<>"",C31,""),IF('Customer Base'!$I$15="AUTOMATE",IF(A31<>"",C31,""),"")) | P31: ="Hybrid Solar System with "&'Customer Base'!$J$7&"kVA inverter, "&'Customer Base'!$J$8&"kWh Battery, "&'Customer Base'!$J$9&"kWp Solar Panels and Remote Monitoring" -> Hybrid Solar System with 5kVA inverter, 10kWh Battery, 5.085kWp Solar Panels and Remote Monitoring | AM31: 0.5 | AN31: 24/500 | AO31: =IF('Customer Base'!$I$15="MANUAL",IFERROR(AM31*B31,""),IF('Customer Base'!$I$15="AUTOMATE",IFERROR(AM31*A31,""),"")) | AQ31: 24 | AR31: Multiplus | AS31: 1 | AT31: =IF(AND(AR31=$AY$1,$AZ$1=AN31),BA$1,"") | AV31: =IF(AU31<>"",AU31,AT31) | AW31: 20 | BA31: {=INDEX(AM$6:AM$161,MATCH(0,COUNTIF($BA$5:BA30,AM$6:AM$161),0))} -> 4 | BD31: {=INDEX(AM$205:AM$236,MATCH(0,COUNTIF($BD$5:BD30,AM$205:AM$236),0))} -> #N/A
A32: =IF(AND('Customer Base'!D$8=24,'Customer Base'!D$13="Victron",'Customer Base'!E$13="Multiplus",'Customer Base'!D$14>0.5,'Customer Base'!D$14<=0.8),'Customer Base'!D$15,IF(AND('Customer Base'!D$7="Mini-Grid",'Customer Base'!D$8=24,'Customer Base'!F$13="Victron",'Customer Base'!F$14>0.5,'Customer Base'!F$14<=0.8),'Customer Base'!F$15,"")) | C32: Victron MultiPlus 24/800/35-16 230V VE.Bus | D32: 307.91 | E32: 290.012 | F32: =$D32/1.219 -> 252.59229 | G32: =IFERROR(ROUNDUP(F32*'Customer Base'!$J$5,2),0) -> 4218.3 | H32: =$E32/1.219 -> 237.90976 | I32: =IFERROR(ROUNDUP(H32*'Customer Base'!$J$5,2),0) -> 3973.1 | J32: =ROUNDUP((M32/$L$4)*$L$3*3,-1) -> 6790 | K32: North East Region | L32: =J32/'Customer Base'!$J$5 -> 406.58683 | M32: 646 | N32: 27 | O32: =IF('Customer Base'!$I$15="MANUAL",IF(B32<>"",C32,""),IF('Customer Base'!$I$15="AUTOMATE",IF(A32<>"",C32,""),"")) | P32: ="Hybrid Solar System with "&'Customer Base'!$J$7&"kVA inverter, "&'Customer Base'!$J$8&"kWh Battery, and "&'Customer Base'!$J$9&"kWp Solar Panels" -> Hybrid Solar System with 5kVA inverter, 10kWh Battery, and 5.085kWp Solar Panels | AM32: 0.8 | AN32: 24/800 | AO32: =IF('Customer Base'!$I$15="MANUAL",IFERROR(AM32*B32,""),IF('Customer Base'!$I$15="AUTOMATE",IFERROR(AM32*A32,""),"")) | AQ32: 24 | AR32: Multiplus | AS32: 1 | AT32: =IF(AND(AR32=$AY$1,$AZ$1=AN32),BA$1,"") | AV32: =IF(AU32<>"",AU32,AT32) | AW32: 35 | BA32: {=INDEX(AM$6:AM$161,MATCH(0,COUNTIF($BA$5:BA31,AM$6:AM$161),0))} -> #N/A | BD32: {=INDEX(AM$205:AM$236,MATCH(0,COUNTIF($BD$5:BD31,AM$205:AM$236),0))} -> #N/A
A33: =IF(AND('Customer Base'!D$8=24,'Customer Base'!D$13="Victron",'Customer Base'!E$13="Multiplus",'Customer Base'!D$14>0.8,'Customer Base'!D$14<=1.2),'Customer Base'!D$15,IF(AND('Customer Base'!D$7="Mini-Grid",'Customer Base'!D$8=24,'Customer Base'!F$13="Victron",'Customer Base'!F$14>0.8,'Customer Base'!F$14<=1.2),'Customer Base'!F$15,"")) | C33: Victron MultiPlus 24/1200/50-16 230V VE.Bus | D33: 429.83 | E33: 404.838 | F33: =$D33/1.219 -> 352.6087 | G33: =IFERROR(ROUNDUP(F33*'Customer Base'!$J$5,2),0) -> 5888.57 | H33: =$E33/1.219 -> 332.10664 | I33: =IFERROR(ROUNDUP(H33*'Customer Base'!$J$5,2),0) -> 5546.19 | J33: =ROUNDUP((M33/$L$4)*$L$3*3,-1) -> 6790 | K33: Nalerigu | L33: =J33/'Customer Base'!$J$5 -> 406.58683 | M33: 646 | N33: 28 | O33: =IF('Customer Base'!$I$15="MANUAL",IF(B33<>"",C33,""),IF('Customer Base'!$I$15="AUTOMATE",IF(A33<>"",C33,""),"")) | P33: ="Mini-grid Solar System with "&'Customer Base'!$J$7&"kVA inverter, "&'Customer Base'!$J$8&"kWh Battery, "&'Customer Base'!$J$9&"kWp Solar Panels and Remote Monitoring" -> Mini-grid Solar System with 5kVA inverter, 10kWh Battery, 5.085kWp Solar Panels and Remote Monitoring | AM33: 1.2 | AN33: 24/1200 | AO33: =IF('Customer Base'!$I$15="MANUAL",IFERROR(AM33*B33,""),IF('Customer Base'!$I$15="AUTOMATE",IFERROR(AM33*A33,""),"")) | AQ33: 24 | AR33: Multiplus | AS33: 1 | AT33: =IF(AND(AR33=$AY$1,$AZ$1=AN33),BA$1,"") | AV33: =IF(AU33<>"",AU33,AT33) | AW33: 50 | BD33: {=INDEX(AM$205:AM$236,MATCH(0,COUNTIF($BD$5:BD32,AM$205:AM$236),0))} -> #N/A
A34: =IF(AND('Customer Base'!D$8=24,'Customer Base'!D$13="Victron",'Customer Base'!E$13="Multiplus",'Customer Base'!D$14>1.2,'Customer Base'!D$14<=1.6),'Customer Base'!D$15,IF(AND('Customer Base'!D$7="Mini-Grid",'Customer Base'!D$8=24,'Customer Base'!F$13="Victron",'Customer Base'!F$14>1.2,'Customer Base'!F$14<=1.6),'Customer Base'!F$15,"")) | C34: Victron MultiPlus 24/1600/70-16 230V VE.Bus | D34: 488.51 | E34: 460.112 | F34: =$D34/1.219 -> 400.74651 | G34: =IFERROR(ROUNDUP(F34*'Customer Base'!$J$5,2),0) -> 6692.47 | H34: =$E34/1.219 -> 377.45037 | I34: =IFERROR(ROUNDUP(H34*'Customer Base'!$J$5,2),0) -> 6303.43 | J34: =ROUNDUP((M34/$L$4)*$L$3*3,-1) -> 8220 | K34: Savanna Region | L34: =J34/'Customer Base'!$J$5 -> 492.21557 | M34: 782 | N34: 29 | O34: =IF('Customer Base'!$I$15="MANUAL",IF(B34<>"",C34,""),IF('Customer Base'!$I$15="AUTOMATE",IF(A34<>"",C34,""),"")) | AM34: 1.6 | AN34: 24/1600 | AO34: =IF('Customer Base'!$I$15="MANUAL",IFERROR(AM34*B34,""),IF('Customer Base'!$I$15="AUTOMATE",IFERROR(AM34*A34,""),"")) | AQ34: 24 | AR34: Multiplus | AS34: 1 | AT34: =IF(AND(AR34=$AY$1,$AZ$1=AN34),BA$1,"") | AV34: =IF(AU34<>"",AU34,AT34) | AW34: 70 | BD34: {=INDEX(AM$205:AM$236,MATCH(0,COUNTIF($BD$5:BD33,AM$205:AM$236),0))} -> #N/A
A35: =IF(AND('Customer Base'!D$8=24,'Customer Base'!D$13="Victron",'Customer Base'!E$13="Multiplus",'Customer Base'!D$14>1.6,'Customer Base'!D$14<=2),'Customer Base'!D$15,IF(AND('Customer Base'!D$7="Mini-Grid",'Customer Base'!D$8=24,'Customer Base'!F$13="Victron",'Customer Base'!F$14>1.6,'Customer Base'!F$14<=2),'Customer Base'!F$15,"")) | C35: Victron MultiPlus 24/2000/80-32 230V VE.Bus | D35: 544.51 | E35: 512.86 | F35: =$D35/1.219 -> 446.68581 | G35: =IFERROR(ROUNDUP(F35*'Customer Base'!$J$5,2),0) -> 7459.66 | H35: =$E35/1.219 -> 420.7219 | I35: =IFERROR(ROUNDUP(H35*'Customer Base'!$J$5,2),0) -> 7026.06 | J35: =ROUNDUP((M35/$L$4)*$L$3*3,-1) -> 8220 | K35: Damango | L35: =J35/'Customer Base'!$J$5 -> 492.21557 | M35: 782 | N35: 30 | O35: =IF('Customer Base'!$I$15="MANUAL",IF(B35<>"",C35,""),IF('Customer Base'!$I$15="AUTOMATE",IF(A35<>"",C35,""),"")) | AM35: 2 | AN35: 24/2000 | AO35: =IF('Customer Base'!$I$15="MANUAL",IFERROR(AM35*B35,""),IF('Customer Base'!$I$15="AUTOMATE",IFERROR(AM35*A35,""),"")) | AQ35: 24 | AR35: Multiplus | AS35: 1 | AT35: =IF(AND(AR35=$AY$1,$AZ$1=AN35),BA$1,"") | AV35: =IF(AU35<>"",AU35,AT35) | AW35: 80 | BD35: {=INDEX(AM$205:AM$236,MATCH(0,COUNTIF($BD$5:BD34,AM$205:AM$236),0))} -> #N/A
C36: Victron MultiPlus 24/3000/35-50 230V VE.Bus | D36: 1293.1 | E36: 1217.916 | F36: =$D36/1.219 -> 1060.7875 | G36: =IFERROR(ROUNDUP(F36*'Customer Base'!$J$5,2),0) -> 17715.16 | H36: =$E36/1.219 -> 999.11075 | I36: =IFERROR(ROUNDUP(H36*'Customer Base'!$J$5,2),0) -> 16685.15 | J36: =ROUNDUP((M36/$L$4)*$L$3*3,-1) -> 6600 | K36: Northern Region | L36: =J36/'Customer Base'!$J$5 -> 395.20958 | M36: 628 | N36: 31 | O36: =IF('Customer Base'!$I$15="MANUAL",IF(B36<>"",C36,""),IF('Customer Base'!$I$15="AUTOMATE",IF(A36<>"",C36,""),"")) | AM36: 3 | AN36: 24/3000/70-50 | AO36: =IF('Customer Base'!$I$15="MANUAL",IFERROR(AM36*B36,""),IF('Customer Base'!$I$15="AUTOMATE",IFERROR(AM36*A36,""),"")) -> 0 | AQ36: 24 | AR36: Multiplus | AS36: 1 | AT36: =IF(AND(AR36=$AY$1,$AZ$1=AN36),BA$1,"") | AV36: =IF(AU36<>"",AU36,AT36) | AW36: 70
A37: =IF(AND('Customer Base'!D$8=48,'Customer Base'!D$13="Victron",'Customer Base'!E$13="Multiplus",'Customer Base'!D$14>0,'Customer Base'!D$14<=0.5),'Customer Base'!D$15,IF(AND('Customer Base'!D$7="Mini-Grid",'Customer Base'!D$8=48,'Customer Base'!F$13="Victron",'Customer Base'!F$14>0,'Customer Base'!F$14<=0.5),'Customer Base'!F$15,"")) | C37: Victron MultiPlus 48/500/6-16 230V VE.Bus | D37: 261 | E37: 246.645 | F37: =$D37/1.219 -> 214.10993 | G37: =IFERROR(ROUNDUP(F37*'Customer Base'!$J$5,2),0) -> 3575.64 | H37: =$E37/1.219 -> 202.33388 | I37: =IFERROR(ROUNDUP(H37*'Customer Base'!$J$5,2),0) -> 3378.98 | J37: =ROUNDUP((M37/$L$4)*$L$3*3,-1) -> 6600 | K37: Tamale | L37: =J37/'Customer Base'!$J$5 -> 395.20958 | M37: 628 | N37: 32 | O37: =IF('Customer Base'!$I$15="MANUAL",IF(B37<>"",C37,""),IF('Customer Base'!$I$15="AUTOMATE",IF(A37<>"",C37,""),"")) | AM37: 0.5 | AN37: 48/500 | AO37: =IF('Customer Base'!$I$15="MANUAL",IFERROR(AM37*B37,""),IF('Customer Base'!$I$15="AUTOMATE",IFERROR(AM37*A37,""),"")) | AQ37: 48 | AR37: Multiplus | AS37: 1 | AT37: =IF(AND(AR37=$AY$1,$AZ$1=AN37),BA$1,"") | AV37: =IF(AU37<>"",AU37,AT37) | AW37: 6
A38: =IF(AND('Customer Base'!D$8=48,'Customer Base'!D$13="Victron",'Customer Base'!E$13="Multiplus",'Customer Base'!D$14>0.5,'Customer Base'!D$14<=0.8),'Customer Base'!D$15,IF(AND('Customer Base'!D$7="Mini-Grid",'Customer Base'!D$8=48,'Customer Base'!F$13="Victron",'Customer Base'!F$14>0.5,'Customer Base'!F$14<=0.8),'Customer Base'!F$15,"")) | C38: Victron MultiPlus 48/800/9-16 230V VE.Bus | D38: 307.91 | E38: 290.012 | F38: =$D38/1.219 -> 252.59229 | G38: =IFERROR(ROUNDUP(F38*'Customer Base'!$J$5,2),0) -> 4218.3 | H38: =$E38/1.219 -> 237.90976 | I38: =IFERROR(ROUNDUP(H38*'Customer Base'!$J$5,2),0) -> 3973.1 | L38: =IF(H38>F38,"lkkajdfkj","") | N38: 33 | O38: =IF('Customer Base'!$I$15="MANUAL",IF(B38<>"",C38,""),IF('Customer Base'!$I$15="AUTOMATE",IF(A38<>"",C38,""),"")) | AM38: 0.8 | AN38: 48/800 | AO38: =IF('Customer Base'!$I$15="MANUAL",IFERROR(AM38*B38,""),IF('Customer Base'!$I$15="AUTOMATE",IFERROR(AM38*A38,""),"")) | AQ38: 48 | AR38: Multiplus | AS38: 1 | AT38: =IF(AND(AR38=$AY$1,$AZ$1=AN38),BA$1,"") | AV38: =IF(AU38<>"",AU38,AT38) | AW38: 9
A39: =IF(AND('Customer Base'!D$8=48,'Customer Base'!D$13="Victron",'Customer Base'!E$13="Multiplus",'Customer Base'!D$14>0.8,'Customer Base'!D$14<=1.2),'Customer Base'!D$15,IF(AND('Customer Base'!D$7="Mini-Grid",'Customer Base'!D$8=48,'Customer Base'!F$13="Victron",'Customer Base'!F$14>0.8,'Customer Base'!F$14<=1.2),'Customer Base'!F$15,"")) | C39: Victron MultiPlus 48/1200/13-16 230V VE.Bus | D39: 429.83 | E39: 404.838 | F39: =$D39/1.219 -> 352.6087 | G39: =IFERROR(ROUNDUP(F39*'Customer Base'!$J$5,2),0) -> 5888.57 | H39: =$E39/1.219 -> 332.10664 | I39: =IFERROR(ROUNDUP(H39*'Customer Base'!$J$5,2),0) -> 5546.19 | L39: =IF(H39>F39,"lkkajdfkj","") | N39: 34 | O39: =IF('Customer Base'!$I$15="MANUAL",IF(B39<>"",C39,""),IF('Customer Base'!$I$15="AUTOMATE",IF(A39<>"",C39,""),"")) | AM39: 1.2 | AN39: 48/1200 | AO39: =IF('Customer Base'!$I$15="MANUAL",IFERROR(AM39*B39,""),IF('Customer Base'!$I$15="AUTOMATE",IFERROR(AM39*A39,""),"")) | AQ39: 48 | AR39: Multiplus | AS39: 1 | AT39: =IF(AND(AR39=$AY$1,$AZ$1=AN39),BA$1,"") | AV39: =IF(AU39<>"",AU39,AT39) | AW39: 13
A40: =IF(AND('Customer Base'!D$8=48,'Customer Base'!D$13="Victron",'Customer Base'!E$13="Multiplus",'Customer Base'!D$14>1.2,'Customer Base'!D$14<=1.6),'Customer Base'!D$15,IF(AND('Customer Base'!D$7="Mini-Grid",'Customer Base'!D$8=48,'Customer Base'!F$13="Victron",'Customer Base'!F$14>1.2,'Customer Base'!F$14<=1.6),'Customer Base'!F$15,"")) | C40: Victron MultiPlus 48/1600/20-16 230V VE.Bus | D40: 488.51 | E40: 460.112 | F40: =$D40/1.219 -> 400.74651 | G40: =IFERROR(ROUNDUP(F40*'Customer Base'!$J$5,2),0) -> 6692.47 | H40: =$E40/1.219 -> 377.45037 | I40: =IFERROR(ROUNDUP(H40*'Customer Base'!$J$5,2),0) -> 6303.43 | L40: =IF(H40>F40,"lkkajdfkj","") | N40: 35 | O40: =IF('Customer Base'!$I$15="MANUAL",IF(B40<>"",C40,""),IF('Customer Base'!$I$15="AUTOMATE",IF(A40<>"",C40,""),"")) | AM40: 1.6 | AN40: 48/1600 | AO40: =IF('Customer Base'!$I$15="MANUAL",IFERROR(AM40*B40,""),IF('Customer Base'!$I$15="AUTOMATE",IFERROR(AM40*A40,""),"")) | AQ40: 48 | AR40: Multiplus | AS40: 1 | AT40: =IF(AND(AR40=$AY$1,$AZ$1=AN40),BA$1,"") | AV40: =IF(AU40<>"",AU40,AT40) | AW40: 20
A41: =IF(AND('Customer Base'!D$8=48,'Customer Base'!D$13="Victron",'Customer Base'!E$13="Multiplus",'Customer Base'!D$14>1.6,'Customer Base'!D$14<=2),'Customer Base'!D$15,IF(AND('Customer Base'!D$7="Mini-Grid",'Customer Base'!D$8=48,'Customer Base'!F$13="Victron",'Customer Base'!F$14>1.6,'Customer Base'!F$14<=2),'Customer Base'!F$15,"")) | C41: Victron MultiPlus 48/2000/25-32 230V VE.Bus | D41: 544.51 | E41: 512.86 | F41: =$D41/1.219 -> 446.68581 | G41: =IFERROR(ROUNDUP(F41*'Customer Base'!$J$5,2),0) -> 7459.66 | H41: =$E41/1.219 -> 420.7219 | I41: =IFERROR(ROUNDUP(H41*'Customer Base'!$J$5,2),0) -> 7026.06 | L41: =IF(H41>F41,"lkkajdfkj","") | N41: 36 | O41: =IF('Customer Base'!$I$15="MANUAL",IF(B41<>"",C41,""),IF('Customer Base'!$I$15="AUTOMATE",IF(A41<>"",C41,""),"")) | AM41: 2 | AN41: 48/2000 | AO41: =IF('Customer Base'!$I$15="MANUAL",IFERROR(AM41*B41,""),IF('Customer Base'!$I$15="AUTOMATE",IFERROR(AM41*A41,""),"")) | AQ41: 48 | AR41: Multiplus | AS41: 1 | AT41: =IF(AND(AR41=$AY$1,$AZ$1=AN41),BA$1,"") | AV41: =IF(AU41<>"",AU41,AT41) | AW41: 25
C42: Victron MultiPlus 48/3000/35-16 230V VE.Bus | D42: 829.87 | E42: 781.618 | F42: =$D42/1.219 -> 680.77933 | G42: =IFERROR(ROUNDUP(F42*'Customer Base'!$J$5,2),0) -> 11369.02 | H42: =$E42/1.219 -> 641.19606 | I42: =IFERROR(ROUNDUP(H42*'Customer Base'!$J$5,2),0) -> 10707.98 | L42: =IF(H42>F42,"lkkajdfkj","") | N42: 37 | O42: =IF('Customer Base'!$I$15="MANUAL",IF(B42<>"",C42,""),IF('Customer Base'!$I$15="AUTOMATE",IF(A42<>"",C42,""),"")) | AM42: 3 | AN42: 48/3000/35-16 | AO42: =IF('Customer Base'!$I$15="MANUAL",IFERROR(AM42*B42,""),IF('Customer Base'!$I$15="AUTOMATE",IFERROR(AM42*A42,""),"")) -> 0 | AQ42: 48 | AR42: Multiplus | AS42: 1 | AT42: =IF(AND(AR42=$AY$1,$AZ$1=AN42),BA$1,"") | AV42: =IF(AU42<>"",AU42,AT42) | AW42: 35
C43: Victron MultiPlus 48/3000/35-50 230V VE.Bus | D43: 865.99 | E43: 815.638 | F43: =$D43/1.219 -> 710.41017 | G43: =IFERROR(ROUNDUP(F43*'Customer Base'!$J$5,2),0) -> 11863.85 | H43: =$E43/1.219 -> 669.10418 | I43: =IFERROR(ROUNDUP(H43*'Customer Base'!$J$5,2),0) -> 11174.04 | L43: =IF(H43>F43,"lkkajdfkj","") | N43: 38 | O43: =IF('Customer Base'!$I$15="MANUAL",IF(B43<>"",C43,""),IF('Customer Base'!$I$15="AUTOMATE",IF(A43<>"",C43,""),"")) | AM43: 3 | AN43: 48/3000/35-50 | AO43: =IF('Customer Base'!$I$15="MANUAL",IFERROR(AM43*B43,""),IF('Customer Base'!$I$15="AUTOMATE",IFERROR(AM43*A43,""),"")) -> 0 | AQ43: 48 | AR43: Multiplus | AS43: 1 | AT43: =IF(AND(AR43=$AY$1,$AZ$1=AN43),BA$1,"") -> 1 | AV43: =IF(AU43<>"",AU43,AT43) -> 1 | AW43: 35
C44: Victron MultiPlus 48/5000/70-100 230V VE.Bus | D44: 1174.79 | E44: 1106.492 | F44: =$D44/1.219 -> 963.73257 | G44: =IFERROR(ROUNDUP(F44*'Customer Base'!$J$5,2),0) -> 16094.34 | H44: =$E44/1.219 -> 907.70468 | I44: =IFERROR(ROUNDUP(H44*'Customer Base'!$J$5,2),0) -> 15158.67 | L44: =IF(H44>F44,"lkkajdfkj","") | N44: 39 | O44: =IF('Customer Base'!$I$15="MANUAL",IF(B44<>"",C44,""),IF('Customer Base'!$I$15="AUTOMATE",IF(A44<>"",C44,""),"")) | AM44: 5 | AN44: 48/5000 | AO44: =IF('Customer Base'!$I$15="MANUAL",IFERROR(AM44*B44,""),IF('Customer Base'!$I$15="AUTOMATE",IFERROR(AM44*A44,""),"")) -> 0 | AQ44: 48 | AR44: Multiplus | AS44: 1 | AT44: =IF(AND(AR44=$AY$1,$AZ$1=AN44),BA$1,"") | AV44: =IF(AU44<>"",AU44,AT44) | AW44: 70
A45: =IF(AND('Customer Base'!D$8=48,'Customer Base'!D$13="Victron",'Customer Base'!E$13="Multiplus",'Customer Base'!D$14>5,'Customer Base'!D$14<=6),'Customer Base'!D$15,IF(AND('Customer Base'!D$7="Mini-Grid",'Customer Base'!D$8=48,'Customer Base'!F$13="Victron",'Customer Base'!F$14>5,'Customer Base'!F$14<=6),'Customer Base'!F$15,"")) | C45: Victron Multi RS Solar 48/6000/100-450/100 1 tracker | D45: 1914.36 | E45: 1803.06 | F45: =$D45/1.219 -> 1570.4348 | G45: =IFERROR(ROUNDUP(F45*'Customer Base'!$J$5,2),0) -> 26226.27 | H45: =$E45/1.219 -> 1479.1304 | I45: =IFERROR(ROUNDUP(H45*'Customer Base'!$J$5,2),0) -> 24701.48 | L45: =IF(H45>F45,"lkkajdfkj","") | N45: 40 | O45: =IF('Customer Base'!$I$15="MANUAL",IF(B45<>"",C45,""),IF('Customer Base'!$I$15="AUTOMATE",IF(A45<>"",C45,""),"")) | AM45: 6 | AN45: 48/6000 | AO45: =IF('Customer Base'!$I$15="MANUAL",IFERROR(AM45*B45,""),IF('Customer Base'!$I$15="AUTOMATE",IFERROR(AM45*A45,""),"")) | AP45: 450 | AQ45: 48 | AR45: Multiplus | AS45: 1 | AT45: =IF(AND(AR45=$AY$1,$AZ$1=AN45),BA$1,"") | AV45: =IF(AU45<>"",AU45,AT45) | AW45: 100
L46: =IF(H46>F46,"lkkajdfkj","") | N46: 41 | O46: =IF('Customer Base'!$I$15="MANUAL",IF(B46<>"",C46,""),IF('Customer Base'!$I$15="AUTOMATE",IF(A46<>"",C46,""),"")) | AO46: =IF('Customer Base'!$I$15="MANUAL",IFERROR(AM46*B46,""),IF('Customer Base'!$I$15="AUTOMATE",IFERROR(AM46*A46,""),"")) -> 0 | AT46: =IF(AND(AR46=$AY$1,$AZ$1=AN46),BA$1,"")
A47: =IF(AND('Customer Base'!D$8=24,'Customer Base'!D$13="Victron",'Customer Base'!E$13="Multiplus",'Customer Base'!D$14>2,'Customer Base'!D$14<=3),'Customer Base'!D$15,IF(AND('Customer Base'!D$7="Mini-Grid",'Customer Base'!D$8=24,'Customer Base'!F$13="Victron",'Customer Base'!F$14>2,'Customer Base'!F$14<=3),'Customer Base'!F$15,"")) | C47: Victron MultiPlus-II 24/3000/35-32 230V | D47: 988.79 | E47: 931.306 | F47: =$D47/1.219 -> 811.14848 | G47: =IFERROR(ROUNDUP(F47*'Customer Base'!$J$5,2),0) -> 13546.18 | H47: =$E47/1.219 -> 763.9918 | I47: =IFERROR(ROUNDUP(H47*'Customer Base'!$J$5,2),0) -> 12758.67 | L47: =IF(H47>F47,"lkkajdfkj","") | N47: 42 | O47: =IF('Customer Base'!$I$15="MANUAL",IF(B47<>"",C47,""),IF('Customer Base'!$I$15="AUTOMATE",IF(A47<>"",C47,""),"")) | AM47: 3 | AN47: 24/3000 | AO47: =IF('Customer Base'!$I$15="MANUAL",IFERROR(AM47*B47,""),IF('Customer Base'!$I$15="AUTOMATE",IFERROR(AM47*A47,""),"")) | AQ47: 24 | AR47: Multiplus_II | AS47: 1 | AT47: =IF(AND(AR47=$AY$1,$AZ$1=AN47),BA$1,"") | AV47: =IF(AU47<>"",AU47,AT47) | AW47: 70
A48: =IF(AND('Customer Base'!D$8=24,'Customer Base'!D$13="Victron",'Customer Base'!E$13="Multiplus",'Customer Base'!D$14>3,'Customer Base'!D$14<=5),'Customer Base'!D$15,IF(AND('Customer Base'!D$7="Mini-Grid",'Customer Base'!D$8=24,'Customer Base'!F$13="Victron",'Customer Base'!F$14>3,'Customer Base'!F$14<=5),'Customer Base'!F$15,"")) | C48: Victron MultiPlus-II 24/5000/70-50 230V | D48: 2166.876 | E48: 1950.188 | F48: =$D48/1.219 -> 1777.5849 | G48: =IFERROR(ROUNDUP(F48*'Customer Base'!$J$5,2),0) -> 29685.67 | H48: =$E48/1.219 -> 1599.8261 | I48: =IFERROR(ROUNDUP(H48*'Customer Base'!$J$5,2),0) -> 26717.1 | L48: =IF(H48>F48,"lkkajdfkj","") | N48: 43 | O48: =IF('Customer Base'!$I$15="MANUAL",IF(B48<>"",C48,""),IF('Customer Base'!$I$15="AUTOMATE",IF(A48<>"",C48,""),"")) | AM48: 5 | AN48: 24/5000 | AO48: =IF('Customer Base'!$I$15="MANUAL",IFERROR(AM48*B48,""),IF('Customer Base'!$I$15="AUTOMATE",IFERROR(AM48*A48,""),"")) | AQ48: 24 | AR48: Multiplus_II | AS48: 1 | AT48: =IF(AND(AR48=$AY$1,$AZ$1=AN48),BA$1,"") | AV48: =IF(AU48<>"",AU48,AT48) | AW48: 120
A49: =IF(AND('Customer Base'!D$8=48,'Customer Base'!D$13="Victron",'Customer Base'!E$13="Multiplus",'Customer Base'!D$14>2,'Customer Base'!D$14<=3),'Customer Base'!D$15,IF(AND('Customer Base'!D$7="Mini-Grid",'Customer Base'!D$8=48,'Customer Base'!F$13="Victron",'Customer Base'!F$14>2,'Customer Base'!F$14<=3),'Customer Base'!F$15,"")) | C49: Victron MultiPlus-II 48/3000/35-32 230V | D49: 592.37 | E49: 557.928 | F49: =$D49/1.219 -> 485.9475 | G49: =IFERROR(ROUNDUP(F49*'Customer Base'!$J$5,2),0) -> 8115.33 | H49: =$E49/1.219 -> 457.69319 | I49: =IFERROR(ROUNDUP(H49*'Customer Base'!$J$5,2),0) -> 7643.48 | L49: =IF(H49>F49,"lkkajdfkj","") | N49: 45 | O49: =IF('Customer Base'!$I$15="MANUAL",IF(B49<>"",C49,""),IF('Customer Base'!$I$15="AUTOMATE",IF(A49<>"",C49,""),"")) | AM49: 3 | AN49: 48/3000 | AO49: =IF('Customer Base'!$I$15="MANUAL",IFERROR(AM49*B49,""),IF('Customer Base'!$I$15="AUTOMATE",IFERROR(AM49*A49,""),"")) | AQ49: 48 | AR49: Multiplus_II | AS49: 1 | AT49: =IF(AND(AR49=$AY$1,$AZ$1=AN49),BA$1,"") | AV49: =IF(AU49<>"",AU49,AT49) | AW49: 35
A50: =IF(AND('Customer Base'!D$8=48,'Customer Base'!D$13="Victron",'Customer Base'!E$13="Multiplus",'Customer Base'!D$14>3,'Customer Base'!D$14<=5),'Customer Base'!D$15,IF(AND('Customer Base'!D$7="Mini-Grid",'Customer Base'!D$8=48,'Customer Base'!F$13="Victron",'Customer Base'!F$14>3,'Customer Base'!F$14<=5),'Customer Base'!F$15,"")) -> 1 | B50: 1 | C50: Victron MultiPlus-II 48/5000/70-50 230V | D50: 937.31 | E50: 882.819 | F50: =$D50/1.219 -> 768.91715 | G50: =IFERROR(ROUNDUP(F50*'Customer Base'!$J$5,2),0) -> 12840.92 | H50: =$E50/1.219 -> 724.21575 | I50: =IFERROR(ROUNDUP(H50*'Customer Base'!$J$5,2),0) -> 12094.41 | L50: =IF(H50>F50,"lkkajdfkj","") | N50: 46 | O50: =IF('Customer Base'!$I$15="MANUAL",IF(B50<>"",C50,""),IF('Customer Base'!$I$15="AUTOMATE",IF(A50<>"",C50,""),"")) -> Victron MultiPlus-II 48/5000/70-50 230V | AM50: 5 | AN50: 48/5000 | AO50: =IF('Customer Base'!$I$15="MANUAL",IFERROR(AM50*B50,""),IF('Customer Base'!$I$15="AUTOMATE",IFERROR(AM50*A50,""),"")) -> 5 | AQ50: 48 | AR50: Multiplus_II | AS50: 1 | AT50: =IF(AND(AR50=$AY$1,$AZ$1=AN50),BA$1,"") | AV50: =IF(AU50<>"",AU50,AT50) | AW50: 70
A51: =IF(AND('Customer Base'!D$8=48,'Customer Base'!D$13="Victron",'Customer Base'!E$13="Multiplus",'Customer Base'!D$14>6,'Customer Base'!D$14<=8),'Customer Base'!D$15,IF(AND('Customer Base'!D$7="Mini-Grid",'Customer Base'!D$8=48,'Customer Base'!F$13="Victron",'Customer Base'!F$14>6,'Customer Base'!F$14<=8),'Customer Base'!F$15,"")) | C51: Victron MultiPlus-II 48/8000/110-100/100 230V | D51: 1629.91 | E51: 1535.144 | F51: =$D51/1.219 -> 1337.0878 | G51: =IFERROR(ROUNDUP(F51*'Customer Base'!$J$5,2),0) -> 22329.37 | H51: =$E51/1.219 -> 1259.347 | I51: =IFERROR(ROUNDUP(H51*'Customer Base'!$J$5,2),0) -> 21031.1 | L51: =IF(H51>F51,"lkkajdfkj","") | N51: 47 | O51: =IF('Customer Base'!$I$15="MANUAL",IF(B51<>"",C51,""),IF('Customer Base'!$I$15="AUTOMATE",IF(A51<>"",C51,""),"")) | AM51: 8 | AN51: 48/8000 | AO51: =IF('Customer Base'!$I$15="MANUAL",IFERROR(AM51*B51,""),IF('Customer Base'!$I$15="AUTOMATE",IFERROR(AM51*A51,""),"")) | AQ51: 48 | AR51: Multiplus_II | AS51: 1 | AT51: =IF(AND(AR51=$AY$1,$AZ$1=AN51),BA$1,"") | AV51: =IF(AU51<>"",AU51,AT51) | AW51: 110
A52: =IF(AND('Customer Base'!D$8=48,'Customer Base'!D$13="Victron",'Customer Base'!E$13="Multiplus",'Customer Base'!D$14>8,'Customer Base'!D$14<=10),'Customer Base'!D$15,IF(AND('Customer Base'!D$7="Mini-Grid",'Customer Base'!D$8=48,'Customer Base'!F$13="Victron",'Customer Base'!F$14>8,'Customer Base'!F$14<=10),'Customer Base'!F$15,"")) | C52: Victron MultiPlus-II 48/10000/140-100 230V | D52: 1945.97 | E52: 1832.836 | F52: =$D52/1.219 -> 1596.3659 | G52: =IFERROR(ROUNDUP(F52*'Customer Base'!$J$5,2),0) -> 26659.32 | H52: =$E52/1.219 -> 1503.557 | I52: =IFERROR(ROUNDUP(H52*'Customer Base'!$J$5,2),0) -> 25109.41 | L52: =IF(H52>F52,"lkkajdfkj","") | N52: 48 | O52: =IF('Customer Base'!$I$15="MANUAL",IF(B52<>"",C52,""),IF('Customer Base'!$I$15="AUTOMATE",IF(A52<>"",C52,""),"")) | AM52: 10 | AN52: 48/10000 | AO52: =IF('Customer Base'!$I$15="MANUAL",IFERROR(AM52*B52,""),IF('Customer Base'!$I$15="AUTOMATE",IFERROR(AM52*A52,""),"")) | AQ52: 48 | AR52: Multiplus_II | AS52: 1 | AT52: =IF(AND(AR52=$AY$1,$AZ$1=AN52),BA$1,"") | AV52: =IF(AU52<>"",AU52,AT52) | AW52: 140
A53: =IF(AND('Customer Base'!D$8=48,'Customer Base'!D$13="Victron",'Customer Base'!E$13="Multiplus",'Customer Base'!D$14>10,'Customer Base'!D$14<=15),'Customer Base'!D$15,IF(AND('Customer Base'!D$7="Mini-Grid",'Customer Base'!D$8=48,'Customer Base'!F$13="Victron",'Customer Base'!F$14>10,'Customer Base'!F$14<=15),'Customer Base'!F$15,"")) | C53: Victron MultiPlus-II 48/15000/200-100 230V | D53: 2716.22 | E53: 2558.304 | F53: =$D53/1.219 -> 2228.2363 | G53: =IFERROR(ROUNDUP(F53*'Customer Base'!$J$5,2),0) -> 37211.55 | H53: =$E53/1.219 -> 2098.6907 | I53: =IFERROR(ROUNDUP(H53*'Customer Base'!$J$5,2),0) -> 35048.14 | L53: =IF(H53>F53,"lkkajdfkj","") | N53: 49 | O53: =IF('Customer Base'!$I$15="MANUAL",IF(B53<>"",C53,""),IF('Customer Base'!$I$15="AUTOMATE",IF(A53<>"",C53,""),"")) | AM53: 15 | AN53: 48/15000 | AO53: =IF('Customer Base'!$I$15="MANUAL",IFERROR(AM53*B53,""),IF('Customer Base'!$I$15="AUTOMATE",IFERROR(AM53*A53,""),"")) | AQ53: 48 | AR53: Multiplus_II | AS53: 1 | AT53: =IF(AND(AR53=$AY$1,$AZ$1=AN53),BA$1,"") | AV53: =IF(AU53<>"",AU53,AT53) | AW53: 200
C54: Victron MultiPlus-II 48/3000/35-32 230V GX | D54: 674.55 | E54: 635.332 | F54: =$D54/1.219 -> 553.36341 | G54: =IFERROR(ROUNDUP(F54*'Customer Base'!$J$5,2),0) -> 9241.17 | H54: =$E54/1.219 -> 521.19114 | I54: =IFERROR(ROUNDUP(H54*'Customer Base'!$J$5,2),0) -> 8703.9 | J54: =IF(D54<>"",IF(D54<E54,"lkdfjk",""),"") | L54: =IF(H54>F54,"lkkajdfkj","") | N54: 51 | O54: =IF('Customer Base'!$I$15="MANUAL",IF(B54<>"",C54,""),IF('Customer Base'!$I$15="AUTOMATE",IF(A54<>"",C54,""),"")) | AM54: 3 | AN54: 48/3000 | AO54: =IF('Customer Base'!$I$15="MANUAL",IFERROR(AM54*B54,""),IF('Customer Base'!$I$15="AUTOMATE",IFERROR(AM54*A54,""),"")) -> 0 | AQ54: 48 | AR54: Multiplus_II_GX | AS54: 1 | AT54: =IF(AND(AR54=$AY$1,$AZ$1=AN54),BA$1,"") | AV54: =IF(AU54<>"",AU54,AT54) | AW54: 35
C55: Victron MultiPlus-II 48/5000/70-50 230V GX | D55: 1038.45 | E55: 978.075 | F55: =$D55/1.219 -> 851.88679 | G55: =IFERROR(ROUNDUP(F55*'Customer Base'!$J$5,2),0) -> 14226.51 | H55: =$E55/1.219 -> 802.35849 | I55: =IFERROR(ROUNDUP(H55*'Customer Base'!$J$5,2),0) -> 13399.39 | J55: =IF(D55<>"",IF(D55<E55,"lkdfjk",""),"") | L55: =IF(H55>F55,"lkkajdfkj","") | N55: 52 | O55: =IF('Customer Base'!$I$15="MANUAL",IF(B55<>"",C55,""),IF('Customer Base'!$I$15="AUTOMATE",IF(A55<>"",C55,""),"")) | AM55: 5 | AN55: 48/5000 | AO55: =IF('Customer Base'!$I$15="MANUAL",IFERROR(AM55*B55,""),IF('Customer Base'!$I$15="AUTOMATE",IFERROR(AM55*A55,""),"")) -> 0 | AQ55: 48 | AR55: Multiplus_II_GX | AS55: 1 | AT55: =IF(AND(AR55=$AY$1,$AZ$1=AN55),BA$1,"") | AV55: =IF(AU55<>"",AU55,AT55) | AW55: 70
F56: =$D56/1.219 -> 0 | G56: =IFERROR(ROUNDUP(F56*'Customer Base'!$J$5,2),0) -> 0 | H56: =$E56/1.219 -> 0 | I56: =IFERROR(ROUNDUP(H56*'Customer Base'!$J$5,2),0) -> 0 | J56: =IF(D56<>"",IF(D56<E56,"lkdfjk",""),"") | L56: =IF(H56>F56,"lkkajdfkj","") | N56: 53 | O56: =IF('Customer Base'!$I$15="MANUAL",IF(B56<>"",C56,""),IF('Customer Base'!$I$15="AUTOMATE",IF(A56<>"",C56,""),"")) | AO56: =IF('Customer Base'!$I$15="MANUAL",IFERROR(AM56*B56,""),IF('Customer Base'!$I$15="AUTOMATE",IFERROR(AM56*A56,""),"")) -> 0 | AT56: =IF(AND(AR56=$AY$1,$AZ$1=AN56),BA$1,"") | AV56: =IF(AU56<>"",AU56,AT56)
A57: =IF(AND('Customer Base'!D$8=48,'Customer Base'!D$13="Victron",'Customer Base'!E$13="Quattro",'Customer Base'!D$14=5),'Customer Base'!D$15,IF(AND('Customer Base'!D$7="Mini-Grid",'Customer Base'!D$8=48,'Customer Base'!F$13="Victron",'Customer Base'!F$14=5),'Customer Base'!F$15,"")) | C57: Victron Quattro 48/5000/70-100/100 230V VE.Bus | D57: 1672.37 | E57: 1575.126 | F57: =$D57/1.219 -> 1371.9196 | G57: =IFERROR(ROUNDUP(F57*'Customer Base'!$J$5,2),0) -> 22911.06 | H57: =$E57/1.219 -> 1292.146 | I57: =IFERROR(ROUNDUP(H57*'Customer Base'!$J$5,2),0) -> 21578.84 | J57: =IF(D57<>"",IF(D57<E57,"lkdfjk",""),"") | L57: =IF(H57>F57,"lkkajdfkj","") | N57: 54 | O57: =IF('Customer Base'!$I$15="MANUAL",IF(B57<>"",C57,""),IF('Customer Base'!$I$15="AUTOMATE",IF(A57<>"",C57,""),"")) | AM57: 5 | AN57: 48/5000 | AO57: =IF('Customer Base'!$I$15="MANUAL",IFERROR(AM57*B57,""),IF('Customer Base'!$I$15="AUTOMATE",IFERROR(AM57*A57,""),"")) | AQ57: 48 | AR57: Quattro | AS57: 1 | AT57: =IF(AND(AR57=$AY$1,$AZ$1=AN57),BA$1,"") | AV57: =IF(AU57<>"",AU57,AT57) | AW57: 70
A58: =IF(AND('Customer Base'!D$8=48,'Customer Base'!D$13="Victron",'Customer Base'!E$13="Quattro",'Customer Base'!D$14>5,'Customer Base'!D$14<=8),'Customer Base'!D$15,IF(AND('Customer Base'!D$7="Mini-Grid",'Customer Base'!D$8=48,'Customer Base'!F$13="Victron",'Customer Base'!F$14>5,'Customer Base'!F$14<=8),'Customer Base'!F$15,"")) | C58: Victron Quattro 48/8000/110-100/100 230V VE.Bus | D58: 2207.83 | E58: 2079.464 | F58: =$D58/1.219 -> 1811.1813 | G58: =IFERROR(ROUNDUP(F58*'Customer Base'!$J$5,2),0) -> 30246.73 | H58: =$E58/1.219 -> 1705.8769 | I58: =IFERROR(ROUNDUP(H58*'Customer Base'!$J$5,2),0) -> 28488.15 | J58: =IF(D58<>"",IF(D58<E58,"lkdfjk",""),"") | L58: =IF(H58>F58,"lkkajdfkj","") | N58: 55 | O58: =IF('Customer Base'!$I$15="MANUAL",IF(B58<>"",C58,""),IF('Customer Base'!$I$15="AUTOMATE",IF(A58<>"",C58,""),"")) | AM58: 8 | AN58: 48/8000 | AO58: =IF('Customer Base'!$I$15="MANUAL",IFERROR(AM58*B58,""),IF('Customer Base'!$I$15="AUTOMATE",IFERROR(AM58*A58,""),"")) | AQ58: 48 | AR58: Quattro | AS58: 1 | AT58: =IF(AND(AR58=$AY$1,$AZ$1=AN58),BA$1,"") | AV58: =IF(AU58<>"",AU58,AT58) | AW58: 110
A59: =IF(AND('Customer Base'!D$8=48,'Customer Base'!D$13="Victron",'Customer Base'!E$13="Quattro",'Customer Base'!D$14>8,'Customer Base'!D$14<=10),'Customer Base'!D$15,IF(AND('Customer Base'!D$7="Mini-Grid",'Customer Base'!D$8=48,'Customer Base'!F$13="Victron",'Customer Base'!F$14>8,'Customer Base'!F$14<=10),'Customer Base'!F$15,"")) | C59: Victron Quattro 48/10000/140-100/100 230V VE.Bus | D59: 2637.65 | E59: 2484.302 | F59: =$D59/1.219 -> 2163.7818 | G59: =IFERROR(ROUNDUP(F59*'Customer Base'!$J$5,2),0) -> 36135.16 | H59: =$E59/1.219 -> 2037.9836 | I59: =IFERROR(ROUNDUP(H59*'Customer Base'!$J$5,2),0) -> 34034.33 | J59: =IF(D59<>"",IF(D59<E59,"lkdfjk",""),"") | L59: =IF(H59>F59,"lkkajdfkj","") | N59: 56 | O59: =IF('Customer Base'!$I$15="MANUAL",IF(B59<>"",C59,""),IF('Customer Base'!$I$15="AUTOMATE",IF(A59<>"",C59,""),"")) | AM59: 10 | AN59: 48/10000 | AO59: =IF('Customer Base'!$I$15="MANUAL",IFERROR(AM59*B59,""),IF('Customer Base'!$I$15="AUTOMATE",IFERROR(AM59*A59,""),"")) | AQ59: 48 | AR59: Quattro | AS59: 1 | AT59: =IF(AND(AR59=$AY$1,$AZ$1=AN59),BA$1,"") | AV59: =IF(AU59<>"",AU59,AT59) | AW59: 140
A60: =IF(AND('Customer Base'!D$8=48,'Customer Base'!D$13="Victron",'Customer Base'!E$13="Quattro",'Customer Base'!D$14>10,'Customer Base'!D$14<=15),'Customer Base'!D$15,IF(AND('Customer Base'!D$7="Mini-Grid",'Customer Base'!D$8=48,'Customer Base'!F$13="Victron",'Customer Base'!F$14>10,'Customer Base'!F$14<=15),'Customer Base'!F$15,"")) | C60: Victron Quattro 48/15000/200-100/100 230V VE.Bus | D60: 3464.8 | E60: 3263.36 | F60: =$D60/1.219 -> 2842.3298 | G60: =IFERROR(ROUNDUP(F60*'Customer Base'!$J$5,2),0) -> 47466.91 | H60: =$E60/1.219 -> 2677.0796 | I60: =IFERROR(ROUNDUP(H60*'Customer Base'!$J$5,2),0) -> 44707.23 | J60: =IF(D60<>"",IF(D60<E60,"lkdfjk",""),"") | L60: =IF(H60>F60,"lkkajdfkj","") | N60: 57 | O60: =IF('Customer Base'!$I$15="MANUAL",IF(B60<>"",C60,""),IF('Customer Base'!$I$15="AUTOMATE",IF(A60<>"",C60,""),"")) | AM60: 15 | AN60: 48/15000 | AO60: =IF('Customer Base'!$I$15="MANUAL",IFERROR(AM60*B60,""),IF('Customer Base'!$I$15="AUTOMATE",IFERROR(AM60*A60,""),"")) | AQ60: 48 | AR60: Quattro | AS60: 1 | AT60: =IF(AND(AR60=$AY$1,$AZ$1=AN60),BA$1,"") | AV60: =IF(AU60<>"",AU60,AT60) | AW60: 200
F61: =$D61/1.219 -> 0 | G61: =IFERROR(ROUNDUP(F61*'Customer Base'!$J$5,2),0) -> 0 | H61: =$E61/1.219 -> 0 | I61: =IFERROR(ROUNDUP(H61*'Customer Base'!$J$5,2),0) -> 0 | J61: =IF(D61<>"",IF(D61<E61,"lkdfjk",""),"") | L61: =IF(H61>F61,"lkkajdfkj","") | N61: 58 | O61: =IF('Customer Base'!$I$15="MANUAL",IF(B61<>"",C61,""),IF('Customer Base'!$I$15="AUTOMATE",IF(A61<>"",C61,""),"")) | AO61: =IF('Customer Base'!$I$15="MANUAL",IFERROR(AM61*B61,""),IF('Customer Base'!$I$15="AUTOMATE",IFERROR(AM61*A61,""),"")) -> 0 | AT61: =IF(AND(AR61=$AY$1,$AZ$1=AN61),BA$1,"") | AV61: =IF(AU61<>"",AU61,AT61)
C62: Victron Quattro-II 48/5000/70-50/50 230V VE.Bus | D62: 1462.86 | E62: 1377.81 | F62: =$D62/1.219 -> 1200.0492 | G62: =IFERROR(ROUNDUP(F62*'Customer Base'!$J$5,2),0) -> 20040.83 | H62: =$E62/1.219 -> 1130.2789 | I62: =IFERROR(ROUNDUP(H62*'Customer Base'!$J$5,2),0) -> 18875.66 | J62: =IF(D62<>"",IF(D62<E62,"lkdfjk",""),"") | L62: =IF(H62>F62,"lkkajdfkj","") | N62: 59 | O62: =IF('Customer Base'!$I$15="MANUAL",IF(B62<>"",C62,""),IF('Customer Base'!$I$15="AUTOMATE",IF(A62<>"",C62,""),"")) | AM62: 5 | AN62: 48/5000 | AO62: =IF('Customer Base'!$I$15="MANUAL",IFERROR(AM62*B62,""),IF('Customer Base'!$I$15="AUTOMATE",IFERROR(AM62*A62,""),"")) -> 0 | AQ62: 48 | AR62: EasySolar | AS62: 1 | AT62: =IF(AND(AR62=$AY$1,$AZ$1=AN62),BA$1,"") | AV62: =IF(AU62<>"",AU62,AT62) | AW62: 70
F63: =$D63/1.219 -> 0 | G63: =IFERROR(ROUNDUP(F63*'Customer Base'!$J$5,2),0) -> 0 | H63: =$E63/1.219 -> 0 | I63: =IFERROR(ROUNDUP(H63*'Customer Base'!$J$5,2),0) -> 0 | J63: =IF(D63<>"",IF(D63<E63,"lkdfjk",""),"") | L63: =IF(H63>F63,"lkkajdfkj","") | N63: 60 | O63: =IF('Customer Base'!$I$15="MANUAL",IF(B63<>"",C63,""),IF('Customer Base'!$I$15="AUTOMATE",IF(A63<>"",C63,""),"")) | AO63: =IF('Customer Base'!$I$15="MANUAL",IFERROR(AM63*B63,""),IF('Customer Base'!$I$15="AUTOMATE",IFERROR(AM63*A63,""),"")) -> 0 | AT63: =IF(AND(AR63=$AY$1,$AZ$1=AN63),BA$1,"") | AV63: =IF(AU63<>"",AU63,AT63)
C64: Victron EasySolar-II 24/3000/70-32 MPPT 250/70 GX | D64: 1342.77 | E64: 1264.702 | F64: =$D64/1.219 -> 1101.534 | G64: =IFERROR(ROUNDUP(F64*'Customer Base'!$J$5,2),0) -> 18395.62 | H64: =$E64/1.219 -> 1037.4914 | I64: =IFERROR(ROUNDUP(H64*'Customer Base'!$J$5,2),0) -> 17326.11 | J64: =IF(D64<>"",IF(D64<E64,"lkdfjk",""),"") | L64: =IF(H64>F64,"lkkajdfkj","") | N64: 61 | O64: =IF('Customer Base'!$I$15="MANUAL",IF(B64<>"",C64,""),IF('Customer Base'!$I$15="AUTOMATE",IF(A64<>"",C64,""),"")) | AM64: 3 | AN64: 24/3000 | AO64: =IF('Customer Base'!$I$15="MANUAL",IFERROR(AM64*B64,""),IF('Customer Base'!$I$15="AUTOMATE",IFERROR(AM64*A64,""),"")) -> 0 | AQ64: 24 | AR64: EasySolar_II | AS64: 1 | AT64: =IF(AND(AR64=$AY$1,$AZ$1=AN64),BA$1,"") | AV64: =IF(AU64<>"",AU64,AT64) | AW64: 70
C65: Victron EasySolar-II 48/3000/35-32 MPPT 250/70 GX | D65: 1342.77 | E65: 1264.702 | F65: =$D65/1.219 -> 1101.534 | G65: =IFERROR(ROUNDUP(F65*'Customer Base'!$J$5,2),0) -> 18395.62 | H65: =$E65/1.219 -> 1037.4914 | I65: =IFERROR(ROUNDUP(H65*'Customer Base'!$J$5,2),0) -> 17326.11 | J65: =IF(D65<>"",IF(D65<E65,"lkdfjk",""),"") | L65: =IF(H65>F65,"lkkajdfkj","") | N65: 62 | O65: =IF('Customer Base'!$I$15="MANUAL",IF(B65<>"",C65,""),IF('Customer Base'!$I$15="AUTOMATE",IF(A65<>"",C65,""),"")) | AM65: 3 | AN65: 48/3000 | AO65: =IF('Customer Base'!$I$15="MANUAL",IFERROR(AM65*B65,""),IF('Customer Base'!$I$15="AUTOMATE",IFERROR(AM65*A65,""),"")) -> 0 | AQ65: 48 | AR65: EasySolar_II | AS65: 1 | AT65: =IF(AND(AR65=$AY$1,$AZ$1=AN65),BA$1,"") | AV65: =IF(AU65<>"",AU65,AT65) | AW65: 35
C66: Victron EasySolar-II 48/5000/70-50 MPPT 250/100 GX | D66: 1893.58 | E66: 1783.49 | F66: =$D66/1.219 -> 1553.388 | G66: =IFERROR(ROUNDUP(F66*'Customer Base'!$J$5,2),0) -> 25941.58 | H66: =$E66/1.219 -> 1463.0763 | I66: =IFERROR(ROUNDUP(H66*'Customer Base'!$J$5,2),0) -> 24433.38 | J66: =IF(D66<>"",IF(D66<E66,"lkdfjk",""),"") | L66: =IF(H66>F66,"lkkajdfkj","") | N66: 63 | O66: =IF('Customer Base'!$I$15="MANUAL",IF(B66<>"",C66,""),IF('Customer Base'!$I$15="AUTOMATE",IF(A66<>"",C66,""),"")) | AM66: 5 | AN66: 48/5000 | AO66: =IF('Customer Base'!$I$15="MANUAL",IFERROR(AM66*B66,""),IF('Customer Base'!$I$15="AUTOMATE",IFERROR(AM66*A66,""),"")) -> 0 | AQ66: 48 | AR66: EasySolar_II | AS66: 1 | AT66: =IF(AND(AR66=$AY$1,$AZ$1=AN66),BA$1,"") | AV66: =IF(AU66<>"",AU66,AT66) | AW66: 70
J67: =IF(D67<>"",IF(D67<E67,"lkdfjk",""),"") | L67: =IF(H67>F67,"lkkajdfkj","") | N67: 64 | O67: =IF('Customer Base'!$I$15="MANUAL",IF(B67<>"",C67,""),IF('Customer Base'!$I$15="AUTOMATE",IF(A67<>"",C67,""),"")) | AO67: =IF('Customer Base'!$I$15="MANUAL",IFERROR(AM67*B67,""),IF('Customer Base'!$I$15="AUTOMATE",IFERROR(AM67*A67,""),"")) -> 0 | AT67: =IF(AND(AR67=$AY$1,$AZ$1=AN67),BA$1,"") | AV67: =IF(AU67<>"",AU67,AT67)
C68: Phocos Inverters | J68: =IF(D68<>"",IF(D68<E68,"lkdfjk",""),"") | L68: =IF(H68>F68,"lkkajdfkj","") | N68: 65 | O68: =IF('Customer Base'!$I$15="MANUAL",IF(B68<>"",C68,""),IF('Customer Base'!$I$15="AUTOMATE",IF(A68<>"",C68,""),"")) | AO68: =IF('Customer Base'!$I$15="MANUAL",IFERROR(AM68*B68,""),IF('Customer Base'!$I$15="AUTOMATE",IFERROR(AM68*A68,""),"")) -> 0 | AT68: =IF(AND(AR68=$AY$1,$AZ$1=AN68),BA$1,"") | AV68: =IF(AU68<>"",AU68,AT68)
A69: =IF(AND('Customer Base'!D$9=1,'Customer Base'!D$13="Phocos",'Customer Base'!D$14>0,'Customer Base'!D$14<=3),'Customer Base'!D$15,IF(AND('Customer Base'!D$7="Mini-Grid",'Customer Base'!D$9=1,'Customer Base'!F$13="Phocos",'Customer Base'!F$14>0,'Customer Base'!F$14<=3),'Customer Base'!F$15,"")) | C69: Phocos Inverter PSW-H-3KW-230/24V | D69: 1170.41 | E69: 1102.361 | F69: =$D69/1.219 -> 960.13946 | G69: =IFERROR(ROUNDUP(F69*'Customer Base'!$J$5,2),0) -> 16034.33 | H69: =$E69/1.219 -> 904.31583 | I69: =IFERROR(ROUNDUP(H69*'Customer Base'!$J$5,2),0) -> 15102.08 | J69: =IF(D69<>"",IF(D69<E69,"lkdfjk",""),"") | L69: =IF(H69>F69,"lkkajdfkj","") | N69: 66 | O69: =IF('Customer Base'!$I$15="MANUAL",IF(B69<>"",C69,""),IF('Customer Base'!$I$15="AUTOMATE",IF(A69<>"",C69,""),"")) | AM69: 3 | AN69: 24/3000 | AO69: =IF('Customer Base'!$I$15="MANUAL",IFERROR(AM69*B69,""),IF('Customer Base'!$I$15="AUTOMATE",IFERROR(AM69*A69,""),"")) | AP69: 450 | AQ69: 24 | AR69: Phocos_H | AS69: 1 | AT69: =IF(AND(AR69=$AY$1,$AZ$1=AN69),BA$1,"") | AV69: =IF(AU69<>"",AU69,AT69) | AW69: 80
A70: =IF(AND('Customer Base'!D$9=1,'Customer Base'!D$13="Phocos",'Customer Base'!D$14>3,'Customer Base'!D$14<=5),'Customer Base'!D$15,IF(AND('Customer Base'!D$7="Mini-Grid",'Customer Base'!D$9=1,'Customer Base'!F$13="Phocos",'Customer Base'!F$14>3,'Customer Base'!F$14<=5),'Customer Base'!F$15,"")) | C70: Phocos Inverter PSW-H-5KW-230/48V | D70: 1204 | E70: 1134 | F70: =$D70/1.219 -> 987.69483 | G70: =IFERROR(ROUNDUP(F70*'Customer Base'!$J$5,2),0) -> 16494.51 | H70: =$E70/1.219 -> 930.27071 | I70: =IFERROR(ROUNDUP(H70*'Customer Base'!$J$5,2),0) -> 15535.53 | J70: =IF(D70<>"",IF(D70<E70,"lkdfjk",""),"") | L70: =IF(H70>F70,"lkkajdfkj","") | N70: 67 | O70: =IF('Customer Base'!$I$15="MANUAL",IF(B70<>"",C70,""),IF('Customer Base'!$I$15="AUTOMATE",IF(A70<>"",C70,""),"")) | AM70: 5 | AN70: 48/5000 | AO70: =IF('Customer Base'!$I$15="MANUAL",IFERROR(AM70*B70,""),IF('Customer Base'!$I$15="AUTOMATE",IFERROR(AM70*A70,""),"")) | AP70: 450 | AQ70: 48 | AR70: Phocos_H | AS70: 1 | AT70: =IF(AND(AR70=$AY$1,$AZ$1=AN70),BA$1,"") | AV70: =IF(AU70<>"",AU70,AT70) | AW70: 80
A71: =IF(AND('Customer Base'!D$9=1,'Customer Base'!D$13="Phocos",'Customer Base'!D$14>5,'Customer Base'!D$14<=8),'Customer Base'!D$15,IF(AND('Customer Base'!D$7="Mini-Grid",'Customer Base'!D$9=1,'Customer Base'!F$13="Phocos",'Customer Base'!F$14>5,'Customer Base'!F$14<=8),'Customer Base'!F$15,"")) | C71: Phocos Inverter PSW-H-8KW-230/48V | D71: 1582.4 | E71: 1490.4 | F71: =$D71/1.219 -> 1298.1132 | G71: =IFERROR(ROUNDUP(F71*'Customer Base'!$J$5,2),0) -> 21678.5 | H71: =$E71/1.219 -> 1222.6415 | I71: =IFERROR(ROUNDUP(H71*'Customer Base'!$J$5,2),0) -> 20418.12 | J71: =IF(D71<>"",IF(D71<E71,"lkdfjk",""),"") | L71: =IF(H71>F71,"lkkajdfkj","") | N71: 68 | O71: =IF('Customer Base'!$I$15="MANUAL",IF(B71<>"",C71,""),IF('Customer Base'!$I$15="AUTOMATE",IF(A71<>"",C71,""),"")) | AM71: 8 | AN71: 48/8000 | AO71: =IF('Customer Base'!$I$15="MANUAL",IFERROR(AM71*B71,""),IF('Customer Base'!$I$15="AUTOMATE",IFERROR(AM71*A71,""),"")) | AP71: 500 | AQ71: 48 | AR71: Phocos_H | AS71: 1 | AT71: =IF(AND(AR71=$AY$1,$AZ$1=AN71),BA$1,"") | AV71: =IF(AU71<>"",AU71,AT71) | AW71: 120
C72: Phocos Inverter PSW-B-3KW-230/24V | D72: 757.69 | E72: 713.642 | F72: =$D72/1.219 -> 621.56686 | G72: =IFERROR(ROUNDUP(F72*'Customer Base'!$J$5,2),0) -> 10380.17 | H72: =$E72/1.219 -> 585.43232 | I72: =IFERROR(ROUNDUP(H72*'Customer Base'!$J$5,2),0) -> 9776.72 | J72: =IF(D72<>"",IF(D72<E72,"lkdfjk",""),"") | L72: =IF(H72>F72,"lkkajdfkj","") | N72: 69 | O72: =IF('Customer Base'!$I$15="MANUAL",IF(B72<>"",C72,""),IF('Customer Base'!$I$15="AUTOMATE",IF(A72<>"",C72,""),"")) | AM72: 3 | AN72: 24/3000 | AO72: =IF('Customer Base'!$I$15="MANUAL",IFERROR(AM72*B72,""),IF('Customer Base'!$I$15="AUTOMATE",IFERROR(AM72*A72,""),"")) -> 0 | AP72: 145 | AQ72: 24 | AR72: Phocos_B | AS72: 1 | AT72: =IF(AND(AR72=$AY$1,$AZ$1=AN72),BA$1,"") | AV72: =IF(AU72<>"",AU72,AT72) | AW72: 60
C73: Remote Monitoring & Control Gateway w. PhocosLink Cloud Plan | D73: 342.28 | E73: 322.38 | F73: =$D73/1.219 -> 280.78753 | G73: =IFERROR(ROUNDUP(F73*'Customer Base'!$J$5,2),0) -> 4689.16 | H73: =$E73/1.219 -> 264.46267 | I73: =IFERROR(ROUNDUP(H73*'Customer Base'!$J$5,2),0) -> 4416.53 | J73: =IF(D73<>"",IF(D73<E73,"lkdfjk",""),"") | L73: =IF(H73>F73,"lkkajdfkj","") | N73: 70 | O73: =IF('Customer Base'!$I$15="MANUAL",IF(B73<>"",C73,""),IF('Customer Base'!$I$15="AUTOMATE",IF(A73<>"",C73,""),"")) | AO73: =IF('Customer Base'!$I$15="MANUAL",IFERROR(AM73*B73,""),IF('Customer Base'!$I$15="AUTOMATE",IFERROR(AM73*A73,""),"")) -> 0 | AT73: =IF(AND(AR73=$AY$1,$AZ$1=AN73),BA$1,"") | AV73: =IF(AU73<>"",AU73,AT73)
C74: Any-Bridge IOT Gateway + Phocoslink Cloud Report | D74: 368.15 | E74: 318.4 | F74: =$D74/1.219 -> 302.00984 | G74: =IFERROR(ROUNDUP(F74*'Customer Base'!$J$5,2),0) -> 5043.57 | H74: =$E74/1.219 -> 261.1977 | I74: =IFERROR(ROUNDUP(H74*'Customer Base'!$J$5,2),0) -> 4362.01 | J74: =IF(D74<>"",IF(D74<E74,"lkdfjk",""),"") | L74: =IF(H74>F74,"lkkajdfkj","") | N74: 71 | O74: =IF('Customer Base'!$I$15="MANUAL",IF(B74<>"",C74,""),IF('Customer Base'!$I$15="AUTOMATE",IF(A74<>"",C74,""),"")) | AO74: =IF('Customer Base'!$I$15="MANUAL",IFERROR(AM74*B74,""),IF('Customer Base'!$I$15="AUTOMATE",IFERROR(AM74*A74,""),"")) -> 0 | AT74: =IF(AND(AR74=$AY$1,$AZ$1=AN74),BA$1,"") | AV74: =IF(AU74<>"",AU74,AT74)
J75: =IF(D75<>"",IF(D75<E75,"lkdfjk",""),"") | L75: =IF(H75>F75,"lkkajdfkj","") | N75: 72 | O75: =IF('Customer Base'!$I$15="MANUAL",IF(B75<>"",C75,""),IF('Customer Base'!$I$15="AUTOMATE",IF(A75<>"",C75,""),"")) | AO75: =IF('Customer Base'!$I$15="MANUAL",IFERROR(AM75*B75,""),IF('Customer Base'!$I$15="AUTOMATE",IFERROR(AM75*A75,""),"")) -> 0 | AT75: =IF(AND(AR75=$AY$1,$AZ$1=AN75),BA$1,"") | AV75: =IF(AU75<>"",AU75,AT75)
C76: Deye Inverters | J76: =IF(D76<>"",IF(D76<E76,"lkdfjk",""),"") | L76: =IF(H76>F76,"lkkajdfkj","") | N76: 73 | O76: =IF('Customer Base'!$I$15="MANUAL",IF(B76<>"",C76,""),IF('Customer Base'!$I$15="AUTOMATE",IF(A76<>"",C76,""),"")) | AO76: =IF('Customer Base'!$I$15="MANUAL",IFERROR(AM76*B76,""),IF('Customer Base'!$I$15="AUTOMATE",IFERROR(AM76*A76,""),"")) -> 0 | AT76: =IF(AND(AR76=$AY$1,$AZ$1=AN76),BA$1,"") | AV76: =IF(AU76<>"",AU76,AT76)
A77: =IF(AND('Customer Base'!D$9=1,'Customer Base'!D$13="Deye",'Customer Base'!D$14>0,'Customer Base'!D$14<=3),'Customer Base'!D$15,IF(AND('Customer Base'!D$7="Mini-Grid",'Customer Base'!D$9=1,'Customer Base'!F$13="Deye",'Customer Base'!F$14>0,'Customer Base'!F$14<=3),'Customer Base'!F$15,"")) | C77: Deye SUN-3K-SG04LP1- EU - Single phase 3kW LV hybrid inverter | D77: 1276.5 | E77: 1138.5 | F77: =$D77/1.219 -> 1047.1698 | G77: =IFERROR(ROUNDUP(F77*'Customer Base'!$J$5,2),0) -> 17487.74 | H77: =$E77/1.219 -> 933.96226 | I77: =IFERROR(ROUNDUP(H77*'Customer Base'!$J$5,2),0) -> 15597.17 | J77: =IF(D77<>"",IF(D77<E77,"lkdfjk",""),"") | L77: =IF(H77>F77,"lkkajdfkj","") | N77: 74 | O77: =IF('Customer Base'!$I$15="MANUAL",IF(B77<>"",C77,""),IF('Customer Base'!$I$15="AUTOMATE",IF(A77<>"",C77,""),"")) | AM77: 3 | AN77: 48/3000 | AO77: =IF('Customer Base'!$I$15="MANUAL",IFERROR(AM77*B77,""),IF('Customer Base'!$I$15="AUTOMATE",IFERROR(AM77*A77,""),"")) | AP77: 500 | AQ77: 48 | AR77: Deye | AS77: 1 | AT77: =IF(AND(AR77=$AY$1,$AZ$1=AN77),BA$1,"") | AV77: =IF(AU77<>"",AU77,AT77) | AW77: 70
A78: =IF(AND('Customer Base'!D$9=1,'Customer Base'!D$13="Deye",'Customer Base'!D$14>3,'Customer Base'!D$14<=5),'Customer Base'!D$15,IF(AND('Customer Base'!D$7="Mini-Grid",'Customer Base'!D$9=1,'Customer Base'!F$13="Deye",'Customer Base'!F$14>3,'Customer Base'!F$14<=5),'Customer Base'!F$15,"")) | C78: Deye SUN-5K-SG03LP1- EU - Single phase 5kW LV hybrid inverter | D78: 1554 | E78: 1386 | F78: =$D78/1.219 -> 1274.8154 | G78: =IFERROR(ROUNDUP(F78*'Customer Base'!$J$5,2),0) -> 21289.42 | H78: =$E78/1.219 -> 1136.9975 | I78: =IFERROR(ROUNDUP(H78*'Customer Base'!$J$5,2),0) -> 18987.86 | J78: =IF(D78<>"",IF(D78<E78,"lkdfjk",""),"") | L78: =IF(H78>F78,"lkkajdfkj","") | N78: 75 | O78: =IF('Customer Base'!$I$15="MANUAL",IF(B78<>"",C78,""),IF('Customer Base'!$I$15="AUTOMATE",IF(A78<>"",C78,""),"")) | AM78: 5 | AN78: 48/5000 | AO78: =IF('Customer Base'!$I$15="MANUAL",IFERROR(AM78*B78,""),IF('Customer Base'!$I$15="AUTOMATE",IFERROR(AM78*A78,""),"")) | AP78: 500 | AQ78: 48 | AR78: Deye | AS78: 1 | AT78: =IF(AND(AR78=$AY$1,$AZ$1=AN78),BA$1,"") | AV78: =IF(AU78<>"",AU78,AT78) | AW78: 120
A79: =IF(AND('Customer Base'!D$9=1,'Customer Base'!D$13="Deye",'Customer Base'!D$14>5,'Customer Base'!D$14<=6),'Customer Base'!D$15,IF(AND('Customer Base'!D$7="Mini-Grid",'Customer Base'!D$9=1,'Customer Base'!F$13="Deye",'Customer Base'!F$14>5,'Customer Base'!F$14<=6),'Customer Base'!F$15,"")) | C79: Deye SUN-6K-SG05LP1- EU- Single phase 6kW LV hybrid inverter | D79: 1646.5 | E79: 1468.5 | F79: =$D79/1.219 -> 1350.6973 | G79: =IFERROR(ROUNDUP(F79*'Customer Base'!$J$5,2),0) -> 22556.65 | H79: =$E79/1.219 -> 1204.676 | I79: =IFERROR(ROUNDUP(H79*'Customer Base'!$J$5,2),0) -> 20118.09 | J79: =IF(D79<>"",IF(D79<E79,"lkdfjk",""),"") | L79: =IF(H79>F79,"lkkajdfkj","") | N79: 76 | O79: =IF('Customer Base'!$I$15="MANUAL",IF(B79<>"",C79,""),IF('Customer Base'!$I$15="AUTOMATE",IF(A79<>"",C79,""),"")) | AM79: 6 | AN79: 48/6000 | AO79: =IF('Customer Base'!$I$15="MANUAL",IFERROR(AM79*B79,""),IF('Customer Base'!$I$15="AUTOMATE",IFERROR(AM79*A79,""),"")) | AP79: 500 | AQ79: 48 | AR79: Deye | AS79: 1 | AT79: =IF(AND(AR79=$AY$1,$AZ$1=AN79),BA$1,"") | AV79: =IF(AU79<>"",AU79,AT79) | AW79: 135
A80: =IF(AND('Customer Base'!D$9=1,'Customer Base'!D$13="Deye",'Customer Base'!D$14>6,'Customer Base'!D$14<=8),'Customer Base'!D$15,IF(AND('Customer Base'!D$7="Mini-Grid",'Customer Base'!D$9=1,'Customer Base'!F$13="Deye",'Customer Base'!F$14>6,'Customer Base'!F$14<=8),'Customer Base'!F$15,"")) | C80: Deye SUN-8K-SG01LP1- EU- Single phase 8kW LV hybrid inverter | D80: 2525.25 | E80: 2252.25 | F80: =$D80/1.219 -> 2071.5751 | G80: =IFERROR(ROUNDUP(F80*'Customer Base'!$J$5,2),0) -> 34595.31 | H80: =$E80/1.219 -> 1847.621 | I80: =IFERROR(ROUNDUP(H80*'Customer Base'!$J$5,2),0) -> 30855.28 | J80: =IF(D80<>"",IF(D80<E80,"lkdfjk",""),"") | L80: =IF(H80>F80,"lkkajdfkj","") | N80: 77 | O80: =IF('Customer Base'!$I$15="MANUAL",IF(B80<>"",C80,""),IF('Customer Base'!$I$15="AUTOMATE",IF(A80<>"",C80,""),"")) | AM80: 8 | AN80: 48/8000 | AO80: =IF('Customer Base'!$I$15="MANUAL",IFERROR(AM80*B80,""),IF('Customer Base'!$I$15="AUTOMATE",IFERROR(AM80*A80,""),"")) | AP80: 500 | AQ80: 48 | AR80: Deye | AS80: 1 | AT80: =IF(AND(AR80=$AY$1,$AZ$1=AN80),BA$1,"") | AV80: =IF(AU80<>"",AU80,AT80) | AW80: 190
A81: =IF(AND('Customer Base'!D$9=1,'Customer Base'!D$13="Deye",'Customer Base'!D$14>8,'Customer Base'!D$14<=16),'Customer Base'!D$15,IF(AND('Customer Base'!D$7="Mini-Grid",'Customer Base'!D$9=1,'Customer Base'!F$13="Deye",'Customer Base'!F$14>8,'Customer Base'!F$14<=16),'Customer Base'!F$15,"")) | C81: Deye SUN-16K-SG01LP1- EU- Single phase 16kW LV hybrid inverter | D81: 4810 | E81: 4290 | F81: =$D81/1.219 -> 3945.8573 | G81: =IFERROR(ROUNDUP(F81*'Customer Base'!$J$5,2),0) -> 65895.82 | H81: =$E81/1.219 -> 3519.2781 | I81: =IFERROR(ROUNDUP(H81*'Customer Base'!$J$5,2),0) -> 58771.95 | J81: =IF(D81<>"",IF(D81<E81,"lkdfjk",""),"") | L81: =IF(H81>F81,"lkkajdfkj","") | N81: 78 | O81: =IF('Customer Base'!$I$15="MANUAL",IF(B81<>"",C81,""),IF('Customer Base'!$I$15="AUTOMATE",IF(A81<>"",C81,""),"")) | AM81: 16 | AN81: 48/16000 | AO81: =IF('Customer Base'!$I$15="MANUAL",IFERROR(AM81*B81,""),IF('Customer Base'!$I$15="AUTOMATE",IFERROR(AM81*A81,""),"")) | AP81: 500 | AQ81: 48 | AR81: Deye | AS81: 1 | AT81: =IF(AND(AR81=$AY$1,$AZ$1=AN81),BA$1,"") | AV81: =IF(AU81<>"",AU81,AT81) | AW81: 290
A82: =IF(AND('Customer Base'!D$9=3,'Customer Base'!D$13="Deye",'Customer Base'!D$14>0,'Customer Base'!D$14<=10),'Customer Base'!D$15,IF(AND('Customer Base'!D$7="Mini-Grid",'Customer Base'!D$9=3,'Customer Base'!F$13="Deye",'Customer Base'!F$14>0,'Customer Base'!F$14<=10),'Customer Base'!F$15,"")) | C82: Deye SUN-10K-SG04LP3- EU - Three phase 10kW LV hybrid inverter | D82: 3400.3 | E82: 3032.7 | F82: =$D82/1.219 -> 2789.4176 | G82: =IFERROR(ROUNDUP(F82*'Customer Base'!$J$5,2),0) -> 46583.28 | H82: =$E82/1.219 -> 2487.8589 | I82: =IFERROR(ROUNDUP(H82*'Customer Base'!$J$5,2),0) -> 41547.25 | J82: =IF(D82<>"",IF(D82<E82,"lkdfjk",""),"") | L82: =IF(H82>F82,"lkkajdfkj","") | N82: 79 | O82: =IF('Customer Base'!$I$15="MANUAL",IF(B82<>"",C82,""),IF('Customer Base'!$I$15="AUTOMATE",IF(A82<>"",C82,""),"")) | AM82: 10 | AN82: 48/10000 | AO82: =IF('Customer Base'!$I$15="MANUAL",IFERROR(AM82*B82,""),IF('Customer Base'!$I$15="AUTOMATE",IFERROR(AM82*A82,""),"")) | AP82: 800 | AQ82: 48 | AR82: Deye | AS82: 3 | AT82: =IF(AND(AR82=$AY$1,$AZ$1=AN82),BA$1,"") | AV82: =IF(AU82<>"",AU82,AT82) | AW82: 210
A83: =IF(AND('Customer Base'!D$9=3,'Customer Base'!D$13="Deye",'Customer Base'!D$14>10,'Customer Base'!D$14<=12),'Customer Base'!D$15,IF(AND('Customer Base'!D$7="Mini-Grid",'Customer Base'!D$9=3,'Customer Base'!F$13="Deye",'Customer Base'!F$14>10,'Customer Base'!F$14<=12),'Customer Base'!F$15,"")) | C83: Deye SUN-12K-SG04LP3- EU - Three phase 12kW LV hybrid inverter | D83: 3594.55 | E83: 3205.95 | F83: =$D83/1.219 -> 2948.7695 | G83: =IFERROR(ROUNDUP(F83*'Customer Base'!$J$5,2),0) -> 49244.46 | H83: =$E83/1.219 -> 2629.9836 | I83: =IFERROR(ROUNDUP(H83*'Customer Base'!$J$5,2),0) -> 43920.73 | J83: =IF(D83<>"",IF(D83<E83,"lkdfjk",""),"") | L83: =IF(H83>F83,"lkkajdfkj","") | N83: 80 | O83: =IF('Customer Base'!$I$15="MANUAL",IF(B83<>"",C83,""),IF('Customer Base'!$I$15="AUTOMATE",IF(A83<>"",C83,""),"")) | AM83: 12 | AN83: 48/12000 | AO83: =IF('Customer Base'!$I$15="MANUAL",IFERROR(AM83*B83,""),IF('Customer Base'!$I$15="AUTOMATE",IFERROR(AM83*A83,""),"")) | AP83: 800 | AQ83: 48 | AR83: Deye | AS83: 3 | AT83: =IF(AND(AR83=$AY$1,$AZ$1=AN83),BA$1,"") | AV83: =IF(AU83<>"",AU83,AT83) | AW83: 240
J84: =IF(D84<>"",IF(D84<E84,"lkdfjk",""),"") | L84: =IF(H84>F84,"lkkajdfkj","") | N84: 81 | O84: =IF('Customer Base'!$I$15="MANUAL",IF(B84<>"",C84,""),IF('Customer Base'!$I$15="AUTOMATE",IF(A84<>"",C84,""),"")) | AO84: =IF('Customer Base'!$I$15="MANUAL",IFERROR(AM84*B84,""),IF('Customer Base'!$I$15="AUTOMATE",IFERROR(AM84*A84,""),"")) -> 0 | AT84: =IF(AND(AR84=$AY$1,$AZ$1=AN84),BA$1,"") | AV84: =IF(AU84<>"",AU84,AT84)
C85: Huawei Inverters | J85: =IF(D85<>"",IF(D85<E85,"lkdfjk",""),"") | L85: =IF(H85>F85,"lkkajdfkj","") | N85: 82 | O85: =IF('Customer Base'!$I$15="MANUAL",IF(B85<>"",C85,""),IF('Customer Base'!$I$15="AUTOMATE",IF(A85<>"",C85,""),"")) | AO85: =IF('Customer Base'!$I$15="MANUAL",IFERROR(AM85*B85,""),IF('Customer Base'!$I$15="AUTOMATE",IFERROR(AM85*A85,""),"")) -> 0 | AT85: =IF(AND(AR85=$AY$1,$AZ$1=AN85),BA$1,"") | AV85: =IF(AU85<>"",AU85,AT85)
A86: =IF(AND('Customer Base'!D$9=1,'Customer Base'!D$13="Huawei",'Customer Base'!D$14>0,'Customer Base'!D$14<=2),'Customer Base'!D$15,IF(AND('Customer Base'!D$7="Mini-Grid",'Customer Base'!D$9=1,'Customer Base'!F$13="Huawei",'Customer Base'!F$14>0,'Customer Base'!F$14<=2),'Customer Base'!F$15,"")) | C86: Huawei SUN 2000-2KTL-L1 | D86: 729.28 | E86: 686.88 | F86: =$D86/1.219 -> 598.26087 | G86: =IFERROR(ROUNDUP(F86*'Customer Base'!$J$5,2),0) -> 9990.96 | H86: =$E86/1.219 -> 563.47826 | I86: =IFERROR(ROUNDUP(H86*'Customer Base'!$J$5,2),0) -> 9410.09 | J86: =IF(D86<>"",IF(D86<E86,"lkdfjk",""),"") | L86: =IF(H86>F86,"lkkajdfkj","") | N86: 83 | O86: =IF('Customer Base'!$I$15="MANUAL",IF(B86<>"",C86,""),IF('Customer Base'!$I$15="AUTOMATE",IF(A86<>"",C86,""),"")) | AM86: 2 | AN86: 48/2000 | AO86: =IF('Customer Base'!$I$15="MANUAL",IFERROR(AM86*B86,""),IF('Customer Base'!$I$15="AUTOMATE",IFERROR(AM86*A86,""),"")) | AP86: 600 | AQ86: 48 | AR86: Huawei | AS86: 1 | AT86: =IF(AND(AR86=$AY$1,$AZ$1=AN86),BA$1,"") | AV86: =IF(AU86<>"",AU86,AT86)
A87: =IF(AND('Customer Base'!D$9=1,'Customer Base'!D$13="Huawei",'Customer Base'!D$14>2,'Customer Base'!D$14<=3),'Customer Base'!D$15,IF(AND('Customer Base'!D$7="Mini-Grid",'Customer Base'!D$9=1,'Customer Base'!F$13="Huawei",'Customer Base'!F$14>2,'Customer Base'!F$14<=3),'Customer Base'!F$15,"")) | C87: Huawei SUN 2000-3KTL-L1 | D87: 846.14 | E87: 796.943 | F87: =$D87/1.219 -> 694.12633 | G87: =IFERROR(ROUNDUP(F87*'Customer Base'!$J$5,2),0) -> 11591.91 | H87: =$E87/1.219 -> 653.76784 | I87: =IFERROR(ROUNDUP(H87*'Customer Base'!$J$5,2),0) -> 10917.93 | J87: =IF(D87<>"",IF(D87<E87,"lkdfjk",""),"") | L87: =IF(H87>F87,"lkkajdfkj","") | N87: 84 | O87: =IF('Customer Base'!$I$15="MANUAL",IF(B87<>"",C87,""),IF('Customer Base'!$I$15="AUTOMATE",IF(A87<>"",C87,""),"")) | AM87: 3 | AN87: 48/3000 | AO87: =IF('Customer Base'!$I$15="MANUAL",IFERROR(AM87*B87,""),IF('Customer Base'!$I$15="AUTOMATE",IFERROR(AM87*A87,""),"")) | AP87: 600 | AQ87: 48 | AR87: Huawei | AS87: 1 | AT87: =IF(AND(AR87=$AY$1,$AZ$1=AN87),BA$1,"") | AV87: =IF(AU87<>"",AU87,AT87)
A88: =IF(AND('Customer Base'!D$9=1,'Customer Base'!D$13="Huawei",'Customer Base'!D$14>3,'Customer Base'!D$14<=5),'Customer Base'!D$15,IF(AND('Customer Base'!D$7="Mini-Grid",'Customer Base'!D$9=1,'Customer Base'!F$13="Huawei",'Customer Base'!F$14>3,'Customer Base'!F$14<=5),'Customer Base'!F$15,"")) | C88: Huawei SUN 2000-5KTL-L1 | D88: 1086.13 | E88: 1022.981 | F88: =$D88/1.219 -> 891.00082 | G88: =IFERROR(ROUNDUP(F88*'Customer Base'!$J$5,2),0) -> 14879.72 | H88: =$E88/1.219 -> 839.19688 | I88: =IFERROR(ROUNDUP(H88*'Customer Base'!$J$5,2),0) -> 14014.59 | J88: =IF(D88<>"",IF(D88<E88,"lkdfjk",""),"") | L88: =IF(H88>F88,"lkkajdfkj","") | N88: 85 | O88: =IF('Customer Base'!$I$15="MANUAL",IF(B88<>"",C88,""),IF('Customer Base'!$I$15="AUTOMATE",IF(A88<>"",C88,""),"")) | AM88: 5 | AN88: 48/5000 | AO88: =IF('Customer Base'!$I$15="MANUAL",IFERROR(AM88*B88,""),IF('Customer Base'!$I$15="AUTOMATE",IFERROR(AM88*A88,""),"")) | AP88: 600 | AQ88: 48 | AR88: Huawei | AS88: 1 | AT88: =IF(AND(AR88=$AY$1,$AZ$1=AN88),BA$1,"") | AV88: =IF(AU88<>"",AU88,AT88)
A89: =IF(AND('Customer Base'!D$9=3,'Customer Base'!D$13="Huawei",'Customer Base'!D$14>0,'Customer Base'!D$14<=5),'Customer Base'!D$15,IF(AND('Customer Base'!D$7="Mini-Grid",'Customer Base'!D$9=3,'Customer Base'!F$13="Huawei",'Customer Base'!F$14>0,'Customer Base'!F$14<=5),'Customer Base'!F$15,"")) | C89: Huawei SUN 2000-5KTL-M1 | D89: 1266.35 | E89: 1192.725 | F89: =$D89/1.219 -> 1038.8433 | G89: =IFERROR(ROUNDUP(F89*'Customer Base'!$J$5,2),0) -> 17348.69 | H89: =$E89/1.219 -> 978.44545 | I89: =IFERROR(ROUNDUP(H89*'Customer Base'!$J$5,2),0) -> 16340.04 | J89: =IF(D89<>"",IF(D89<E89,"lkdfjk",""),"") | L89: =IF(H89>F89,"lkkajdfkj","") | N89: 86 | O89: =IF('Customer Base'!$I$15="MANUAL",IF(B89<>"",C89,""),IF('Customer Base'!$I$15="AUTOMATE",IF(A89<>"",C89,""),"")) | AM89: 5 | AN89: 48/5000 | AO89: =IF('Customer Base'!$I$15="MANUAL",IFERROR(AM89*B89,""),IF('Customer Base'!$I$15="AUTOMATE",IFERROR(AM89*A89,""),"")) | AP89: 1100 | AQ89: 48 | AR89: Huawei | AS89: 1 | AT89: =IF(AND(AR89=$AY$1,$AZ$1=AN89),BA$1,"") | AV89: =IF(AU89<>"",AU89,AT89)
A90: =IF(AND('Customer Base'!D$9=3,'Customer Base'!D$13="Huawei",'Customer Base'!D$14>5,'Customer Base'!D$14<=10),'Customer Base'!D$15,IF(AND('Customer Base'!D$7="Mini-Grid",'Customer Base'!D$9=3,'Customer Base'!F$13="Huawei",'Customer Base'!F$14>5,'Customer Base'!F$14<=10),'Customer Base'!F$15,"")) | C90: Huawei SUN 2000-10KTL-M1 | D90: 1884.04 | E90: 1774.499 | F90: =$D90/1.219 -> 1545.5619 | G90: =IFERROR(ROUNDUP(F90*'Customer Base'!$J$5,2),0) -> 25810.89 | H90: =$E90/1.219 -> 1455.7006 | I90: =IFERROR(ROUNDUP(H90*'Customer Base'!$J$5,2),0) -> 24310.2 | J90: =IF(D90<>"",IF(D90<E90,"lkdfjk",""),"") | L90: =IF(H90>F90,"lkkajdfkj","") | N90: 87 | O90: =IF('Customer Base'!$I$15="MANUAL",IF(B90<>"",C90,""),IF('Customer Base'!$I$15="AUTOMATE",IF(A90<>"",C90,""),"")) | AM90: 10 | AN90: 48/10000 | AO90: =IF('Customer Base'!$I$15="MANUAL",IFERROR(AM90*B90,""),IF('Customer Base'!$I$15="AUTOMATE",IFERROR(AM90*A90,""),"")) | AP90: 1100 | AQ90: 48 | AR90: Huawei | AS90: 1 | AT90: =IF(AND(AR90=$AY$1,$AZ$1=AN90),BA$1,"") | AV90: =IF(AU90<>"",AU90,AT90)
A91: =IF(AND('Customer Base'!D$9=3,'Customer Base'!D$13="Huawei",'Customer Base'!D$14>10,'Customer Base'!D$14<=20),'Customer Base'!D$15,IF(AND('Customer Base'!D$7="Mini-Grid",'Customer Base'!D$9=3,'Customer Base'!F$13="Huawei",'Customer Base'!F$14>10,'Customer Base'!F$14<=20),'Customer Base'!F$15,"")) | C91: Huawei SUN2000-20KTL-M5 | D91: 2491.11 | E91: 2346.278 | F91: =$D91/1.219 -> 2043.5685 | G91: =IFERROR(ROUNDUP(F91*'Customer Base'!$J$5,2),0) -> 34127.6 | H91: =$E91/1.219 -> 1924.7564 | I91: =IFERROR(ROUNDUP(H91*'Customer Base'!$J$5,2),0) -> 32143.44 | J91: =IF(D91<>"",IF(D91<E91,"lkdfjk",""),"") | L91: =IF(H91>F91,"lkkajdfkj","") | N91: 88 | O91: =IF('Customer Base'!$I$15="MANUAL",IF(B91<>"",C91,""),IF('Customer Base'!$I$15="AUTOMATE",IF(A91<>"",C91,""),"")) | AM91: 20 | AN91: 48/20000 | AO91: =IF('Customer Base'!$I$15="MANUAL",IFERROR(AM91*B91,""),IF('Customer Base'!$I$15="AUTOMATE",IFERROR(AM91*A91,""),"")) | AP91: 1100 | AQ91: 48 | AR91: Huawei | AS91: 3 | AT91: =IF(AND(AR91=$AY$1,$AZ$1=AN91),BA$1,"") | AV91: =IF(AU91<>"",AU91,AT91)
A92: =IF(AND('Customer Base'!D$9=3,'Customer Base'!D$13="Huawei",'Customer Base'!D$14>20,'Customer Base'!D$14<=30),'Customer Base'!D$15,IF(AND('Customer Base'!D$7="Mini-Grid",'Customer Base'!D$9=3,'Customer Base'!F$13="Huawei",'Customer Base'!F$14>20,'Customer Base'!F$14<=30),'Customer Base'!F$15,"")) | C92: Huawei SUN2000-30KTL-M3 | D92: 2913.47 | E92: 2744.086 | F92: =$D92/1.219 -> 2390.0492 | G92: =IFERROR(ROUNDUP(F92*'Customer Base'!$J$5,2),0) -> 39913.83 | H92: =$E92/1.219 -> 2251.096 | I92: =IFERROR(ROUNDUP(H92*'Customer Base'!$J$5,2),0) -> 37593.31 | J92: =IF(D92<>"",IF(D92<E92,"lkdfjk",""),"") | L92: =IF(H92>F92,"lkkajdfkj","") | N92: 89 | O92: =IF('Customer Base'!$I$15="MANUAL",IF(B92<>"",C92,""),IF('Customer Base'!$I$15="AUTOMATE",IF(A92<>"",C92,""),"")) | AM92: 30 | AN92: 48/30000 | AO92: =IF('Customer Base'!$I$15="MANUAL",IFERROR(AM92*B92,""),IF('Customer Base'!$I$15="AUTOMATE",IFERROR(AM92*A92,""),"")) | AP92: 1100 | AQ92: 48 | AR92: Huawei | AS92: 3 | AT92: =IF(AND(AR92=$AY$1,$AZ$1=AN92),BA$1,"") | AV92: =IF(AU92<>"",AU92,AT92)
A93: =IF(AND('Customer Base'!D$9=3,'Customer Base'!D$13="Huawei",'Customer Base'!D$14>30,'Customer Base'!D$14<=40),'Customer Base'!D$15,IF(AND('Customer Base'!D$7="Mini-Grid",'Customer Base'!D$9=3,'Customer Base'!F$13="Huawei",'Customer Base'!F$14>30,'Customer Base'!F$14<=40),'Customer Base'!F$15,"")) | C93: Huawei SUN2000-40KTL-M3 | D93: 3448.48 | E93: 3247.987 | F93: =$D93/1.219 -> 2828.9418 | G93: =IFERROR(ROUNDUP(F93*'Customer Base'!$J$5,2),0) -> 47243.33 | H93: =$E93/1.219 -> 2664.4684 | I93: =IFERROR(ROUNDUP(H93*'Customer Base'!$J$5,2),0) -> 44496.63 | J93: =IF(D93<>"",IF(D93<E93,"lkdfjk",""),"") | L93: =IF(H93>F93,"lkkajdfkj","") | N93: 90 | O93: =IF('Customer Base'!$I$15="MANUAL",IF(B93<>"",C93,""),IF('Customer Base'!$I$15="AUTOMATE",IF(A93<>"",C93,""),"")) | AM93: 40 | AN93: 48/40000 | AO93: =IF('Customer Base'!$I$15="MANUAL",IFERROR(AM93*B93,""),IF('Customer Base'!$I$15="AUTOMATE",IFERROR(AM93*A93,""),"")) | AP93: 1100 | AQ93: 48 | AR93: Huawei | AS93: 3 | AT93: =IF(AND(AR93=$AY$1,$AZ$1=AN93),BA$1,"") | AV93: =IF(AU93<>"",AU93,AT93)
A94: =IF(AND('Customer Base'!D$9=3,'Customer Base'!D$13="Huawei",'Customer Base'!D$14>40,'Customer Base'!D$14<=50),'Customer Base'!D$15,IF(AND('Customer Base'!D$7="Mini-Grid",'Customer Base'!D$9=3,'Customer Base'!F$13="Huawei",'Customer Base'!F$14>40,'Customer Base'!F$14<=50),'Customer Base'!F$15,"")) | C94: Huawei SUN 2000-50KTL-M3 | D94: 3756.7 | E94: 3538.291 | F94: =$D94/1.219 -> 3081.7884 | G94: =IFERROR(ROUNDUP(F94*'Customer Base'!$J$5,2),0) -> 51465.87 | H94: =$E94/1.219 -> 2902.6177 | I94: =IFERROR(ROUNDUP(H94*'Customer Base'!$J$5,2),0) -> 48473.72 | J94: =IF(D94<>"",IF(D94<E94,"lkdfjk",""),"") | L94: =IF(H94>F94,"lkkajdfkj","") | N94: 91 | O94: =IF('Customer Base'!$I$15="MANUAL",IF(B94<>"",C94,""),IF('Customer Base'!$I$15="AUTOMATE",IF(A94<>"",C94,""),"")) | AM94: 50 | AN94: 48/50000 | AO94: =IF('Customer Base'!$I$15="MANUAL",IFERROR(AM94*B94,""),IF('Customer Base'!$I$15="AUTOMATE",IFERROR(AM94*A94,""),"")) | AP94: 1100 | AQ94: 48 | AR94: Huawei | AS94: 3 | AT94: =IF(AND(AR94=$AY$1,$AZ$1=AN94),BA$1,"") | AV94: =IF(AU94<>"",AU94,AT94)
A95: =IFERROR(IF(AND('Customer Base'!D7="Grid-Tied",'Customer Base'!D13="Huawei",'Customer Base'!D34="No"),1,""),"") | C95: Huawei Function Module, Smart Dongle-WLAN-FE, SDongleA-05, WLAN-FE Wireless Module, EQ-10N | D95: 65.12 | E95: 61.236 | F95: =$D95/1.219 -> 53.420837 | G95: =IFERROR(ROUNDUP(F95*'Customer Base'!$J$5,2),0) -> 892.13 | H95: =$E95/1.219 -> 50.234619 | I95: =IFERROR(ROUNDUP(H95*'Customer Base'!$J$5,2),0) -> 838.92 | J95: =IF(D95<>"",IF(D95<E95,"lkdfjk",""),"") | L95: =IF(H95>F95,"lkkajdfkj","") | N95: 92 | O95: =IF('Customer Base'!$I$15="MANUAL",IF(B95<>"",C95,""),IF('Customer Base'!$I$15="AUTOMATE",IF(A95<>"",C95,""),"")) | AO95: =IF('Customer Base'!$I$15="MANUAL",IFERROR(AM95*B95,""),IF('Customer Base'!$I$15="AUTOMATE",IFERROR(AM95*A95,""),"")) | AT95: =IF(AND(AR95=$AY$1,$AZ$1=AN95),BA$1,"") | AV95: =IF(AU95<>"",AU95,AT95)
C96: Huawei Function Module, Inverter external 4G dongle, Supporting the communication for 10 devices at most | D96: 158.93 | E96: 149.688 | F96: =$D96/1.219 -> 130.37736 | G96: =IFERROR(ROUNDUP(F96*'Customer Base'!$J$5,2),0) -> 2177.31 | H96: =$E96/1.219 -> 122.79573 | I96: =IFERROR(ROUNDUP(H96*'Customer Base'!$J$5,2),0) -> 2050.69 | J96: =IF(D96<>"",IF(D96<E96,"lkdfjk",""),"") | L96: =IF(H96>F96,"lkkajdfkj","") | N96: 93 | O96: =IF('Customer Base'!$I$15="MANUAL",IF(B96<>"",C96,""),IF('Customer Base'!$I$15="AUTOMATE",IF(A96<>"",C96,""),"")) | AO96: =IF('Customer Base'!$I$15="MANUAL",IFERROR(AM96*B96,""),IF('Customer Base'!$I$15="AUTOMATE",IFERROR(AM96*A96,""),"")) -> 0 | AT96: =IF(AND(AR96=$AY$1,$AZ$1=AN96),BA$1,"") | AV96: =IF(AU96<>"",AU96,AT96)
C97: Huawei SmartLogger 3000A01GL | D97: 605.01 | E97: 569.835 | F97: =$D97/1.219 -> 496.31665 | G97: =IFERROR(ROUNDUP(F97*'Customer Base'!$J$5,2),0) -> 8288.49 | H97: =$E97/1.219 -> 467.46103 | I97: =IFERROR(ROUNDUP(H97*'Customer Base'!$J$5,2),0) -> 7806.6 | J97: =IF(D97<>"",IF(D97<E97,"lkdfjk",""),"") | L97: =IF(H97>F97,"lkkajdfkj","") | N97: 94 | O97: =IF('Customer Base'!$I$15="MANUAL",IF(B97<>"",C97,""),IF('Customer Base'!$I$15="AUTOMATE",IF(A97<>"",C97,""),"")) | AO97: =IF('Customer Base'!$I$15="MANUAL",IFERROR(AM97*B97,""),IF('Customer Base'!$I$15="AUTOMATE",IFERROR(AM97*A97,""),"")) -> 0 | AT97: =IF(AND(AR97=$AY$1,$AZ$1=AN97),BA$1,"") | AV97: =IF(AU97<>"",AU97,AT97)
A98: =IFERROR(IF(AND('Customer Base'!D7="Grid-Tied",'Customer Base'!D13="Huawei",'Customer Base'!D34="No"),1,""),"") | C98: Huawei DTSU666-H 250A/50mA 3-Phase Smart Power Sensor | D98: 101.51 | E98: 95.612 | F98: =$D98/1.219 -> 83.273175 | G98: =IFERROR(ROUNDUP(F98*'Customer Base'!$J$5,2),0) -> 1390.67 | H98: =$E98/1.219 -> 78.434783 | I98: =IFERROR(ROUNDUP(H98*'Customer Base'!$J$5,2),0) -> 1309.87 | J98: =IF(D98<>"",IF(D98<E98,"lkdfjk",""),"") | L98: =IF(H98>F98,"lkkajdfkj","") | N98: 95 | O98: =IF('Customer Base'!$I$15="MANUAL",IF(B98<>"",C98,""),IF('Customer Base'!$I$15="AUTOMATE",IF(A98<>"",C98,""),"")) | AO98: =IF('Customer Base'!$I$15="MANUAL",IFERROR(AM98*B98,""),IF('Customer Base'!$I$15="AUTOMATE",IFERROR(AM98*A98,""),"")) | AT98: =IF(AND(AR98=$AY$1,$AZ$1=AN98),BA$1,"") | AV98: =IF(AU98<>"",AU98,AT98)
C99: Huawei DDSU666-H | D99: 66.75 | E99: 62.872 | F99: =$D99/1.219 -> 54.757998 | G99: =IFERROR(ROUNDUP(F99*'Customer Base'!$J$5,2),0) -> 914.46 | H99: =$E99/1.219 -> 51.576702 | I99: =IFERROR(ROUNDUP(H99*'Customer Base'!$J$5,2),0) -> 861.34 | J99: =IF(D99<>"",IF(D99<E99,"lkdfjk",""),"") | L99: =IF(H99>F99,"lkkajdfkj","") | N99: 96 | O99: =IF('Customer Base'!$I$15="MANUAL",IF(B99<>"",C99,""),IF('Customer Base'!$I$15="AUTOMATE",IF(A99<>"",C99,""),"")) | AO99: =IF('Customer Base'!$I$15="MANUAL",IFERROR(AM99*B99,""),IF('Customer Base'!$I$15="AUTOMATE",IFERROR(AM99*A99,""),"")) -> 0 | AT99: =IF(AND(AR99=$AY$1,$AZ$1=AN99),BA$1,"") | AV99: =IF(AU99<>"",AU99,AT99)
C100: Huawei IOT outdoor 4G module | D100: 294.12 | E100: 277.02 | F100: =$D100/1.219 -> 241.27974 | G100: =IFERROR(ROUNDUP(F100*'Customer Base'!$J$5,2),0) -> 4029.38 | H100: =$E100/1.219 -> 227.25185 | I100: =IFERROR(ROUNDUP(H100*'Customer Base'!$J$5,2),0) -> 3795.11 | J100: =IF(D100<>"",IF(D100<E100,"lkdfjk",""),"") | L100: =IF(H100>F100,"lkkajdfkj","") | N100: 97 | O100: =IF('Customer Base'!$I$15="MANUAL",IF(B100<>"",C100,""),IF('Customer Base'!$I$15="AUTOMATE",IF(A100<>"",C100,""),"")) | AO100: =IF('Customer Base'!$I$15="MANUAL",IFERROR(AM100*B100,""),IF('Customer Base'!$I$15="AUTOMATE",IFERROR(AM100*A100,""),"")) -> 0 | AT100: =IF(AND(AR100=$AY$1,$AZ$1=AN100),BA$1,"") | AV100: =IF(AU100<>"",AU100,AT100)
...

Sheet Client List
B1: CLIENT NAME | C1: TOWN | D1: CITY/REGION | E1: PHONE NUMBER | F1: CODE | G1: CONTACT PEERSON | H1: EMAIL ADDRESS | N1: =SUM(Items!A242:A254) -> 9 | O1: =IF(MOD($N$1,ROW())=0,ROW(),"") -> 1 | P1: =IFERROR(LARGE(O$1:O$100, ROW()), "") -> 9 | Q1: =_xlfn.TEXTJOIN(", ", TRUE, P1:P100) -> 9, 3, 1
B2: Tilman Rippel | C2: Mankoadze - Winneba | D2: Central Region | E2: 0545245745 | F2: =UPPER(LEFT(B2,1)) & IFERROR(UPPER(LEFT(MID(B2,FIND(" ",B2)+1,LEN(B2)),1)),"") & IFERROR(UPPER(LEFT(MID(B2,FIND(" ",B2,FIND(" ",B2)+1)+1,LEN(B2)),1)),"") & IFERROR(UPPER(LEFT(MID(B2,FIND(" ",B2,FIND(" ",B2,FIND(" ",B2)+1)+1)+1,LEN(B2)),1)),"") -> TR | I2: Username | J2: Passcode | O2: =IF(MOD($N$1,ROW())=0,ROW(),"") | P2: =IFERROR(LARGE(O$1:O$100, ROW()), "") -> 3 | U2: =IF(MOD($T$500,ROW())=0,ROW(),"") -> 2
B3: Apostle Baidoo | C3: Kasoa | D3: Accra | E3: 0504253726 | F3: =UPPER(LEFT(B3,1)) & IFERROR(UPPER(LEFT(MID(B3,FIND(" ",B3)+1,LEN(B3)),1)),"") & IFERROR(UPPER(LEFT(MID(B3,FIND(" ",B3,FIND(" ",B3)+1)+1,LEN(B3)),1)),"") & IFERROR(UPPER(LEFT(MID(B3,FIND(" ",B3,FIND(" ",B3,FIND(" ",B3)+1)+1)+1,LEN(B3)),1)),"") -> AB | I3: Emmanuel | J3: 1234 | O3: =IF(MOD($N$1,ROW())=0,ROW(),"") -> 3 | P3: =IFERROR(LARGE(O$1:O$100, ROW()), "") -> 1 | U3: =IF(MOD($T$500,ROW())=0,ROW(),"") -> 3
B4: Dr. Tony Aidoo | C4: East Legon | D4: Accra | E4: 0244355633 | F4: =UPPER(LEFT(B4,1)) & IFERROR(UPPER(LEFT(MID(B4,FIND(" ",B4)+1,LEN(B4)),1)),"") & IFERROR(UPPER(LEFT(MID(B4,FIND(" ",B4,FIND(" ",B4)+1)+1,LEN(B4)),1)),"") & IFERROR(UPPER(LEFT(MID(B4,FIND(" ",B4,FIND(" ",B4,FIND(" ",B4)+1)+1)+1,LEN(B4)),1)),"") -> DTA | I4: Gorden | J4: 5555 | O4: =IF(MOD($N$1,ROW())=0,ROW(),"") | P4: =IFERROR(LARGE(O$1:O$100, ROW()), "") | U4: =IF(MOD($T$500,ROW())=0,ROW(),"") -> 4
B5: Rider Steel | C5: Tema | D5: Tema | E5: 0 | F5: =UPPER(LEFT(B5,1)) & IFERROR(UPPER(LEFT(MID(B5,FIND(" ",B5)+1,LEN(B5)),1)),"") & IFERROR(UPPER(LEFT(MID(B5,FIND(" ",B5,FIND(" ",B5)+1)+1,LEN(B5)),1)),"") & IFERROR(UPPER(LEFT(MID(B5,FIND(" ",B5,FIND(" ",B5,FIND(" ",B5)+1)+1)+1,LEN(B5)),1)),"") -> RS | I5: Postino | J5: 1980 | O5: =IF(MOD($N$1,ROW())=0,ROW(),"") | P5: =IFERROR(LARGE(O$1:O$100, ROW()), "") | U5: =IF(MOD($T$500,ROW())=0,ROW(),"") -> 5
B6: HPW Fresh & Dry | C6: Adeiso | D6: Eastern Region | E6: 0 | F6: =UPPER(LEFT(B6,1)) & IFERROR(UPPER(LEFT(MID(B6,FIND(" ",B6)+1,LEN(B6)),1)),"") & IFERROR(UPPER(LEFT(MID(B6,FIND(" ",B6,FIND(" ",B6)+1)+1,LEN(B6)),1)),"") & IFERROR(UPPER(LEFT(MID(B6,FIND(" ",B6,FIND(" ",B6,FIND(" ",B6)+1)+1)+1,LEN(B6)),1)),"") -> HF&D | O6: =IF(MOD($N$1,ROW())=0,ROW(),"") | P6: =IFERROR(LARGE(O$1:O$100, ROW()), "") | U6: =IF(MOD($T$500,ROW())=0,ROW(),"") -> 6
B7: Christian Akuffo | C7: Adjringanor | D7: Accra | E7: 0 | F7: =UPPER(LEFT(B7,1)) & IFERROR(UPPER(LEFT(MID(B7,FIND(" ",B7)+1,LEN(B7)),1)),"") & IFERROR(UPPER(LEFT(MID(B7,FIND(" ",B7,FIND(" ",B7)+1)+1,LEN(B7)),1)),"") & IFERROR(UPPER(LEFT(MID(B7,FIND(" ",B7,FIND(" ",B7,FIND(" ",B7)+1)+1)+1,LEN(B7)),1)),"") -> CA | O7: =IF(MOD($N$1,ROW())=0,ROW(),"") | P7: =IFERROR(LARGE(O$1:O$100, ROW()), "") | U7: =IF(MOD($T$500,ROW())=0,ROW(),"") -> 7
B8: Mr. Ebow - IT Consortium | C8: Tema, Community 22 | D8: Tema | E8: 0242782978 | F8: =UPPER(LEFT(B8,1)) & IFERROR(UPPER(LEFT(MID(B8,FIND(" ",B8)+1,LEN(B8)),1)),"") & IFERROR(UPPER(LEFT(MID(B8,FIND(" ",B8,FIND(" ",B8)+1)+1,LEN(B8)),1)),"") & IFERROR(UPPER(LEFT(MID(B8,FIND(" ",B8,FIND(" ",B8,FIND(" ",B8)+1)+1)+1,LEN(B8)),1)),"") -> ME-I | O8: =IF(MOD($N$1,ROW())=0,ROW(),"") | P8: =IFERROR(LARGE(O$1:O$100, ROW()), "") | U8: =IF(MOD($T$500,ROW())=0,ROW(),"") -> 8
B9: Ada Island | C9: Ada | D9: Greater Accra Region | E9: 0 | F9: =UPPER(LEFT(B9,1)) & IFERROR(UPPER(LEFT(MID(B9,FIND(" ",B9)+1,LEN(B9)),1)),"") & IFERROR(UPPER(LEFT(MID(B9,FIND(" ",B9,FIND(" ",B9)+1)+1,LEN(B9)),1)),"") & IFERROR(UPPER(LEFT(MID(B9,FIND(" ",B9,FIND(" ",B9,FIND(" ",B9)+1)+1)+1,LEN(B9)),1)),"") -> AI | O9: =IF(MOD($N$1,ROW())=0,ROW(),"") -> 9 | P9: =IFERROR(LARGE(O$1:O$100, ROW()), "") | U9: =IF(MOD($T$500,ROW())=0,ROW(),"") -> 9
B10: Mr. Kobla Nyaletey | C10: Tema, Community 25 | D10: Tema | E10: 0243157124 | F10: =UPPER(LEFT(B10,1)) & IFERROR(UPPER(LEFT(MID(B10,FIND(" ",B10)+1,LEN(B10)),1)),"") & IFERROR(UPPER(LEFT(MID(B10,FIND(" ",B10,FIND(" ",B10)+1)+1,LEN(B10)),1)),"") & IFERROR(UPPER(LEFT(MID(B10,FIND(" ",B10,FIND(" ",B10,FIND(" ",B10)+1)+1)+1,LEN(B10)),1)),"") -> MKN | O10: =IF(MOD($N$1,ROW())=0,ROW(),"") | P10: =IFERROR(LARGE(O$1:O$100, ROW()), "") | U10: =IF(MOD($T$500,ROW())=0,ROW(),"") -> 10
B11: IT Consortium | C11: Adjringanor | D11: Accra | E11: 0553057758 | F11: =UPPER(LEFT(B11,1)) & IFERROR(UPPER(LEFT(MID(B11,FIND(" ",B11)+1,LEN(B11)),1)),"") & IFERROR(UPPER(LEFT(MID(B11,FIND(" ",B11,FIND(" ",B11)+1)+1,LEN(B11)),1)),"") & IFERROR(UPPER(LEFT(MID(B11,FIND(" ",B11,FIND(" ",B11,FIND(" ",B11)+1)+1)+1,LEN(B11)),1)),"") -> IC | G11: Jackie Nyarko | O11: =IF(MOD($N$1,ROW())=0,ROW(),"") | P11: =IFERROR(LARGE(O$1:O$100, ROW()), "") | U11: =IF(MOD($T$500,ROW())=0,ROW(),"") -> 11
B12: Mad. Rebecca | C12: Bolgatanga | D12: Bolgatanga | E12: 0 | F12: =UPPER(LEFT(B12,1)) & IFERROR(UPPER(LEFT(MID(B12,FIND(" ",B12)+1,LEN(B12)),1)),"") & IFERROR(UPPER(LEFT(MID(B12,FIND(" ",B12,FIND(" ",B12)+1)+1,LEN(B12)),1)),"") & IFERROR(UPPER(LEFT(MID(B12,FIND(" ",B12,FIND(" ",B12,FIND(" ",B12)+1)+1)+1,LEN(B12)),1)),"") -> MR | O12: =IF(MOD($N$1,ROW())=0,ROW(),"") | P12: =IFERROR(LARGE(O$1:O$100, ROW()), "") | U12: =IF(MOD($T$500,ROW())=0,ROW(),"") -> 12
B13: Mr. Emmanuel Owusu Ansah | C13: Kumasi | D13: Kumasi | E13: 0 | F13: =UPPER(LEFT(B13,1)) & IFERROR(UPPER(LEFT(MID(B13,FIND(" ",B13)+1,LEN(B13)),1)),"") & IFERROR(UPPER(LEFT(MID(B13,FIND(" ",B13,FIND(" ",B13)+1)+1,LEN(B13)),1)),"") & IFERROR(UPPER(LEFT(MID(B13,FIND(" ",B13,FIND(" ",B13,FIND(" ",B13)+1)+1)+1,LEN(B13)),1)),"") -> MEOA | O13: =IF(MOD($N$1,ROW())=0,ROW(),"") | P13: =IFERROR(LARGE(O$1:O$100, ROW()), "") | U13: =IF(MOD($T$500,ROW())=0,ROW(),"") -> 13
B14: Col. Babilah Sampan | C14: Trade Fair | D14: Accra | E14: 0207419025 | F14: =UPPER(LEFT(B14,1)) & IFERROR(UPPER(LEFT(MID(B14,FIND(" ",B14)+1,LEN(B14)),1)),"") & IFERROR(UPPER(LEFT(MID(B14,FIND(" ",B14,FIND(" ",B14)+1)+1,LEN(B14)),1)),"") & IFERROR(UPPER(LEFT(MID(B14,FIND(" ",B14,FIND(" ",B14,FIND(" ",B14)+1)+1)+1,LEN(B14)),1)),"") -> CBS | O14: =IF(MOD($N$1,ROW())=0,ROW(),"") | P14: =IFERROR(LARGE(O$1:O$100, ROW()), "") | U14: =IF(MOD($T$500,ROW())=0,ROW(),"") -> 14
B15: Dr. Solomon | C15: Bolgatanga | D15: Bolgatanga | E15: 0 | F15: =UPPER(LEFT(B15,1)) & IFERROR(UPPER(LEFT(MID(B15,FIND(" ",B15)+1,LEN(B15)),1)),"") & IFERROR(UPPER(LEFT(MID(B15,FIND(" ",B15,FIND(" ",B15)+1)+1,LEN(B15)),1)),"") & IFERROR(UPPER(LEFT(MID(B15,FIND(" ",B15,FIND(" ",B15,FIND(" ",B15)+1)+1)+1,LEN(B15)),1)),"") -> DS | O15: =IF(MOD($N$1,ROW())=0,ROW(),"") | P15: =IFERROR(LARGE(O$1:O$100, ROW()), "") | U15: =IF(MOD($T$500,ROW())=0,ROW(),"") -> 15
B16: Star Villa Hotel | C16: Kpong | D16: Eastern Region | E16: 0206068598 | F16: =UPPER(LEFT(B16,1)) & IFERROR(UPPER(LEFT(MID(B16,FIND(" ",B16)+1,LEN(B16)),1)),"") & IFERROR(UPPER(LEFT(MID(B16,FIND(" ",B16,FIND(" ",B16)+1)+1,LEN(B16)),1)),"") & IFERROR(UPPER(LEFT(MID(B16,FIND(" ",B16,FIND(" ",B16,FIND(" ",B16)+1)+1)+1,LEN(B16)),1)),"") -> SVH | O16: =IF(MOD($N$1,ROW())=0,ROW(),"") | P16: =IFERROR(LARGE(O$1:O$100, ROW()), "") | U16: =IF(MOD($T$500,ROW())=0,ROW(),"") -> 16
B17: Nagiza Pharmacy | C17: Somanya | D17: Eastern Region | E17: 0249150857 | F17: =UPPER(LEFT(B17,1)) & IFERROR(UPPER(LEFT(MID(B17,FIND(" ",B17)+1,LEN(B17)),1)),"") & IFERROR(UPPER(LEFT(MID(B17,FIND(" ",B17,FIND(" ",B17)+1)+1,LEN(B17)),1)),"") & IFERROR(UPPER(LEFT(MID(B17,FIND(" ",B17,FIND(" ",B17,FIND(" ",B17)+1)+1)+1,LEN(B17)),1)),"") -> NP | O17: =IF(MOD($N$1,ROW())=0,ROW(),"") | P17: =IFERROR(LARGE(O$1:O$100, ROW()), "") | U17: =IF(MOD($T$500,ROW())=0,ROW(),"") -> 17
B18: Frank Domoh | C18: Botwe, Lake Side | D18: Accra | E18: 0244125717 | F18: =UPPER(LEFT(B18,1)) & IFERROR(UPPER(LEFT(MID(B18,FIND(" ",B18)+1,LEN(B18)),1)),"") & IFERROR(UPPER(LEFT(MID(B18,FIND(" ",B18,FIND(" ",B18)+1)+1,LEN(B18)),1)),"") & IFERROR(UPPER(LEFT(MID(B18,FIND(" ",B18,FIND(" ",B18,FIND(" ",B18)+1)+1)+1,LEN(B18)),1)),"") -> FD | O18: =IF(MOD($N$1,ROW())=0,ROW(),"") | P18: =IFERROR(LARGE(O$1:O$100, ROW()), "") | U18: =IF(MOD($T$500,ROW())=0,ROW(),"") -> 18
B19: Frank Domoh Office Minex 360 | C19: East Legon | D19: Accra | E19: 0244125717 | F19: =UPPER(LEFT(B19,1)) & IFERROR(UPPER(LEFT(MID(B19,FIND(" ",B19)+1,LEN(B19)),1)),"") & IFERROR(UPPER(LEFT(MID(B19,FIND(" ",B19,FIND(" ",B19)+1)+1,LEN(B19)),1)),"") & IFERROR(UPPER(LEFT(MID(B19,FIND(" ",B19,FIND(" ",B19,FIND(" ",B19)+1)+1)+1,LEN(B19)),1)),"") -> FDOM | O19: =IF(MOD($N$1,ROW())=0,ROW(),"") | P19: =IFERROR(LARGE(O$1:O$100, ROW()), "") | U19: =IF(MOD($T$500,ROW())=0,ROW(),"") -> 19
B20: Dr. Tweneboah-Koduah | C20: Airport Hills | D20: Accra | E20: 0244842233 | F20: =UPPER(LEFT(B20,1)) & IFERROR(UPPER(LEFT(MID(B20,FIND(" ",B20)+1,LEN(B20)),1)),"") & IFERROR(UPPER(LEFT(MID(B20,FIND(" ",B20,FIND(" ",B20)+1)+1,LEN(B20)),1)),"") & IFERROR(UPPER(LEFT(MID(B20,FIND(" ",B20,FIND(" ",B20,FIND(" ",B20)+1)+1)+1,LEN(B20)),1)),"") -> DT | O20: =IF(MOD($N$1,ROW())=0,ROW(),"") | P20: =IFERROR(LARGE(O$1:O$100, ROW()), "") | U20: =IF(MOD($T$500,ROW())=0,ROW(),"") -> 20
B21: Pastor | C21: West Legon | D21: Accra | E21: 0 | F21: =UPPER(LEFT(B21,1)) & IFERROR(UPPER(LEFT(MID(B21,FIND(" ",B21)+1,LEN(B21)),1)),"") & IFERROR(UPPER(LEFT(MID(B21,FIND(" ",B21,FIND(" ",B21)+1)+1,LEN(B21)),1)),"") & IFERROR(UPPER(LEFT(MID(B21,FIND(" ",B21,FIND(" ",B21,FIND(" ",B21)+1)+1)+1,LEN(B21)),1)),"") -> P | O21: =IF(MOD($N$1,ROW())=0,ROW(),"") | P21: =IFERROR(LARGE(O$1:O$100, ROW()), "") | U21: =IF(MOD($T$500,ROW())=0,ROW(),"") -> 21
B22: Ekow IT Consortium | C22: Tema, Community 22 | D22: Tema | E22: 0 | F22: =UPPER(LEFT(B22,1)) & IFERROR(UPPER(LEFT(MID(B22,FIND(" ",B22)+1,LEN(B22)),1)),"") & IFERROR(UPPER(LEFT(MID(B22,FIND(" ",B22,FIND(" ",B22)+1)+1,LEN(B22)),1)),"") & IFERROR(UPPER(LEFT(MID(B22,FIND(" ",B22,FIND(" ",B22,FIND(" ",B22)+1)+1)+1,LEN(B22)),1)),"") -> EIC | O22: =IF(MOD($N$1,ROW())=0,ROW(),"") | P22: =IFERROR(LARGE(O$1:O$100, ROW()), "") | U22: =IF(MOD($T$500,ROW())=0,ROW(),"") -> 22
B23: Barclays ATM, Kwabenya | C23: Kwabenya | D23: Accra | E23: 0 | F23: =UPPER(LEFT(B23,1)) & IFERROR(UPPER(LEFT(MID(B23,FIND(" ",B23)+1,LEN(B23)),1)),"") & IFERROR(UPPER(LEFT(MID(B23,FIND(" ",B23,FIND(" ",B23)+1)+1,LEN(B23)),1)),"") & IFERROR(UPPER(LEFT(MID(B23,FIND(" ",B23,FIND(" ",B23,FIND(" ",B23)+1)+1)+1,LEN(B23)),1)),"") -> BAK | O23: =IF(MOD($N$1,ROW())=0,ROW(),"") | P23: =IFERROR(LARGE(O$1:O$100, ROW()), "") | U23: =IF(MOD($T$500,ROW())=0,ROW(),"") -> 23
B24: Mad. Diane Manful | C24: Kwabenya | D24: Accra | E24: 0 | F24: =UPPER(LEFT(B24,1)) & IFERROR(UPPER(LEFT(MID(B24,FIND(" ",B24)+1,LEN(B24)),1)),"") & IFERROR(UPPER(LEFT(MID(B24,FIND(" ",B24,FIND(" ",B24)+1)+1,LEN(B24)),1)),"") & IFERROR(UPPER(LEFT(MID(B24,FIND(" ",B24,FIND(" ",B24,FIND(" ",B24)+1)+1)+1,LEN(B24)),1)),"") -> MDM | O24: =IF(MOD($N$1,ROW())=0,ROW(),"") | P24: =IFERROR(LARGE(O$1:O$100, ROW()), "") | U24: =IF(MOD($T$500,ROW())=0,ROW(),"") -> 24
B25: Dr. Alijah | C25: Dzorwulu | D25: Accra | E25: 0 | F25: =UPPER(LEFT(B25,1)) & IFERROR(UPPER(LEFT(MID(B25,FIND(" ",B25)+1,LEN(B25)),1)),"") & IFERROR(UPPER(LEFT(MID(B25,FIND(" ",B25,FIND(" ",B25)+1)+1,LEN(B25)),1)),"") & IFERROR(UPPER(LEFT(MID(B25,FIND(" ",B25,FIND(" ",B25,FIND(" ",B25)+1)+1)+1,LEN(B25)),1)),"") -> DA | O25: =IF(MOD($N$1,ROW())=0,ROW(),"") | P25: =IFERROR(LARGE(O$1:O$100, ROW()), "") | U25: =IF(MOD($T$500,ROW())=0,ROW(),"") -> 25
B26: Mr. Fred Bagonluri | C26: Teiman | D26: Accra | E26: 0 | F26: =UPPER(LEFT(B26,1)) & IFERROR(UPPER(LEFT(MID(B26,FIND(" ",B26)+1,LEN(B26)),1)),"") & IFERROR(UPPER(LEFT(MID(B26,FIND(" ",B26,FIND(" ",B26)+1)+1,LEN(B26)),1)),"") & IFERROR(UPPER(LEFT(MID(B26,FIND(" ",B26,FIND(" ",B26,FIND(" ",B26)+1)+1)+1,LEN(B26)),1)),"") -> MFB | O26: =IF(MOD($N$1,ROW())=0,ROW(),"") | P26: =IFERROR(LARGE(O$1:O$100, ROW()), "") | U26: =IF(MOD($T$500,ROW())=0,ROW(),"") -> 26
B27: Col. Tekyi | C27: Botwe, Lake Side | D27: Accra | E27: 0 | F27: =UPPER(LEFT(B27,1)) & IFERROR(UPPER(LEFT(MID(B27,FIND(" ",B27)+1,LEN(B27)),1)),"") & IFERROR(UPPER(LEFT(MID(B27,FIND(" ",B27,FIND(" ",B27)+1)+1,LEN(B27)),1)),"") & IFERROR(UPPER(LEFT(MID(B27,FIND(" ",B27,FIND(" ",B27,FIND(" ",B27)+1)+1)+1,LEN(B27)),1)),"") -> CT | O27: =IF(MOD($N$1,ROW())=0,ROW(),"") | P27: =IFERROR(LARGE(O$1:O$100, ROW()), "") | U27: =IF(MOD($T$500,ROW())=0,ROW(),"") -> 27
B28: Mr. Stephen Abbey | C28: Kasoa, Millelium City | D28: Accra | E28: 0249029036 | F28: =UPPER(LEFT(B28,1)) & IFERROR(UPPER(LEFT(MID(B28,FIND(" ",B28)+1,LEN(B28)),1)),"") & IFERROR(UPPER(LEFT(MID(B28,FIND(" ",B28,FIND(" ",B28)+1)+1,LEN(B28)),1)),"") & IFERROR(UPPER(LEFT(MID(B28,FIND(" ",B28,FIND(" ",B28,FIND(" ",B28)+1)+1)+1,LEN(B28)),1)),"") -> MSA | O28: =IF(MOD($N$1,ROW())=0,ROW(),"") | P28: =IFERROR(LARGE(O$1:O$100, ROW()), "") | U28: =IF(MOD($T$500,ROW())=0,ROW(),"") -> 28
B29: Technoserve | C29: Teshie | D29: Accra | E29: 0269827541 | F29: =UPPER(LEFT(B29,1)) & IFERROR(UPPER(LEFT(MID(B29,FIND(" ",B29)+1,LEN(B29)),1)),"") & IFERROR(UPPER(LEFT(MID(B29,FIND(" ",B29,FIND(" ",B29)+1)+1,LEN(B29)),1)),"") & IFERROR(UPPER(LEFT(MID(B29,FIND(" ",B29,FIND(" ",B29,FIND(" ",B29)+1)+1)+1,LEN(B29)),1)),"") -> T | O29: =IF(MOD($N$1,ROW())=0,ROW(),"") | P29: =IFERROR(LARGE(O$1:O$100, ROW()), "") | U29: =IF(MOD($T$500,ROW())=0,ROW(),"") -> 29
B30: Don Bosco | C30: Tema | D30: Tema | E30: 0 | F30: =UPPER(LEFT(B30,1)) & IFERROR(UPPER(LEFT(MID(B30,FIND(" ",B30)+1,LEN(B30)),1)),"") & IFERROR(UPPER(LEFT(MID(B30,FIND(" ",B30,FIND(" ",B30)+1)+1,LEN(B30)),1)),"") & IFERROR(UPPER(LEFT(MID(B30,FIND(" ",B30,FIND(" ",B30,FIND(" ",B30)+1)+1)+1,LEN(B30)),1)),"") -> DB | O30: =IF(MOD($N$1,ROW())=0,ROW(),"") | P30: =IFERROR(LARGE(O$1:O$100, ROW()), "") | U30: =IF(MOD($T$500,ROW())=0,ROW(),"") -> 30
B31: Nana Ohene Gyan | C31: Airport Hills | D31: Accra | E31: 0502085511 | F31: =UPPER(LEFT(B31,1)) & IFERROR(UPPER(LEFT(MID(B31,FIND(" ",B31)+1,LEN(B31)),1)),"") & IFERROR(UPPER(LEFT(MID(B31,FIND(" ",B31,FIND(" ",B31)+1)+1,LEN(B31)),1)),"") & IFERROR(UPPER(LEFT(MID(B31,FIND(" ",B31,FIND(" ",B31,FIND(" ",B31)+1)+1)+1,LEN(B31)),1)),"") -> NOG | O31: =IF(MOD($N$1,ROW())=0,ROW(),"") | P31: =IFERROR(LARGE(O$1:O$100, ROW()), "") | U31: =IF(MOD($T$500,ROW())=0,ROW(),"") -> 31
B32: Toll Booth | C32: Pobiman | D32: Accra | E32: 0 | F32: =UPPER(LEFT(B32,1)) & IFERROR(UPPER(LEFT(MID(B32,FIND(" ",B32)+1,LEN(B32)),1)),"") & IFERROR(UPPER(LEFT(MID(B32,FIND(" ",B32,FIND(" ",B32)+1)+1,LEN(B32)),1)),"") & IFERROR(UPPER(LEFT(MID(B32,FIND(" ",B32,FIND(" ",B32,FIND(" ",B32)+1)+1)+1,LEN(B32)),1)),"") -> TB | O32: =IF(MOD($N$1,ROW())=0,ROW(),"") | P32: =IFERROR(LARGE(O$1:O$100, ROW()), "") | U32: =IF(MOD($T$500,ROW())=0,ROW(),"") -> 32
B33: Seth Kye | C33: Adjringanor | D33: Accra | E33: 0 | F33: =UPPER(LEFT(B33,1)) & IFERROR(UPPER(LEFT(MID(B33,FIND(" ",B33)+1,LEN(B33)),1)),"") & IFERROR(UPPER(LEFT(MID(B33,FIND(" ",B33,FIND(" ",B33)+1)+1,LEN(B33)),1)),"") & IFERROR(UPPER(LEFT(MID(B33,FIND(" ",B33,FIND(" ",B33,FIND(" ",B33)+1)+1)+1,LEN(B33)),1)),"") -> SK | O33: =IF(MOD($N$1,ROW())=0,ROW(),"") | P33: =IFERROR(LARGE(O$1:O$100, ROW()), "") | U33: =IF(MOD($T$500,ROW())=0,ROW(),"") -> 33
B34: Teabag Charity-(Mankoadze Vocational College) | C34: Mankoadze | D34: Winneba | E34: 0243202246 | F34: =UPPER(LEFT(B34,1)) & IFERROR(UPPER(LEFT(MID(B34,FIND(" ",B34)+1,LEN(B34)),1)),"") & IFERROR(UPPER(LEFT(MID(B34,FIND(" ",B34,FIND(" ",B34)+1)+1,LEN(B34)),1)),"") & IFERROR(UPPER(LEFT(MID(B34,FIND(" ",B34,FIND(" ",B34,FIND(" ",B34)+1)+1)+1,LEN(B34)),1)),"") -> TCVC | O34: =IF(MOD($N$1,ROW())=0,ROW(),"") | P34: =IFERROR(LARGE(O$1:O$100, ROW()), "") | U34: =IF(MOD($T$500,ROW())=0,ROW(),"") -> 34
B35: Pentecost Hospital | C35: Madina Estates | D35: Accra | E35: 0244667816 | F35: =UPPER(LEFT(B35,1)) & IFERROR(UPPER(LEFT(MID(B35,FIND(" ",B35)+1,LEN(B35)),1)),"") & IFERROR(UPPER(LEFT(MID(B35,FIND(" ",B35,FIND(" ",B35)+1)+1,LEN(B35)),1)),"") & IFERROR(UPPER(LEFT(MID(B35,FIND(" ",B35,FIND(" ",B35,FIND(" ",B35)+1)+1)+1,LEN(B35)),1)),"") -> PH | O35: =IF(MOD($N$1,ROW())=0,ROW(),"") | P35: =IFERROR(LARGE(O$1:O$100, ROW()), "") | U35: =IF(MOD($T$500,ROW())=0,ROW(),"") -> 35
B36: Col. Ivy Tamakloe | C36: Amrahia | D36: Accra | E36: 0273547715 / 0244729569 | F36: =UPPER(LEFT(B36,1)) & IFERROR(UPPER(LEFT(MID(B36,FIND(" ",B36)+1,LEN(B36)),1)),"") & IFERROR(UPPER(LEFT(MID(B36,FIND(" ",B36,FIND(" ",B36)+1)+1,LEN(B36)),1)),"") & IFERROR(UPPER(LEFT(MID(B36,FIND(" ",B36,FIND(" ",B36,FIND(" ",B36)+1)+1)+1,LEN(B36)),1)),"") -> CIT | O36: =IF(MOD($N$1,ROW())=0,ROW(),"") | P36: =IFERROR(LARGE(O$1:O$100, ROW()), "") | U36: =IF(MOD($T$500,ROW())=0,ROW(),"") -> 36
B37: Francis Digber | C37: No. 8 Kisseman crescent | D37: Accra | E37: 0208113062 | F37: =UPPER(LEFT(B37,1)) & IFERROR(UPPER(LEFT(MID(B37,FIND(" ",B37)+1,LEN(B37)),1)),"") & IFERROR(UPPER(LEFT(MID(B37,FIND(" ",B37,FIND(" ",B37)+1)+1,LEN(B37)),1)),"") & IFERROR(UPPER(LEFT(MID(B37,FIND(" ",B37,FIND(" ",B37,FIND(" ",B37)+1)+1)+1,LEN(B37)),1)),"") -> FD | O37: =IF(MOD($N$1,ROW())=0,ROW(),"") | P37: =IFERROR(LARGE(O$1:O$100, ROW()), "") | U37: =IF(MOD($T$500,ROW())=0,ROW(),"") -> 37
B38: Dr. Awudu Tinorgh | E38: 0269431524 | F38: =UPPER(LEFT(B38,1)) & IFERROR(UPPER(LEFT(MID(B38,FIND(" ",B38)+1,LEN(B38)),1)),"") & IFERROR(UPPER(LEFT(MID(B38,FIND(" ",B38,FIND(" ",B38)+1)+1,LEN(B38)),1)),"") & IFERROR(UPPER(LEFT(MID(B38,FIND(" ",B38,FIND(" ",B38,FIND(" ",B38)+1)+1)+1,LEN(B38)),1)),"") -> DAT | O38: =IF(MOD($N$1,ROW())=0,ROW(),"") | P38: =IFERROR(LARGE(O$1:O$100, ROW()), "") | U38: =IF(MOD($T$500,ROW())=0,ROW(),"") -> 38
B39: Mr. Senyo Amengo | E39: 0208303920 | F39: =UPPER(LEFT(B39,1)) & IFERROR(UPPER(LEFT(MID(B39,FIND(" ",B39)+1,LEN(B39)),1)),"") & IFERROR(UPPER(LEFT(MID(B39,FIND(" ",B39,FIND(" ",B39)+1)+1,LEN(B39)),1)),"") & IFERROR(UPPER(LEFT(MID(B39,FIND(" ",B39,FIND(" ",B39,FIND(" ",B39)+1)+1)+1,LEN(B39)),1)),"") -> MSA | O39: =IF(MOD($N$1,ROW())=0,ROW(),"") | P39: =IFERROR(LARGE(O$1:O$100, ROW()), "") | U39: =IF(MOD($T$500,ROW())=0,ROW(),"") -> 39
B40: Life Forms Limited | C40: Labone | D40: Accra | E40: 0268666838 | F40: =UPPER(LEFT(B40,1)) & IFERROR(UPPER(LEFT(MID(B40,FIND(" ",B40)+1,LEN(B40)),1)),"") & IFERROR(UPPER(LEFT(MID(B40,FIND(" ",B40,FIND(" ",B40)+1)+1,LEN(B40)),1)),"") & IFERROR(UPPER(LEFT(MID(B40,FIND(" ",B40,FIND(" ",B40,FIND(" ",B40)+1)+1)+1,LEN(B40)),1)),"") -> LFL | O40: =IF(MOD($N$1,ROW())=0,ROW(),"") | P40: =IFERROR(LARGE(O$1:O$100, ROW()), "") | U40: =IF(MOD($T$500,ROW())=0,ROW(),"") -> 40
B41: Mr. Francis Dancan | C41: Pokuase | D41: Accra | E41: 0208887879 | F41: =UPPER(LEFT(B41,1)) & IFERROR(UPPER(LEFT(MID(B41,FIND(" ",B41)+1,LEN(B41)),1)),"") & IFERROR(UPPER(LEFT(MID(B41,FIND(" ",B41,FIND(" ",B41)+1)+1,LEN(B41)),1)),"") & IFERROR(UPPER(LEFT(MID(B41,FIND(" ",B41,FIND(" ",B41,FIND(" ",B41)+1)+1)+1,LEN(B41)),1)),"") -> MFD | O41: =IF(MOD($N$1,ROW())=0,ROW(),"") | P41: =IFERROR(LARGE(O$1:O$100, ROW()), "") | U41: =IF(MOD($T$500,ROW())=0,ROW(),"") -> 41
B42: Dr. Quartey | C42: Pokuase, ACP Estates | D42: Accra | E42: 0262012364 | F42: =UPPER(LEFT(B42,1)) & IFERROR(UPPER(LEFT(MID(B42,FIND(" ",B42)+1,LEN(B42)),1)),"") & IFERROR(UPPER(LEFT(MID(B42,FIND(" ",B42,FIND(" ",B42)+1)+1,LEN(B42)),1)),"") & IFERROR(UPPER(LEFT(MID(B42,FIND(" ",B42,FIND(" ",B42,FIND(" ",B42)+1)+1)+1,LEN(B42)),1)),"") -> DQ | O42: =IF(MOD($N$1,ROW())=0,ROW(),"") | P42: =IFERROR(LARGE(O$1:O$100, ROW()), "") | U42: =IF(MOD($T$500,ROW())=0,ROW(),"") -> 42
B43: Mad. Susana Otchere | C43: North Kaneshie | D43: Accra | E43: 0208110033 | F43: =UPPER(LEFT(B43,1)) & IFERROR(UPPER(LEFT(MID(B43,FIND(" ",B43)+1,LEN(B43)),1)),"") & IFERROR(UPPER(LEFT(MID(B43,FIND(" ",B43,FIND(" ",B43)+1)+1,LEN(B43)),1)),"") & IFERROR(UPPER(LEFT(MID(B43,FIND(" ",B43,FIND(" ",B43,FIND(" ",B43)+1)+1)+1,LEN(B43)),1)),"") -> MSO | O43: =IF(MOD($N$1,ROW())=0,ROW(),"") | P43: =IFERROR(LARGE(O$1:O$100, ROW()), "") | U43: =IF(MOD($T$500,ROW())=0,ROW(),"") -> 43
B44: Mr. Richmond Amartey | C44: Tema, Community 18 | D44: Tema | E44: 0208198308 | F44: =UPPER(LEFT(B44,1)) & IFERROR(UPPER(LEFT(MID(B44,FIND(" ",B44)+1,LEN(B44)),1)),"") & IFERROR(UPPER(LEFT(MID(B44,FIND(" ",B44,FIND(" ",B44)+1)+1,LEN(B44)),1)),"") & IFERROR(UPPER(LEFT(MID(B44,FIND(" ",B44,FIND(" ",B44,FIND(" ",B44)+1)+1)+1,LEN(B44)),1)),"") -> MRA | O44: =IF(MOD($N$1,ROW())=0,ROW(),"") | P44: =IFERROR(LARGE(O$1:O$100, ROW()), "") | U44: =IF(MOD($T$500,ROW())=0,ROW(),"") -> 44
B45: Col. Akorful | C45: Ashiyie | D45: Accra | E45: 0244313491 | F45: =UPPER(LEFT(B45,1)) & IFERROR(UPPER(LEFT(MID(B45,FIND(" ",B45)+1,LEN(B45)),1)),"") & IFERROR(UPPER(LEFT(MID(B45,FIND(" ",B45,FIND(" ",B45)+1)+1,LEN(B45)),1)),"") & IFERROR(UPPER(LEFT(MID(B45,FIND(" ",B45,FIND(" ",B45,FIND(" ",B45)+1)+1)+1,LEN(B45)),1)),"") -> CA | O45: =IF(MOD($N$1,ROW())=0,ROW(),"") | P45: =IFERROR(LARGE(O$1:O$100, ROW()), "") | U45: =IF(MOD($T$500,ROW())=0,ROW(),"") -> 45
B46: Mr. John Akonful | C46: Spintex | D46: Accra | E46: 0208180445 | F46: =UPPER(LEFT(B46,1)) & IFERROR(UPPER(LEFT(MID(B46,FIND(" ",B46)+1,LEN(B46)),1)),"") & IFERROR(UPPER(LEFT(MID(B46,FIND(" ",B46,FIND(" ",B46)+1)+1,LEN(B46)),1)),"") & IFERROR(UPPER(LEFT(MID(B46,FIND(" ",B46,FIND(" ",B46,FIND(" ",B46)+1)+1)+1,LEN(B46)),1)),"") -> MJA | O46: =IF(MOD($N$1,ROW())=0,ROW(),"") | P46: =IFERROR(LARGE(O$1:O$100, ROW()), "") | U46: =IF(MOD($T$500,ROW())=0,ROW(),"") -> 46
B47: UNHCR Hospital | C47: Fetentaa | D47: Sunyani | E47: 0 | F47: =UPPER(LEFT(B47,1)) & IFERROR(UPPER(LEFT(MID(B47,FIND(" ",B47)+1,LEN(B47)),1)),"") & IFERROR(UPPER(LEFT(MID(B47,FIND(" ",B47,FIND(" ",B47)+1)+1,LEN(B47)),1)),"") & IFERROR(UPPER(LEFT(MID(B47,FIND(" ",B47,FIND(" ",B47,FIND(" ",B47)+1)+1)+1,LEN(B47)),1)),"") -> UH | O47: =IF(MOD($N$1,ROW())=0,ROW(),"") | P47: =IFERROR(LARGE(O$1:O$100, ROW()), "") | U47: =IF(MOD($T$500,ROW())=0,ROW(),"") -> 47
B48: UNHCR | C48: Ampain | D48: Takoradi | E48: 0 | F48: =UPPER(LEFT(B48,1)) & IFERROR(UPPER(LEFT(MID(B48,FIND(" ",B48)+1,LEN(B48)),1)),"") & IFERROR(UPPER(LEFT(MID(B48,FIND(" ",B48,FIND(" ",B48)+1)+1,LEN(B48)),1)),"") & IFERROR(UPPER(LEFT(MID(B48,FIND(" ",B48,FIND(" ",B48,FIND(" ",B48)+1)+1)+1,LEN(B48)),1)),"") -> U | O48: =IF(MOD($N$1,ROW())=0,ROW(),"") | P48: =IFERROR(LARGE(O$1:O$100, ROW()), "") | U48: =IF(MOD($T$500,ROW())=0,ROW(),"") -> 48
B49: ECOBANK, Harper Road | C49: Harper Road, Kumasi | D49: Kumasi | E49: 0 | F49: =UPPER(LEFT(B49,1)) & IFERROR(UPPER(LEFT(MID(B49,FIND(" ",B49)+1,LEN(B49)),1)),"") & IFERROR(UPPER(LEFT(MID(B49,FIND(" ",B49,FIND(" ",B49)+1)+1,LEN(B49)),1)),"") & IFERROR(UPPER(LEFT(MID(B49,FIND(" ",B49,FIND(" ",B49,FIND(" ",B49)+1)+1)+1,LEN(B49)),1)),"") -> EHR | O49: =IF(MOD($N$1,ROW())=0,ROW(),"") | P49: =IFERROR(LARGE(O$1:O$100, ROW()), "") | U49: =IF(MOD($T$500,ROW())=0,ROW(),"") -> 49
B50: ECOBANK, Kwabenya | C50: Kwabenya | D50: Accra | E50: 0 | F50: =UPPER(LEFT(B50,1)) & IFERROR(UPPER(LEFT(MID(B50,FIND(" ",B50)+1,LEN(B50)),1)),"") & IFERROR(UPPER(LEFT(MID(B50,FIND(" ",B50,FIND(" ",B50)+1)+1,LEN(B50)),1)),"") & IFERROR(UPPER(LEFT(MID(B50,FIND(" ",B50,FIND(" ",B50,FIND(" ",B50)+1)+1)+1,LEN(B50)),1)),"") -> EK | O50: =IF(MOD($N$1,ROW())=0,ROW(),"") | P50: =IFERROR(LARGE(O$1:O$100, ROW()), "") | U50: =IF(MOD($T$500,ROW())=0,ROW(),"") -> 50
B51: ECOBANK, Tudu | C51: Tudu | D51: Accra | E51: 0 | F51: =UPPER(LEFT(B51,1)) & IFERROR(UPPER(LEFT(MID(B51,FIND(" ",B51)+1,LEN(B51)),1)),"") & IFERROR(UPPER(LEFT(MID(B51,FIND(" ",B51,FIND(" ",B51)+1)+1,LEN(B51)),1)),"") & IFERROR(UPPER(LEFT(MID(B51,FIND(" ",B51,FIND(" ",B51,FIND(" ",B51)+1)+1)+1,LEN(B51)),1)),"") -> ET | O51: =IF(MOD($N$1,ROW())=0,ROW(),"") | P51: =IFERROR(LARGE(O$1:O$100, ROW()), "") | U51: =IF(MOD($T$500,ROW())=0,ROW(),"") -> 51
B52: ECOBANK, Kwashieman | C52: Kwashieman | D52: Accra | E52: 0 | F52: =UPPER(LEFT(B52,1)) & IFERROR(UPPER(LEFT(MID(B52,FIND(" ",B52)+1,LEN(B52)),1)),"") & IFERROR(UPPER(LEFT(MID(B52,FIND(" ",B52,FIND(" ",B52)+1)+1,LEN(B52)),1)),"") & IFERROR(UPPER(LEFT(MID(B52,FIND(" ",B52,FIND(" ",B52,FIND(" ",B52)+1)+1)+1,LEN(B52)),1)),"") -> EK | O52: =IF(MOD($N$1,ROW())=0,ROW(),"") | P52: =IFERROR(LARGE(O$1:O$100, ROW()), "") | U52: =IF(MOD($T$500,ROW())=0,ROW(),"") -> 52
B53: Jacob Aguda | C53: Amarmoley | D53: Accra | E53: 0244602960 | F53: =UPPER(LEFT(B53,1)) & IFERROR(UPPER(LEFT(MID(B53,FIND(" ",B53)+1,LEN(B53)),1)),"") & IFERROR(UPPER(LEFT(MID(B53,FIND(" ",B53,FIND(" ",B53)+1)+1,LEN(B53)),1)),"") & IFERROR(UPPER(LEFT(MID(B53,FIND(" ",B53,FIND(" ",B53,FIND(" ",B53)+1)+1)+1,LEN(B53)),1)),"") -> JA | O53: =IF(MOD($N$1,ROW())=0,ROW(),"") | P53: =IFERROR(LARGE(O$1:O$100, ROW()), "") | U53: =IF(MOD($T$500,ROW())=0,ROW(),"") -> 53
B54: Mad. Esther Percy | C54: Tema, Community 18 | D54: Tema | E54: 0277402353 | F54: =UPPER(LEFT(B54,1)) & IFERROR(UPPER(LEFT(MID(B54,FIND(" ",B54)+1,LEN(B54)),1)),"") & IFERROR(UPPER(LEFT(MID(B54,FIND(" ",B54,FIND(" ",B54)+1)+1,LEN(B54)),1)),"") & IFERROR(UPPER(LEFT(MID(B54,FIND(" ",B54,FIND(" ",B54,FIND(" ",B54)+1)+1)+1,LEN(B54)),1)),"") -> MEP | O54: =IF(MOD($N$1,ROW())=0,ROW(),"") | P54: =IFERROR(LARGE(O$1:O$100, ROW()), "") | U54: =IF(MOD($T$500,ROW())=0,ROW(),"") -> 54
B55: Cheki Ghana | C55: East Legon | D55: Accra | E55: 0242077030 | F55: =UPPER(LEFT(B55,1)) & IFERROR(UPPER(LEFT(MID(B55,FIND(" ",B55)+1,LEN(B55)),1)),"") & IFERROR(UPPER(LEFT(MID(B55,FIND(" ",B55,FIND(" ",B55)+1)+1,LEN(B55)),1)),"") & IFERROR(UPPER(LEFT(MID(B55,FIND(" ",B55,FIND(" ",B55,FIND(" ",B55)+1)+1)+1,LEN(B55)),1)),"") -> CG | O55: =IF(MOD($N$1,ROW())=0,ROW(),"") | P55: =IFERROR(LARGE(O$1:O$100, ROW()), "") | U55: =IF(MOD($T$500,ROW())=0,ROW(),"") -> 55
B56: Mr. Eric Amoako-Twum | C56: East Legon | D56: Accra | E56: 0202097989 | F56: =UPPER(LEFT(B56,1)) & IFERROR(UPPER(LEFT(MID(B56,FIND(" ",B56)+1,LEN(B56)),1)),"") & IFERROR(UPPER(LEFT(MID(B56,FIND(" ",B56,FIND(" ",B56)+1)+1,LEN(B56)),1)),"") & IFERROR(UPPER(LEFT(MID(B56,FIND(" ",B56,FIND(" ",B56,FIND(" ",B56)+1)+1)+1,LEN(B56)),1)),"") -> MEA | O56: =IF(MOD($N$1,ROW())=0,ROW(),"") | P56: =IFERROR(LARGE(O$1:O$100, ROW()), "") | U56: =IF(MOD($T$500,ROW())=0,ROW(),"") -> 56
B57: Mr. Richard Torku | C57: Botwe | D57: Accra | E57: 0242732899 | F57: =UPPER(LEFT(B57,1)) & IFERROR(UPPER(LEFT(MID(B57,FIND(" ",B57)+1,LEN(B57)),1)),"") & IFERROR(UPPER(LEFT(MID(B57,FIND(" ",B57,FIND(" ",B57)+1)+1,LEN(B57)),1)),"") & IFERROR(UPPER(LEFT(MID(B57,FIND(" ",B57,FIND(" ",B57,FIND(" ",B57)+1)+1)+1,LEN(B57)),1)),"") -> MRT | O57: =IF(MOD($N$1,ROW())=0,ROW(),"") | P57: =IFERROR(LARGE(O$1:O$100, ROW()), "") | U57: =IF(MOD($T$500,ROW())=0,ROW(),"") -> 57
B58: Joojo | C58: Tema | D58: Accra | E58: 0244656550 | F58: =UPPER(LEFT(B58,1)) & IFERROR(UPPER(LEFT(MID(B58,FIND(" ",B58)+1,LEN(B58)),1)),"") & IFERROR(UPPER(LEFT(MID(B58,FIND(" ",B58,FIND(" ",B58)+1)+1,LEN(B58)),1)),"") & IFERROR(UPPER(LEFT(MID(B58,FIND(" ",B58,FIND(" ",B58,FIND(" ",B58)+1)+1)+1,LEN(B58)),1)),"") -> J | O58: =IF(MOD($N$1,ROW())=0,ROW(),"") | P58: =IFERROR(LARGE(O$1:O$100, ROW()), "") | U58: =IF(MOD($T$500,ROW())=0,ROW(),"") -> 58
B59: Mamadu Saidu Camara | C59: Dzorwulu | D59: Accra | E59: 0545515581 | F59: =UPPER(LEFT(B59,1)) & IFERROR(UPPER(LEFT(MID(B59,FIND(" ",B59)+1,LEN(B59)),1)),"") & IFERROR(UPPER(LEFT(MID(B59,FIND(" ",B59,FIND(" ",B59)+1)+1,LEN(B59)),1)),"") & IFERROR(UPPER(LEFT(MID(B59,FIND(" ",B59,FIND(" ",B59,FIND(" ",B59)+1)+1)+1,LEN(B59)),1)),"") -> MSC | O59: =IF(MOD($N$1,ROW())=0,ROW(),"") | P59: =IFERROR(LARGE(O$1:O$100, ROW()), "") | U59: =IF(MOD($T$500,ROW())=0,ROW(),"") -> 59
B60: Mark | C60: Kwabenya | D60: Accra | E60: 0545515581 | F60: =UPPER(LEFT(B60,1)) & IFERROR(UPPER(LEFT(MID(B60,FIND(" ",B60)+1,LEN(B60)),1)),"") & IFERROR(UPPER(LEFT(MID(B60,FIND(" ",B60,FIND(" ",B60)+1)+1,LEN(B60)),1)),"") & IFERROR(UPPER(LEFT(MID(B60,FIND(" ",B60,FIND(" ",B60,FIND(" ",B60)+1)+1)+1,LEN(B60)),1)),"") -> M | O60: =IF(MOD($N$1,ROW())=0,ROW(),"") | P60: =IFERROR(LARGE(O$1:O$100, ROW()), "") | U60: =IF(MOD($T$500,ROW())=0,ROW(),"") -> 60
B61: Mr. Andrew Bodom | C61: Tema, Golf City | D61: Tema | E61: 0244711696 | F61: =UPPER(LEFT(B61,1)) & IFERROR(UPPER(LEFT(MID(B61,FIND(" ",B61)+1,LEN(B61)),1)),"") & IFERROR(UPPER(LEFT(MID(B61,FIND(" ",B61,FIND(" ",B61)+1)+1,LEN(B61)),1)),"") & IFERROR(UPPER(LEFT(MID(B61,FIND(" ",B61,FIND(" ",B61,FIND(" ",B61)+1)+1)+1,LEN(B61)),1)),"") -> MAB | O61: =IF(MOD($N$1,ROW())=0,ROW(),"") | P61: =IFERROR(LARGE(O$1:O$100, ROW()), "") | U61: =IF(MOD($T$500,ROW())=0,ROW(),"") -> 61
B62: Sofo Ali | C62: Kwabenya / Dansoman | D62: Accra | E62: 0203321586 | F62: =UPPER(LEFT(B62,1)) & IFERROR(UPPER(LEFT(MID(B62,FIND(" ",B62)+1,LEN(B62)),1)),"") & IFERROR(UPPER(LEFT(MID(B62,FIND(" ",B62,FIND(" ",B62)+1)+1,LEN(B62)),1)),"") & IFERROR(UPPER(LEFT(MID(B62,FIND(" ",B62,FIND(" ",B62,FIND(" ",B62)+1)+1)+1,LEN(B62)),1)),"") -> SA | O62: =IF(MOD($N$1,ROW())=0,ROW(),"") | P62: =IFERROR(LARGE(O$1:O$100, ROW()), "") | U62: =IF(MOD($T$500,ROW())=0,ROW(),"") -> 62
B63: Stella Tagoe | C63: Spintex | D63: Accra | E63: 0206629048 | F63: =UPPER(LEFT(B63,1)) & IFERROR(UPPER(LEFT(MID(B63,FIND(" ",B63)+1,LEN(B63)),1)),"") & IFERROR(UPPER(LEFT(MID(B63,FIND(" ",B63,FIND(" ",B63)+1)+1,LEN(B63)),1)),"") & IFERROR(UPPER(LEFT(MID(B63,FIND(" ",B63,FIND(" ",B63,FIND(" ",B63)+1)+1)+1,LEN(B63)),1)),"") -> ST | O63: =IF(MOD($N$1,ROW())=0,ROW(),"") | P63: =IFERROR(LARGE(O$1:O$100, ROW()), "") | U63: =IF(MOD($T$500,ROW())=0,ROW(),"") -> 63
B64: Ama | C64: Abelenkpe | D64: Accra | E64: 0202518318 0244136281 | F64: =UPPER(LEFT(B64,1)) & IFERROR(UPPER(LEFT(MID(B64,FIND(" ",B64)+1,LEN(B64)),1)),"") & IFERROR(UPPER(LEFT(MID(B64,FIND(" ",B64,FIND(" ",B64)+1)+1,LEN(B64)),1)),"") & IFERROR(UPPER(LEFT(MID(B64,FIND(" ",B64,FIND(" ",B64,FIND(" ",B64)+1)+1)+1,LEN(B64)),1)),"") -> A | O64: =IF(MOD($N$1,ROW())=0,ROW(),"") | P64: =IFERROR(LARGE(O$1:O$100, ROW()), "") | U64: =IF(MOD($T$500,ROW())=0,ROW(),"") -> 64
... B99: Owusu Gabriel | C99: Afienya - Mataheko | D99: Accra | E99: 0244650656 | F99: =UPPER(LEFT(B99,1)) & IFERROR(UPPER(LEFT(MID(B99,FIND(" ",B99)+1,LEN(B99)),1)),"") & IFERROR(UPPER(LEFT(MID(B99,FIND(" ",B99,FIND(" ",B99)+1)+1,LEN(B99)),1)),"") & IFERROR(UPPER(LEFT(MID(B99,FIND(" ",B99,FIND(" ",B99,FIND(" ",B99)+1)+1)+1,LEN(B99)),1)),"") -> OG | O99: =IF(MOD($N$1,ROW())=0,ROW(),"") | P99: =IFERROR(LARGE(O$1:O$100, ROW()), "") | U99: =IF(MOD($T$500,ROW())=0,ROW(),"") -> 99
B100: Nestle Ghana Business Center | C100: Tema, Community 1 | D100: Tema | E100: 0248707010 | F100: =UPPER(LEFT(B100,1)) & IFERROR(UPPER(LEFT(MID(B100,FIND(" ",B100)+1,LEN(B100)),1)),"") & IFERROR(UPPER(LEFT(MID(B100,FIND(" ",B100,FIND(" ",B100)+1)+1,LEN(B100)),1)),"") & IFERROR(UPPER(LEFT(MID(B100,FIND(" ",B100,FIND(" ",B100,FIND(" ",B100)+1)+1)+1,LEN(B100)),1)),"") -> NGBC | G100: Mahmudu Zakari | O100: =IF(MOD($N$1,ROW())=0,ROW(),"") | P100: =IFERROR(LARGE(O$1:O$100, ROW()), "") | U100: =IF(MOD($T$500,ROW())=0,ROW(),"") -> 100
B101: Nestle Ghana Factory 24V/1.2kVA (002) | C101: Tema | D101: Tema | E101: 0248707010 | F101: =UPPER(LEFT(B101,1)) & IFERROR(UPPER(LEFT(MID(B101,FIND(" ",B101)+1,LEN(B101)),1)),"") & IFERROR(UPPER(LEFT(MID(B101,FIND(" ",B101,FIND(" ",B101)+1)+1,LEN(B101)),1)),"") & IFERROR(UPPER(LEFT(MID(B101,FIND(" ",B101,FIND(" ",B101,FIND(" ",B101)+1)+1)+1,LEN(B101)),1)),"") -> NGF2 | U101: =IF(MOD($T$500,ROW())=0,ROW(),"") -> 101
B102: Nestle Ghana Factory 48V/3kVA (002) | C102: Tema | D102: Tema | E102: 0248707010 | F102: =UPPER(LEFT(B102,1)) & IFERROR(UPPER(LEFT(MID(B102,FIND(" ",B102)+1,LEN(B102)),1)),"") & IFERROR(UPPER(LEFT(MID(B102,FIND(" ",B102,FIND(" ",B102)+1)+1,LEN(B102)),1)),"") & IFERROR(UPPER(LEFT(MID(B102,FIND(" ",B102,FIND(" ",B102,FIND(" ",B102)+1)+1)+1,LEN(B102)),1)),"") -> NGF4
B103: Nestle Ghana 24V/3KVA (004) | C103: Tema | D103: Tema | E103: 0248707010 | F103: =UPPER(LEFT(B103,1)) & IFERROR(UPPER(LEFT(MID(B103,FIND(" ",B103)+1,LEN(B103)),1)),"") & IFERROR(UPPER(LEFT(MID(B103,FIND(" ",B103,FIND(" ",B103)+1)+1,LEN(B103)),1)),"") & IFERROR(UPPER(LEFT(MID(B103,FIND(" ",B103,FIND(" ",B103,FIND(" ",B103)+1)+1)+1,LEN(B103)),1)),"") -> NG2(
B104: Nestle Ghana 24V/350VA (006) Warehouse | C104: Tema | D104: Tema | E104: 0246283848 | F104: =UPPER(LEFT(B104,1)) & IFERROR(UPPER(LEFT(MID(B104,FIND(" ",B104)+1,LEN(B104)),1)),"") & IFERROR(UPPER(LEFT(MID(B104,FIND(" ",B104,FIND(" ",B104)+1)+1,LEN(B104)),1)),"") & IFERROR(UPPER(LEFT(MID(B104,FIND(" ",B104,FIND(" ",B104,FIND(" ",B104)+1)+1)+1,LEN(B104)),1)),"") -> NG2(
B105: Nestle Ghana / EasySolar 48V/3kVA (006) Noble Warehouse | C105: Tema | D105: Tema | F105: =UPPER(LEFT(B105,1)) & IFERROR(UPPER(LEFT(MID(B105,FIND(" ",B105)+1,LEN(B105)),1)),"") & IFERROR(UPPER(LEFT(MID(B105,FIND(" ",B105,FIND(" ",B105)+1)+1,LEN(B105)),1)),"") & IFERROR(UPPER(LEFT(MID(B105,FIND(" ",B105,FIND(" ",B105,FIND(" ",B105)+1)+1)+1,LEN(B105)),1)),"") -> NG/E
B106: Nestle Ghana 48V/5KVA (003) | C106: Tema | D106: Tema | E106: 0246283848 | F106: =UPPER(LEFT(B106,1)) & IFERROR(UPPER(LEFT(MID(B106,FIND(" ",B106)+1,LEN(B106)),1)),"") & IFERROR(UPPER(LEFT(MID(B106,FIND(" ",B106,FIND(" ",B106)+1)+1,LEN(B106)),1)),"") & IFERROR(UPPER(LEFT(MID(B106,FIND(" ",B106,FIND(" ",B106,FIND(" ",B106)+1)+1)+1,LEN(B106)),1)),"") -> NG4(
B107: Nestle Ghana 48V/5KVA (001) | C107: Tema | D107: Tema | E107: 0246283848 | F107: =UPPER(LEFT(B107,1)) & IFERROR(UPPER(LEFT(MID(B107,FIND(" ",B107)+1,LEN(B107)),1)),"") & IFERROR(UPPER(LEFT(MID(B107,FIND(" ",B107,FIND(" ",B107)+1)+1,LEN(B107)),1)),"") & IFERROR(UPPER(LEFT(MID(B107,FIND(" ",B107,FIND(" ",B107,FIND(" ",B107)+1)+1)+1,LEN(B107)),1)),"") -> NG4(
B108: Nestle Ghana 48V/5kVA LMI - Warehouse | C108: Tema | D108: Tema | E108: 0501260482 | F108: =UPPER(LEFT(B108,1)) & IFERROR(UPPER(LEFT(MID(B108,FIND(" ",B108)+1,LEN(B108)),1)),"") & IFERROR(UPPER(LEFT(MID(B108,FIND(" ",B108,FIND(" ",B108)+1)+1,LEN(B108)),1)),"") & IFERROR(UPPER(LEFT(MID(B108,FIND(" ",B108,FIND(" ",B108,FIND(" ",B108)+1)+1)+1,LEN(B108)),1)),"") -> NG4L
B109: Nestle Ghana Limited, Head office 1.2KVA (009) | C109: Dzorwulu | D109: Accra | E109: 0501260482 | F109: =UPPER(LEFT(B109,1)) & IFERROR(UPPER(LEFT(MID(B109,FIND(" ",B109)+1,LEN(B109)),1)),"") & IFERROR(UPPER(LEFT(MID(B109,FIND(" ",B109,FIND(" ",B109)+1)+1,LEN(B109)),1)),"") & IFERROR(UPPER(LEFT(MID(B109,FIND(" ",B109,FIND(" ",B109,FIND(" ",B109)+1)+1)+1,LEN(B109)),1)),"") -> NGLH
B110: Nestle Ghana Limited, Head office 1.6KVA (008) | C110: Dzorwulu | D110: Accra | E110: 0501260482 | F110: =UPPER(LEFT(B110,1)) & IFERROR(UPPER(LEFT(MID(B110,FIND(" ",B110)+1,LEN(B110)),1)),"") & IFERROR(UPPER(LEFT(MID(B110,FIND(" ",B110,FIND(" ",B110)+1)+1,LEN(B110)),1)),"") & IFERROR(UPPER(LEFT(MID(B110,FIND(" ",B110,FIND(" ",B110,FIND(" ",B110)+1)+1)+1,LEN(B110)),1)),"") -> NGLH
B111: Nestle Ghana Limited, Head office 5KVA - Server Room (007) | C111: Dzorwulu | D111: Accra | E111: 0501260482 | F111: =UPPER(LEFT(B111,1)) & IFERROR(UPPER(LEFT(MID(B111,FIND(" ",B111)+1,LEN(B111)),1)),"") & IFERROR(UPPER(LEFT(MID(B111,FIND(" ",B111,FIND(" ",B111)+1)+1,LEN(B111)),1)),"") & IFERROR(UPPER(LEFT(MID(B111,FIND(" ",B111,FIND(" ",B111,FIND(" ",B111)+1)+1)+1,LEN(B111)),1)),"") -> NGLH
B112: Don Bosco Solar Training | C112: Ashaiman | D112: Accra | E112: 0268731202 | F112: =UPPER(LEFT(B112,1)) & IFERROR(UPPER(LEFT(MID(B112,FIND(" ",B112)+1,LEN(B112)),1)),"") & IFERROR(UPPER(LEFT(MID(B112,FIND(" ",B112,FIND(" ",B112)+1)+1,LEN(B112)),1)),"") & IFERROR(UPPER(LEFT(MID(B112,FIND(" ",B112,FIND(" ",B112,FIND(" ",B112)+1)+1)+1,LEN(B112)),1)),"") -> DBST
B113: Lawyer Thomas Acquah | C113: Tema, Community 18 | D113: Tema | E113: 0245390468 | F113: =UPPER(LEFT(B113,1)) & IFERROR(UPPER(LEFT(MID(B113,FIND(" ",B113)+1,LEN(B113)),1)),"") & IFERROR(UPPER(LEFT(MID(B113,FIND(" ",B113,FIND(" ",B113)+1)+1,LEN(B113)),1)),"") & IFERROR(UPPER(LEFT(MID(B113,FIND(" ",B113,FIND(" ",B113,FIND(" ",B113)+1)+1)+1,LEN(B113)),1)),"") -> LTA
B114: Elsie Yaokumah | C114: Oyibi, Ayensu River Estates | D114: Accra | E114: 0208250428 | F114: =UPPER(LEFT(B114,1)) & IFERROR(UPPER(LEFT(MID(B114,FIND(" ",B114)+1,LEN(B114)),1)),"") & IFERROR(UPPER(LEFT(MID(B114,FIND(" ",B114,FIND(" ",B114)+1)+1,LEN(B114)),1)),"") & IFERROR(UPPER(LEFT(MID(B114,FIND(" ",B114,FIND(" ",B114,FIND(" ",B114)+1)+1)+1,LEN(B114)),1)),"") -> EY
B115: Elsie Yaokumah - Afienya | C115: Afienya | D115: Tema | E115: 0208178946 | F115: =UPPER(LEFT(B115,1)) & IFERROR(UPPER(LEFT(MID(B115,FIND(" ",B115)+1,LEN(B115)),1)),"") & IFERROR(UPPER(LEFT(MID(B115,FIND(" ",B115,FIND(" ",B115)+1)+1,LEN(B115)),1)),"") & IFERROR(UPPER(LEFT(MID(B115,FIND(" ",B115,FIND(" ",B115,FIND(" ",B115)+1)+1)+1,LEN(B115)),1)),"") -> EY-A
B116: Derek Tengey | C116: Ashale Botwe | D116: Accra | E116: 0244028812 | F116: =UPPER(LEFT(B116,1)) & IFERROR(UPPER(LEFT(MID(B116,FIND(" ",B116)+1,LEN(B116)),1)),"") & IFERROR(UPPER(LEFT(MID(B116,FIND(" ",B116,FIND(" ",B116)+1)+1,LEN(B116)),1)),"") & IFERROR(UPPER(LEFT(MID(B116,FIND(" ",B116,FIND(" ",B116,FIND(" ",B116)+1)+1)+1,LEN(B116)),1)),"") -> DT
B117: Nana Adjekum | C117: Sakumono | D117: Accra | E117: 0248245171 | F117: =UPPER(LEFT(B117,1)) & IFERROR(UPPER(LEFT(MID(B117,FIND(" ",B117)+1,LEN(B117)),1)),"") & IFERROR(UPPER(LEFT(MID(B117,FIND(" ",B117,FIND(" ",B117)+1)+1,LEN(B117)),1)),"") & IFERROR(UPPER(LEFT(MID(B117,FIND(" ",B117,FIND(" ",B117,FIND(" ",B117)+1)+1)+1,LEN(B117)),1)),"") -> NA
... B124: Albert Tackie | C124: West Hills, Weija | D124: Accra | E124: 0244265024 | F124: =UPPER(LEFT(B124,1)) & IFERROR(UPPER(LEFT(MID(B124,FIND(" ",B124)+1,LEN(B124)),1)),"") & IFERROR(UPPER(LEFT(MID(B124,FIND(" ",B124,FIND(" ",B124)+1)+1,LEN(B124)),1)),"") & IFERROR(UPPER(LEFT(MID(B124,FIND(" ",B124,FIND(" ",B124,FIND(" ",B124)+1)+1)+1,LEN(B124)),1)),"") -> AT
B125: ECOBANK, Tamale | C125: Tamale | D125: Tamale | E125: 0 | F125: =UPPER(LEFT(B125,1)) & IFERROR(UPPER(LEFT(MID(B125,FIND(" ",B125)+1,LEN(B125)),1)),"") & IFERROR(UPPER(LEFT(MID(B125,FIND(" ",B125,FIND(" ",B125)+1)+1,LEN(B125)),1)),"") & IFERROR(UPPER(LEFT(MID(B125,FIND(" ",B125,FIND(" ",B125,FIND(" ",B125)+1)+1)+1,LEN(B125)),1)),"") -> ET
B126: Francis Ahlidza | C126: Danfa | D126: Accra | E126: 0208178730 | F126: =UPPER(LEFT(B126,1)) & IFERROR(UPPER(LEFT(MID(B126,FIND(" ",B126)+1,LEN(B126)),1)),"") & IFERROR(UPPER(LEFT(MID(B126,FIND(" ",B126,FIND(" ",B126)+1)+1,LEN(B126)),1)),"") & IFERROR(UPPER(LEFT(MID(B126,FIND(" ",B126,FIND(" ",B126,FIND(" ",B126)+1)+1)+1,LEN(B126)),1)),"") -> FA
B127: Kofi Agyen | C127: Trasacco | D127: Accra | E127: 0240205719 / 0209011284 | F127: =UPPER(LEFT(B127,1)) & IFERROR(UPPER(LEFT(MID(B127,FIND(" ",B127)+1,LEN(B127)),1)),"") & IFERROR(UPPER(LEFT(MID(B127,FIND(" ",B127,FIND(" ",B127)+1)+1,LEN(B127)),1)),"") & IFERROR(UPPER(LEFT(MID(B127,FIND(" ",B127,FIND(" ",B127,FIND(" ",B127)+1)+1)+1,LEN(B127)),1)),"") -> KA
B128: Mr. Franklin Eleblu | C128: Botwe, Lake Side | D128: Accra | E128: 0243576745 | F128: =UPPER(LEFT(B128,1)) & IFERROR(UPPER(LEFT(MID(B128,FIND(" ",B128)+1,LEN(B128)),1)),"") & IFERROR(UPPER(LEFT(MID(B128,FIND(" ",B128,FIND(" ",B128)+1)+1,LEN(B128)),1)),"") & IFERROR(UPPER(LEFT(MID(B128,FIND(" ",B128,FIND(" ",B128,FIND(" ",B128)+1)+1)+1,LEN(B128)),1)),"") -> MFE
B129: Direct Savings and Loans, Dzorwulu | C129: Dzorwulu | D129: Accra | E129: 0 | F129: =UPPER(LEFT(B129,1)) & IFERROR(UPPER(LEFT(MID(B129,FIND(" ",B129)+1,LEN(B129)),1)),"") & IFERROR(UPPER(LEFT(MID(B129,FIND(" ",B129,FIND(" ",B129)+1)+1,LEN(B129)),1)),"") & IFERROR(UPPER(LEFT(MID(B129,FIND(" ",B129,FIND(" ",B129,FIND(" ",B129)+1)+1)+1,LEN(B129)),1)),"") -> DSAL
B130: Prof. Anamuah-Mensah | C130: Cape Coast | D130: Cape Coast | E130: 0206774104 | F130: =UPPER(LEFT(B130,1)) & IFERROR(UPPER(LEFT(MID(B130,FIND(" ",B130)+1,LEN(B130)),1)),"") & IFERROR(UPPER(LEFT(MID(B130,FIND(" ",B130,FIND(" ",B130)+1)+1,LEN(B130)),1)),"") & IFERROR(UPPER(LEFT(MID(B130,FIND(" ",B130,FIND(" ",B130,FIND(" ",B130)+1)+1)+1,LEN(B130)),1)),"") -> PA
B131: DPGG Vivo Energy Shell | C131: Tema Community 2 | D131: Tema | E131: 0509695225 | F131: =UPPER(LEFT(B131,1)) & IFERROR(UPPER(LEFT(MID(B131,FIND(" ",B131)+1,LEN(B131)),1)),"") & IFERROR(UPPER(LEFT(MID(B131,FIND(" ",B131,FIND(" ",B131)+1)+1,LEN(B131)),1)),"") & IFERROR(UPPER(LEFT(MID(B131,FIND(" ",B131,FIND(" ",B131,FIND(" ",B131)+1)+1)+1,LEN(B131)),1)),"") -> DVES
B132: Mr. Anthony Tweneboah-Koduah | C132: East Legon | D132: Accra | E132: 0208227099 | F132: =UPPER(LEFT(B132,1)) & IFERROR(UPPER(LEFT(MID(B132,FIND(" ",B132)+1,LEN(B132)),1)),"") & IFERROR(UPPER(LEFT(MID(B132,FIND(" ",B132,FIND(" ",B132)+1)+1,LEN(B132)),1)),"") & IFERROR(UPPER(LEFT(MID(B132,FIND(" ",B132,FIND(" ",B132,FIND(" ",B132)+1)+1)+1,LEN(B132)),1)),"") -> MAT
B133: Samuel Addo Frimpong | C133: Nana Krom, Botwe | D133: Accra | E133: 0243119687 | F133: =UPPER(LEFT(B133,1)) & IFERROR(UPPER(LEFT(MID(B133,FIND(" ",B133)+1,LEN(B133)),1)),"") & IFERROR(UPPER(LEFT(MID(B133,FIND(" ",B133,FIND(" ",B133)+1)+1,LEN(B133)),1)),"") & IFERROR(UPPER(LEFT(MID(B133,FIND(" ",B133,FIND(" ",B133,FIND(" ",B133)+1)+1)+1,LEN(B133)),1)),"") -> SAF
B134: Kojo Hesse | C134: Labadi | D134: Accra | E134: 0244842233 | F134: =UPPER(LEFT(B134,1)) & IFERROR(UPPER(LEFT(MID(B134,FIND(" ",B134)+1,LEN(B134)),1)),"") & IFERROR(UPPER(LEFT(MID(B134,FIND(" ",B134,FIND(" ",B134)+1)+1,LEN(B134)),1)),"") & IFERROR(UPPER(LEFT(MID(B134,FIND(" ",B134,FIND(" ",B134,FIND(" ",B134)+1)+1)+1,LEN(B134)),1)),"") -> KH
B135: Techno Serve | C135: Teshie | D135: Accra | E135: 0269827541 | F135: =UPPER(LEFT(B135,1)) & IFERROR(UPPER(LEFT(MID(B135,FIND(" ",B135)+1,LEN(B135)),1)),"") & IFERROR(UPPER(LEFT(MID(B135,FIND(" ",B135,FIND(" ",B135)+1)+1,LEN(B135)),1)),"") & IFERROR(UPPER(LEFT(MID(B135,FIND(" ",B135,FIND(" ",B135,FIND(" ",B135)+1)+1)+1,LEN(B135)),1)),"") -> TS
B136: Atuah Kwesi Aboagye | C136: Trasacco | D136: Accra | E136: 0244437132 | F136: =UPPER(LEFT(B136,1)) & IFERROR(UPPER(LEFT(MID(B136,FIND(" ",B136)+1,LEN(B136)),1)),"") & IFERROR(UPPER(LEFT(MID(B136,FIND(" ",B136,FIND(" ",B136)+1)+1,LEN(B136)),1)),"") & IFERROR(UPPER(LEFT(MID(B136,FIND(" ",B136,FIND(" ",B136,FIND(" ",B136)+1)+1)+1,LEN(B136)),1)),"") -> AKA
B137: Selorm | C137: Powerland, Madina | D137: Accra | E137: 0209607533 | F137: =UPPER(LEFT(B137,1)) & IFERROR(UPPER(LEFT(MID(B137,FIND(" ",B137)+1,LEN(B137)),1)),"") & IFERROR(UPPER(LEFT(MID(B137,FIND(" ",B137,FIND(" ",B137)+1)+1,LEN(B137)),1)),"") & IFERROR(UPPER(LEFT(MID(B137,FIND(" ",B137,FIND(" ",B137,FIND(" ",B137)+1)+1)+1,LEN(B137)),1)),"") -> S
B138: Yawo Farms | C138: Ayikuma | D138: Accra | E138: 0244315547 | F138: =UPPER(LEFT(B138,1)) & IFERROR(UPPER(LEFT(MID(B138,FIND(" ",B138)+1,LEN(B138)),1)),"") & IFERROR(UPPER(LEFT(MID(B138,FIND(" ",B138,FIND(" ",B138)+1)+1,LEN(B138)),1)),"") & IFERROR(UPPER(LEFT(MID(B138,FIND(" ",B138,FIND(" ",B138,FIND(" ",B138)+1)+1)+1,LEN(B138)),1)),"") -> YF
B139: Stephen Appiah-Agyei | C139: Lakeside, Botwe | D139: Accra | E139: 0242979934 | F139: =UPPER(LEFT(B139,1)) & IFERROR(UPPER(LEFT(MID(B139,FIND(" ",B139)+1,LEN(B139)),1)),"") & IFERROR(UPPER(LEFT(MID(B139,FIND(" ",B139,FIND(" ",B139)+1)+1,LEN(B139)),1)),"") & IFERROR(UPPER(LEFT(MID(B139,FIND(" ",B139,FIND(" ",B139,FIND(" ",B139)+1)+1)+1,LEN(B139)),1)),"") -> SA
B140: ECOBANK, Tema Community 1 | C140: Tema Community 1 | D140: Tema | F140: =UPPER(LEFT(B140,1)) & IFERROR(UPPER(LEFT(MID(B140,FIND(" ",B140)+1,LEN(B140)),1)),"") & IFERROR(UPPER(LEFT(MID(B140,FIND(" ",B140,FIND(" ",B140)+1)+1,LEN(B140)),1)),"") & IFERROR(UPPER(LEFT(MID(B140,FIND(" ",B140,FIND(" ",B140,FIND(" ",B140)+1)+1)+1,LEN(B140)),1)),"") -> ETC1
...

Sheet INVOICE
B1: T I N O S O L U T I O N S LTD P. O. Box LG 817, Legon Accra - Ghana Tel: 233 (0) 302 241 971, 0541 123 430 | M1: USD/ GH₵
G7: INVOICE
B9: Customer | J9: Misc
B11: Name | C11: Tilman Rippel | J11: Date | K11: =NOW() -> 45621.555
B12: Address | C12: =IFERROR(VLOOKUP(C11,'Client List'!B:E,2,0),"") -> Mankoadze - Winneba | J12: Order No. | K12: =IFERROR("TSL-" & LEFT(C11,1) & IF(ISNUMBER(FIND(" ",C11)), MID(C11,FIND(" ",C11)+1,1), "") & IF(ISNUMBER(FIND(" ",C11,FIND(" ",C11)+1)), MID(C11,FIND(" ",C11,FIND(" ",C11)+1)+1,1), "") & "-" & TEXT(TODAY(),"ddmmyy"), "") -> TSL-TR-251124
B13: City | C13: =IFERROR(VLOOKUP(C11,'Client List'!B:E,3,0),"") -> Central Region | J13: Rep | Q13: =DATE(2025,6,1) -> 45809
B14: Phone/ Email | C14: =IFERROR(IF(AND(VLOOKUP(C11,'Client List'!B:E,4,0)=0,VLOOKUP(C11,'Client List'!B:H,7,0)=0),"",VLOOKUP(C11,'Client List'!B:E,4,0)&" "&VLOOKUP(C11,'Client List'!B:H,7,0)),"") -> 0545245745 | J14: Currency | K14: GH₵
B15: =IF(C15<>"","Attention","") | C15: =IFERROR(IF(VLOOKUP(C11,'Client List'!B:G,6,0)=0,"",VLOOKUP(C11,'Client List'!B:G,6,0)),"")
B16: Qty | C16: Description | J16: Unit Price | K16: TOTAL
C17: =IF(OR('Customer Base'!D$7="Hybrid",'Customer Base'!D$7="Mini-grid"),'Customer Base'!D$7&" Solar System with "&'Customer Base'!$J$7&"kVA inverter, ",IF('Customer Base'!D$7="Grid-Tied","Grid-Tied Solar System with "&'Customer Base'!$J$7&"kVA inverter, ",IF('Customer Base'!D$7="Mini-Grid","Mini-Grid Solar System with ",IF('Customer Base'!D$7="Backup","Backup System with "&'Customer Base'!$J$7&"kVA inverter, ",""))))&IF(OR('Customer Base'!D$7="Hybrid",'Customer Base'!D$7="Mini-grid"),'Customer Base'!$J$8&"kWh Battery, ","")&IF('Customer Base'!D$7="Backup","and "&'Customer Base'!$J$8&"kWh Battery","")&IF(AND(OR('Customer Base'!D19="Lithium",'Customer Base'!D34="Yes"),OR('Customer Base'!D$7="Hybrid",'Customer Base'!D$7="Mini-grid",'Customer Base'!D$7="Grid-Tied")),'Customer Base'!$J$9&"kWp Solar Panels and Remote Monitoring","")&IF(AND('Customer Base'!D19<>"Lithium",'Customer Base'!D34="No",OR('Customer Base'!D$7="Hybrid",'Customer Base'!D$7="Mini-grid",'Customer Base'!D$7="Grid-Tied")),"and "&'Customer Base'!$J$9&"kWp Solar Panels","") -> Hybrid Solar System with 5kVA inverter, 10kWh Battery, 5.085kWp Solar Panels and Remote Monitoring | K17: =J17*B17 -> 0
B18: {=IF('Customer Base'!$I$15="MANUAL",IFERROR(INDEX(Items!B$6:B$679,SMALL(IF(Items!B$6:B$679<>"",ROW(Items!B$6:B$679)-MIN(ROW(Items!B$6:B$679))+1),Items!N6)),""),IF('Customer Base'!$I$15="AUTOMATE",IFERROR(INDEX(Items!A$6:A$679,SMALL(IF(Items!A$6:A$679<>"",ROW(Items!A$6:A$679)-MIN(ROW(Items!A$6:A$679))+1),Items!N6)),""),""))} -> 1 | C18: {=IFERROR(INDEX(Items!O:O,SMALL(IF(Items!$O$6:$O$676<>"",ROW(Items!$O$6:$O$676)),Items!N6)),"gdhgf")} -> Victron MultiPlus-II 48/5000/70-50 230V | J18: =IF('Customer Base'!I$12="DISPLAY TAX",IF('Customer Base'!$I$17="Retail",IF($K$14="USD",IF(ISNA(VLOOKUP(C18,Items!C$6:F$598,4,0)),"",(VLOOKUP(C18,Items!C$6:F$598,4,0))),IF($K$14="GH₵",IF(ISNA(VLOOKUP(C18,Items!C$6:G$598,5,0)),"",(VLOOKUP(C18,Items!C$6:G$598,5,0))),"")),IF('Customer Base'!$I$17="Super Dealer",IF($K$14="USD",IF(ISNA(VLOOKUP(C18,Items!C$6:I$598,6,0)),"",(VLOOKUP(C18,Items!C$6:I$598,6,0))),IF($K$14="GH₵",IF(ISNA(VLOOKUP(C18,Items!C$6:I$598,7,0)),"",(VLOOKUP(C18,Items!C$6:I$598,7,0))),"")),"")),IF('Customer Base'!I$12="DO NOT DISPLAY TAX",IF('Customer Base'!$I$17="Retail",IF($K$14="USD",IF(ISNA(VLOOKUP(C18,Items!C$6:F$598,2,0)),"",(VLOOKUP(C18,Items!C$6:F$598,2,0))),IF($K$14="GH₵",IF(ISNA(VLOOKUP(C18,Items!C$6:G$598,2,0)),"",'Customer Base'!J$5*(VLOOKUP(C18,Items!C$6:G$598,2,0))),"")),IF('Customer Base'!$I$17="Super Dealer",IF($K$14="USD",IF(ISNA(VLOOKUP(C18,Items!C$6:I$598,3,0)),"",(VLOOKUP(C18,Items!C$6:I$598,3,0))),IF($K$14="GH₵",IF(ISNA(VLOOKUP(C18,Items!C$6:I$598,3,0)),"",'Customer Base'!J$5*(VLOOKUP(C18,Items!C$6:I$598,3,0))),"")),"")),"")) -> 15653.077 | K18: =IFERROR(SUM(B18*J18),"") -> 15653.077
B19: {=IF('Customer Base'!$I$15="MANUAL",IFERROR(INDEX(Items!B$6:B$679,SMALL(IF(Items!B$6:B$679<>"",ROW(Items!B$6:B$679)-MIN(ROW(Items!B$6:B$679))+1),Items!N7)),""),IF('Customer Base'!$I$15="AUTOMATE",IFERROR(INDEX(Items!A$6:A$679,SMALL(IF(Items!A$6:A$679<>"",ROW(Items!A$6:A$679)-MIN(ROW(Items!A$6:A$679))+1),Items!N7)),""),""))} -> 2 | C19: {=IFERROR(INDEX(Items!O:O,SMALL(IF(Items!$O$6:$O$676<>"",ROW(Items!$O$6:$O$676)),Items!N7)),"")} -> BYD LV 5.0KWH Lithium Battery | J19: =IF('Customer Base'!I$12="DISPLAY TAX",IF('Customer Base'!$I$17="Retail",IF($K$14="USD",IF(ISNA(VLOOKUP(C19,Items!C$6:F$598,4,0)),"",(VLOOKUP(C19,Items!C$6:F$598,4,0))),IF($K$14="GH₵",IF(ISNA(VLOOKUP(C19,Items!C$6:G$598,5,0)),"",(VLOOKUP(C19,Items!C$6:G$598,5,0))),"")),IF('Customer Base'!$I$17="Super Dealer",IF($K$14="USD",IF(ISNA(VLOOKUP(C19,Items!C$6:I$598,6,0)),"",(VLOOKUP(C19,Items!C$6:I$598,6,0))),IF($K$14="GH₵",IF(ISNA(VLOOKUP(C19,Items!C$6:I$598,7,0)),"",(VLOOKUP(C19,Items!C$6:I$598,7,0))),"")),"")),IF('Customer Base'!I$12="DO NOT DISPLAY TAX",IF('Customer Base'!$I$17="Retail",IF($K$14="USD",IF(ISNA(VLOOKUP(C19,Items!C$6:F$598,2,0)),"",(VLOOKUP(C19,Items!C$6:F$598,2,0))),IF($K$14="GH₵",IF(ISNA(VLOOKUP(C19,Items!C$6:G$598,2,0)),"",'Customer Base'!J$5*(VLOOKUP(C19,Items!C$6:G$598,2,0))),"")),IF('Customer Base'!$I$17="Super Dealer",IF($K$14="USD",IF(ISNA(VLOOKUP(C19,Items!C$6:I$598,3,0)),"",(VLOOKUP(C19,Items!C$6:I$598,3,0))),IF($K$14="GH₵",IF(ISNA(VLOOKUP(C19,Items!C$6:I$598,3,0)),"",'Customer Base'!J$5*(VLOOKUP(C19,Items!C$6:I$598,3,0))),"")),"")),"")) -> 18996.25 | K19: =IFERROR(SUM(B19*J19),"") -> 37992.5
B20: {=IF('Customer Base'!$I$15="MANUAL",IFERROR(INDEX(Items!B$6:B$679,SMALL(IF(Items!B$6:B$679<>"",ROW(Items!B$6:B$679)-MIN(ROW(Items!B$6:B$679))+1),Items!N8)),""),IF('Customer Base'!$I$15="AUTOMATE",IFERROR(INDEX(Items!A$6:A$679,SMALL(IF(Items!A$6:A$679<>"",ROW(Items!A$6:A$679)-MIN(ROW(Items!A$6:A$679))+1),Items!N8)),""),""))} -> 9 | C20: {=IFERROR(INDEX(Items!O:O,SMALL(IF(Items!$O$6:$O$676<>"",ROW(Items!$O$6:$O$676)),Items!N8)),"")} -> JA Solar JAM72-S30 565 Watts Solar Panel | J20: =IF('Customer Base'!I$12="DISPLAY TAX",IF('Customer Base'!$I$17="Retail",IF($K$14="USD",IF(ISNA(VLOOKUP(C20,Items!C$6:F$598,4,0)),"",(VLOOKUP(C20,Items!C$6:F$598,4,0))),IF($K$14="GH₵",IF(ISNA(VLOOKUP(C20,Items!C$6:G$598,5,0)),"",(VLOOKUP(C20,Items!C$6:G$598,5,0))),"")),IF('Customer Base'!$I$17="Super Dealer",IF($K$14="USD",IF(ISNA(VLOOKUP(C20,Items!C$6:I$598,6,0)),"",(VLOOKUP(C20,Items!C$6:I$598,6,0))),IF($K$14="GH₵",IF(ISNA(VLOOKUP(C20,Items!C$6:I$598,7,0)),"",(VLOOKUP(C20,Items!C$6:I$598,7,0))),"")),"")),IF('Customer Base'!I$12="DO NOT DISPLAY TAX",IF('Customer Base'!$I$17="Retail",IF($K$14="USD",IF(ISNA(VLOOKUP(C20,Items!C$6:F$598,2,0)),"",(VLOOKUP(C20,Items!C$6:F$598,2,0))),IF($K$14="GH₵",IF(ISNA(VLOOKUP(C20,Items!C$6:G$598,2,0)),"",'Customer Base'!J$5*(VLOOKUP(C20,Items!C$6:G$598,2,0))),"")),IF('Customer Base'!$I$17="Super Dealer",IF($K$14="USD",IF(ISNA(VLOOKUP(C20,Items!C$6:I$598,3,0)),"",(VLOOKUP(C20,Items!C$6:I$598,3,0))),IF($K$14="GH₵",IF(ISNA(VLOOKUP(C20,Items!C$6:I$598,3,0)),"",'Customer Base'!J$5*(VLOOKUP(C20,Items!C$6:I$598,3,0))),"")),"")),"")) -> 1946.385 | K20: =IFERROR(SUM(B20*J20),"") -> 17517.465
B21: {=IF('Customer Base'!$I$15="MANUAL",IFERROR(INDEX(Items!B$6:B$679,SMALL(IF(Items!B$6:B$679<>"",ROW(Items!B$6:B$679)-MIN(ROW(Items!B$6:B$679))+1),Items!N9)),""),IF('Customer Base'!$I$15="AUTOMATE",IFERROR(INDEX(Items!A$6:A$679,SMALL(IF(Items!A$6:A$679<>"",ROW(Items!A$6:A$679)-MIN(ROW(Items!A$6:A$679))+1),Items!N9)),""),""))} -> 1 | C21: {=IFERROR(INDEX(Items!O:O,SMALL(IF(Items!$O$6:$O$676<>"",ROW(Items!$O$6:$O$676)),Items!N9)),"")} -> Victron SmartSolar MPPT 100/20 up to 48V | J21: =IF('Customer Base'!I$12="DISPLAY TAX",IF('Customer Base'!$I$17="Retail",IF($K$14="USD",IF(ISNA(VLOOKUP(C21,Items!C$6:F$598,4,0)),"",(VLOOKUP(C21,Items!C$6:F$598,4,0))),IF($K$14="GH₵",IF(ISNA(VLOOKUP(C21,Items!C$6:G$598,5,0)),"",(VLOOKUP(C21,Items!C$6:G$598,5,0))),"")),IF('Customer Base'!$I$17="Super Dealer",IF($K$14="USD",IF(ISNA(VLOOKUP(C21,Items!C$6:I$598,6,0)),"",(VLOOKUP(C21,Items!C$6:I$598,6,0))),IF($K$14="GH₵",IF(ISNA(VLOOKUP(C21,Items!C$6:I$598,7,0)),"",(VLOOKUP(C21,Items!C$6:I$598,7,0))),"")),"")),IF('Customer Base'!I$12="DO NOT DISPLAY TAX",IF('Customer Base'!$I$17="Retail",IF($K$14="USD",IF(ISNA(VLOOKUP(C21,Items!C$6:F$598,2,0)),"",(VLOOKUP(C21,Items!C$6:F$598,2,0))),IF($K$14="GH₵",IF(ISNA(VLOOKUP(C21,Items!C$6:G$598,2,0)),"",'Customer Base'!J$5*(VLOOKUP(C21,Items!C$6:G$598,2,0))),"")),IF('Customer Base'!$I$17="Super Dealer",IF($K$14="USD",IF(ISNA(VLOOKUP(C21,Items!C$6:I$598,3,0)),"",(VLOOKUP(C21,Items!C$6:I$598,3,0))),IF($K$14="GH₵",IF(ISNA(VLOOKUP(C21,Items!C$6:I$598,3,0)),"",'Customer Base'!J$5*(VLOOKUP(C21,Items!C$6:I$598,3,0))),"")),"")),"")) -> 1508.01 | K21: =IFERROR(SUM(B21*J21),"") -> 1508.01
B22: {=IF('Customer Base'!$I$15="MANUAL",IFERROR(INDEX(Items!B$6:B$679,SMALL(IF(Items!B$6:B$679<>"",ROW(Items!B$6:B$679)-MIN(ROW(Items!B$6:B$679))+1),Items!N10)),""),IF('Customer Base'!$I$15="AUTOMATE",IFERROR(INDEX(Items!A$6:A$679,SMALL(IF(Items!A$6:A$679<>"",ROW(Items!A$6:A$679)-MIN(ROW(Items!A$6:A$679))+1),Items!N10)),""),""))} -> 1 | C22: {=IFERROR(INDEX(Items!O:O,SMALL(IF(Items!$O$6:$O$676<>"",ROW(Items!$O$6:$O$676)),Items!N10)),"")} -> Victron SmartSolar MPPT 250/70-Tr VE.Can | J22: =IF('Customer Base'!I$12="DISPLAY TAX",IF('Customer Base'!$I$17="Retail",IF($K$14="USD",IF(ISNA(VLOOKUP(C22,Items!C$6:F$598,4,0)),"",(VLOOKUP(C22,Items!C$6:F$598,4,0))),IF($K$14="GH₵",IF(ISNA(VLOOKUP(C22,Items!C$6:G$598,5,0)),"",(VLOOKUP(C22,Items!C$6:G$598,5,0))),"")),IF('Customer Base'!$I$17="Super Dealer",IF($K$14="USD",IF(ISNA(VLOOKUP(C22,Items!C$6:I$598,6,0)),"",(VLOOKUP(C22,Items!C$6:I$598,6,0))),IF($K$14="GH₵",IF(ISNA(VLOOKUP(C22,Items!C$6:I$598,7,0)),"",(VLOOKUP(C22,Items!C$6:I$598,7,0))),"")),"")),IF('Customer Base'!I$12="DO NOT DISPLAY TAX",IF('Customer Base'!$I$17="Retail",IF($K$14="USD",IF(ISNA(VLOOKUP(C22,Items!C$6:F$598,2,0)),"",(VLOOKUP(C22,Items!C$6:F$598,2,0))),IF($K$14="GH₵",IF(ISNA(VLOOKUP(C22,Items!C$6:G$598,2,0)),"",'Customer Base'!J$5*(VLOOKUP(C22,Items!C$6:G$598,2,0))),"")),IF('Customer Base'!$I$17="Super Dealer",IF($K$14="USD",IF(ISNA(VLOOKUP(C22,Items!C$6:I$598,3,0)),"",(VLOOKUP(C22,Items!C$6:I$598,3,0))),IF($K$14="GH₵",IF(ISNA(VLOOKUP(C22,Items!C$6:I$598,3,0)),"",'Customer Base'!J$5*(VLOOKUP(C22,Items!C$6:I$598,3,0))),"")),"")),"")) -> 8625.884 | K22: =IFERROR(SUM(B22*J22),"") -> 8625.884
B23: {=IF('Customer Base'!$I$15="MANUAL",IFERROR(INDEX(Items!B$6:B$679,SMALL(IF(Items!B$6:B$679<>"",ROW(Items!B$6:B$679)-MIN(ROW(Items!B$6:B$679))+1),Items!N11)),""),IF('Customer Base'!$I$15="AUTOMATE",IFERROR(INDEX(Items!A$6:A$679,SMALL(IF(Items!A$6:A$679<>"",ROW(Items!A$6:A$679)-MIN(ROW(Items!A$6:A$679))+1),Items!N11)),""),""))} -> 1 | C23: {=IFERROR(INDEX(Items!O:O,SMALL(IF(Items!$O$6:$O$676<>"",ROW(Items!$O$6:$O$676)),Items!N11)),"")} -> Victron Cerbo GX | J23: =IF('Customer Base'!I$12="DISPLAY TAX",IF('Customer Base'!$I$17="Retail",IF($K$14="USD",IF(ISNA(VLOOKUP(C23,Items!C$6:F$598,4,0)),"",(VLOOKUP(C23,Items!C$6:F$598,4,0))),IF($K$14="GH₵",IF(ISNA(VLOOKUP(C23,Items!C$6:G$598,5,0)),"",(VLOOKUP(C23,Items!C$6:G$598,5,0))),"")),IF('Customer Base'!$I$17="Super Dealer",IF($K$14="USD",IF(ISNA(VLOOKUP(C23,Items!C$6:I$598,6,0)),"",(VLOOKUP(C23,Items!C$6:I$598,6,0))),IF($K$14="GH₵",IF(ISNA(VLOOKUP(C23,Items!C$6:I$598,7,0)),"",(VLOOKUP(C23,Items!C$6:I$598,7,0))),"")),"")),IF('Customer Base'!I$12="DO NOT DISPLAY TAX",IF('Customer Base'!$I$17="Retail",IF($K$14="USD",IF(ISNA(VLOOKUP(C23,Items!C$6:F$598,2,0)),"",(VLOOKUP(C23,Items!C$6:F$598,2,0))),IF($K$14="GH₵",IF(ISNA(VLOOKUP(C23,Items!C$6:G$598,2,0)),"",'Customer Base'!J$5*(VLOOKUP(C23,Items!C$6:G$598,2,0))),"")),IF('Customer Base'!$I$17="Super Dealer",IF($K$14="USD",IF(ISNA(VLOOKUP(C23,Items!C$6:I$598,3,0)),"",(VLOOKUP(C23,Items!C$6:I$598,3,0))),IF($K$14="GH₵",IF(ISNA(VLOOKUP(C23,Items!C$6:I$598,3,0)),"",'Customer Base'!J$5*(VLOOKUP(C23,Items!C$6:I$598,3,0))),"")),"")),"")) -> 4644.604 | K23: =IFERROR(SUM(B23*J23),"") -> 4644.604
B24: {=IF('Customer Base'!$I$15="MANUAL",IFERROR(INDEX(Items!B$6:B$679,SMALL(IF(Items!B$6:B$679<>"",ROW(Items!B$6:B$679)-MIN(ROW(Items!B$6:B$679))+1),Items!N12)),""),IF('Customer Base'!$I$15="AUTOMATE",IFERROR(INDEX(Items!A$6:A$679,SMALL(IF(Items!A$6:A$679<>"",ROW(Items!A$6:A$679)-MIN(ROW(Items!A$6:A$679))+1),Items!N12)),""),""))} -> 2 | C24: {=IFERROR(INDEX(Items!O:O,SMALL(IF(Items!$O$6:$O$676<>"",ROW(Items!$O$6:$O$676)),Items!N12)),"")} -> Victron Solar Busbar 150A 2P with 10 screws +cover | J24: =IF('Customer Base'!I$12="DISPLAY TAX",IF('Customer Base'!$I$17="Retail",IF($K$14="USD",IF(ISNA(VLOOKUP(C24,Items!C$6:F$598,4,0)),"",(VLOOKUP(C24,Items!C$6:F$598,4,0))),IF($K$14="GH₵",IF(ISNA(VLOOKUP(C24,Items!C$6:G$598,5,0)),"",(VLOOKUP(C24,Items!C$6:G$598,5,0))),"")),IF('Customer Base'!$I$17="Super Dealer",IF($K$14="USD",IF(ISNA(VLOOKUP(C24,Items!C$6:I$598,6,0)),"",(VLOOKUP(C24,Items!C$6:I$598,6,0))),IF($K$14="GH₵",IF(ISNA(VLOOKUP(C24,Items!C$6:I$598,7,0)),"",(VLOOKUP(C24,Items!C$6:I$598,7,0))),"")),"")),IF('Customer Base'!I$12="DO NOT DISPLAY TAX",IF('Customer Base'!$I$17="Retail",IF($K$14="USD",IF(ISNA(VLOOKUP(C24,Items!C$6:F$598,2,0)),"",(VLOOKUP(C24,Items!C$6:F$598,2,0))),IF($K$14="GH₵",IF(ISNA(VLOOKUP(C24,Items!C$6:G$598,2,0)),"",'Customer Base'!J$5*(VLOOKUP(C24,Items!C$6:G$598,2,0))),"")),IF('Customer Base'!$I$17="Super Dealer",IF($K$14="USD",IF(ISNA(VLOOKUP(C24,Items!C$6:I$598,3,0)),"",(VLOOKUP(C24,Items!C$6:I$598,3,0))),IF($K$14="GH₵",IF(ISNA(VLOOKUP(C24,Items!C$6:I$598,3,0)),"",'Customer Base'!J$5*(VLOOKUP(C24,Items!C$6:I$598,3,0))),"")),"")),"")) -> 316.465 | K24: =IFERROR(SUM(B24*J24),"") -> 632.93
B25: {=IF('Customer Base'!$I$15="MANUAL",IFERROR(INDEX(Items!B$6:B$679,SMALL(IF(Items!B$6:B$679<>"",ROW(Items!B$6:B$679)-MIN(ROW(Items!B$6:B$679))+1),Items!N13)),""),IF('Customer Base'!$I$15="AUTOMATE",IFERROR(INDEX(Items!A$6:A$679,SMALL(IF(Items!A$6:A$679<>"",ROW(Items!A$6:A$679)-MIN(ROW(Items!A$6:A$679))+1),Items!N13)),""),""))} -> 1 | C25: {=IFERROR(INDEX(Items!O:O,SMALL(IF(Items!$O$6:$O$676<>"",ROW(Items!$O$6:$O$676)),Items!N13)),"")} -> Solar DC Combiner BHS 2/1 | J25: =IF('Customer Base'!I$12="DISPLAY TAX",IF('Customer Base'!$I$17="Retail",IF($K$14="USD",IF(ISNA(VLOOKUP(C25,Items!C$6:F$598,4,0)),"",(VLOOKUP(C25,Items!C$6:F$598,4,0))),IF($K$14="GH₵",IF(ISNA(VLOOKUP(C25,Items!C$6:G$598,5,0)),"",(VLOOKUP(C25,Items!C$6:G$598,5,0))),"")),IF('Customer Base'!$I$17="Super Dealer",IF($K$14="USD",IF(ISNA(VLOOKUP(C25,Items!C$6:I$598,6,0)),"",(VLOOKUP(C25,Items!C$6:I$598,6,0))),IF($K$14="GH₵",IF(ISNA(VLOOKUP(C25,Items!C$6:I$598,7,0)),"",(VLOOKUP(C25,Items!C$6:I$598,7,0))),"")),"")),IF('Customer Base'!I$12="DO NOT DISPLAY TAX",IF('Customer Base'!$I$17="Retail",IF($K$14="USD",IF(ISNA(VLOOKUP(C25,Items!C$6:F$598,2,0)),"",(VLOOKUP(C25,Items!C$6:F$598,2,0))),IF($K$14="GH₵",IF(ISNA(VLOOKUP(C25,Items!C$6:G$598,2,0)),"",'Customer Base'!J$5*(VLOOKUP(C25,Items!C$6:G$598,2,0))),"")),IF('Customer Base'!$I$17="Super Dealer",IF($K$14="USD",IF(ISNA(VLOOKUP(C25,Items!C$6:I$598,3,0)),"",(VLOOKUP(C25,Items!C$6:I$598,3,0))),IF($K$14="GH₵",IF(ISNA(VLOOKUP(C25,Items!C$6:I$598,3,0)),"",'Customer Base'!J$5*(VLOOKUP(C25,Items!C$6:I$598,3,0))),"")),"")),"")) -> 2010.68 | K25: =IFERROR(SUM(B25*J25),"") -> 2010.68
B26: {=IF('Customer Base'!$I$15="MANUAL",IFERROR(INDEX(Items!B$6:B$679,SMALL(IF(Items!B$6:B$679<>"",ROW(Items!B$6:B$679)-MIN(ROW(Items!B$6:B$679))+1),Items!N14)),""),IF('Customer Base'!$I$15="AUTOMATE",IFERROR(INDEX(Items!A$6:A$679,SMALL(IF(Items!A$6:A$679<>"",ROW(Items!A$6:A$679)-MIN(ROW(Items!A$6:A$679))+1),Items!N14)),""),""))} -> 1 | C26: {=IFERROR(INDEX(Items!O:O,SMALL(IF(Items!$O$6:$O$676<>"",ROW(Items!$O$6:$O$676)),Items!N14)),"")} -> Citel AC Surge Protection Device DAC50VGS-11-275/G VAC 1-Phase | J26: =IF('Customer Base'!I$12="DISPLAY TAX",IF('Customer Base'!$I$17="Retail",IF($K$14="USD",IF(ISNA(VLOOKUP(C26,Items!C$6:F$598,4,0)),"",(VLOOKUP(C26,Items!C$6:F$598,4,0))),IF($K$14="GH₵",IF(ISNA(VLOOKUP(C26,Items!C$6:G$598,5,0)),"",(VLOOKUP(C26,Items!C$6:G$598,5,0))),"")),IF('Customer Base'!$I$17="Super Dealer",IF($K$14="USD",IF(ISNA(VLOOKUP(C26,Items!C$6:I$598,6,0)),"",(VLOOKUP(C26,Items!C$6:I$598,6,0))),IF($K$14="GH₵",IF(ISNA(VLOOKUP(C26,Items!C$6:I$598,7,0)),"",(VLOOKUP(C26,Items!C$6:I$598,7,0))),"")),"")),IF('Customer Base'!I$12="DO NOT DISPLAY TAX",IF('Customer Base'!$I$17="Retail",IF($K$14="USD",IF(ISNA(VLOOKUP(C26,Items!C$6:F$598,2,0)),"",(VLOOKUP(C26,Items!C$6:F$598,2,0))),IF($K$14="GH₵",IF(ISNA(VLOOKUP(C26,Items!C$6:G$598,2,0)),"",'Customer Base'!J$5*(VLOOKUP(C26,Items!C$6:G$598,2,0))),"")),IF('Customer Base'!$I$17="Super Dealer",IF($K$14="USD",IF(ISNA(VLOOKUP(C26,Items!C$6:I$598,3,0)),"",(VLOOKUP(C26,Items!C$6:I$598,3,0))),IF($K$14="GH₵",IF(ISNA(VLOOKUP(C26,Items!C$6:I$598,3,0)),"",'Customer Base'!J$5*(VLOOKUP(C26,Items!C$6:I$598,3,0))),"")),"")),"")) -> 815.795 | K26: =IFERROR(SUM(B26*J26),"") -> 815.795
B27: {=IF('Customer Base'!$I$15="MANUAL",IFERROR(INDEX(Items!B$6:B$679,SMALL(IF(Items!B$6:B$679<>"",ROW(Items!B$6:B$679)-MIN(ROW(Items!B$6:B$679))+1),Items!N15)),""),IF('Customer Base'!$I$15="AUTOMATE",IFERROR(INDEX(Items!A$6:A$679,SMALL(IF(Items!A$6:A$679<>"",ROW(Items!A$6:A$679)-MIN(ROW(Items!A$6:A$679))+1),Items!N15)),""),""))} -> 20 | C27: {=IFERROR(INDEX(Items!O:O,SMALL(IF(Items!$O$6:$O$676<>"",ROW(Items!$O$6:$O$676)),Items!N15)),"")} -> Hikra Sol DC Solar cable 1x4mm2 1500V H1Z2Z2 | J27: =IF('Customer Base'!I$12="DISPLAY TAX",IF('Customer Base'!$I$17="Retail",IF($K$14="USD",IF(ISNA(VLOOKUP(C27,Items!C$6:F$598,4,0)),"",(VLOOKUP(C27,Items!C$6:F$598,4,0))),IF($K$14="GH₵",IF(ISNA(VLOOKUP(C27,Items!C$6:G$598,5,0)),"",(VLOOKUP(C27,Items!C$6:G$598,5,0))),"")),IF('Customer Base'!$I$17="Super Dealer",IF($K$14="USD",IF(ISNA(VLOOKUP(C27,Items!C$6:I$598,6,0)),"",(VLOOKUP(C27,Items!C$6:I$598,6,0))),IF($K$14="GH₵",IF(ISNA(VLOOKUP(C27,Items!C$6:I$598,7,0)),"",(VLOOKUP(C27,Items!C$6:I$598,7,0))),"")),"")),IF('Customer Base'!I$12="DO NOT DISPLAY TAX",IF('Customer Base'!$I$17="Retail",IF($K$14="USD",IF(ISNA(VLOOKUP(C27,Items!C$6:F$598,2,0)),"",(VLOOKUP(C27,Items!C$6:F$598,2,0))),IF($K$14="GH₵",IF(ISNA(VLOOKUP(C27,Items!C$6:G$598,2,0)),"",'Customer Base'!J$5*(VLOOKUP(C27,Items!C$6:G$598,2,0))),"")),IF('Customer Base'!$I$17="Super Dealer",IF($K$14="USD",IF(ISNA(VLOOKUP(C27,Items!C$6:I$598,3,0)),"",(VLOOKUP(C27,Items!C$6:I$598,3,0))),IF($K$14="GH₵",IF(ISNA(VLOOKUP(C27,Items!C$6:I$598,3,0)),"",'Customer Base'!J$5*(VLOOKUP(C27,Items!C$6:I$598,3,0))),"")),"")),"")) -> 17.034 | K27: =IFERROR(SUM(B27*J27),"") -> 340.68
B28: {=IF('Customer Base'!$I$15="MANUAL",IFERROR(INDEX(Items!B$6:B$679,SMALL(IF(Items!B$6:B$679<>"",ROW(Items!B$6:B$679)-MIN(ROW(Items!B$6:B$679))+1),Items!N16)),""),IF('Customer Base'!$I$15="AUTOMATE",IFERROR(INDEX(Items!A$6:A$679,SMALL(IF(Items!A$6:A$679<>"",ROW(Items!A$6:A$679)-MIN(ROW(Items!A$6:A$679))+1),Items!N16)),""),""))} -> 80 | C28: {=IFERROR(INDEX(Items!O:O,SMALL(IF(Items!$O$6:$O$676<>"",ROW(Items!$O$6:$O$676)),Items!N16)),"")} -> Hikra Sol DC Solar cable 1x6mm2 1500V H1Z2Z2 | J28: =IF('Customer Base'!I$12="DISPLAY TAX",IF('Customer Base'!$I$17="Retail",IF($K$14="USD",IF(ISNA(VLOOKUP(C28,Items!C$6:F$598,4,0)),"",(VLOOKUP(C28,Items!C$6:F$598,4,0))),IF($K$14="GH₵",IF(ISNA(VLOOKUP(C28,Items!C$6:G$598,5,0)),"",(VLOOKUP(C28,Items!C$6:G$598,5,0))),"")),IF('Customer Base'!$I$17="Super Dealer",IF($K$14="USD",IF(ISNA(VLOOKUP(C28,Items!C$6:I$598,6,0)),"",(VLOOKUP(C28,Items!C$6:I$598,6,0))),IF($K$14="GH₵",IF(ISNA(VLOOKUP(C28,Items!C$6:I$598,7,0)),"",(VLOOKUP(C28,Items!C$6:I$598,7,0))),"")),"")),IF('Customer Base'!I$12="DO NOT DISPLAY TAX",IF('Customer Base'!$I$17="Retail",IF($K$14="USD",IF(ISNA(VLOOKUP(C28,Items!C$6:F$598,2,0)),"",(VLOOKUP(C28,Items!C$6:F$598,2,0))),IF($K$14="GH₵",IF(ISNA(VLOOKUP(C28,Items!C$6:G$598,2,0)),"",'Customer Base'!J$5*(VLOOKUP(C28,Items!C$6:G$598,2,0))),"")),IF('Customer Base'!$I$17="Super Dealer",IF($K$14="USD",IF(ISNA(VLOOKUP(C28,Items!C$6:I$598,3,0)),"",(VLOOKUP(C28,Items!C$6:I$598,3,0))),IF($K$14="GH₵",IF(ISNA(VLOOKUP(C28,Items!C$6:I$598,3,0)),"",'Customer Base'!J$5*(VLOOKUP(C28,Items!C$6:I$598,3,0))),"")),"")),"")) -> 22.712 | K28: =IFERROR(SUM(B28*J28),"") -> 1816.96
B29: {=IF('Customer Base'!$I$15="MANUAL",IFERROR(INDEX(Items!B$6:B$679,SMALL(IF(Items!B$6:B$679<>"",ROW(Items!B$6:B$679)-MIN(ROW(Items!B$6:B$679))+1),Items!N17)),""),IF('Customer Base'!$I$15="AUTOMATE",IFERROR(INDEX(Items!A$6:A$679,SMALL(IF(Items!A$6:A$679<>"",ROW(Items!A$6:A$679)-MIN(ROW(Items!A$6:A$679))+1),Items!N17)),""),""))} -> 60 | C29: {=IFERROR(INDEX(Items!O:O,SMALL(IF(Items!$O$6:$O$676<>"",ROW(Items!$O$6:$O$676)),Items!N17)),"")} -> Hikra Sol DC Solar cable 1x16mm2 1500V H1Z2Z2 | J29: =IF('Customer Base'!I$12="DISPLAY TAX",IF('Customer Base'!$I$17="Retail",IF($K$14="USD",IF(ISNA(VLOOKUP(C29,Items!C$6:F$598,4,0)),"",(VLOOKUP(C29,Items!C$6:F$598,4,0))),IF($K$14="GH₵",IF(ISNA(VLOOKUP(C29,Items!C$6:G$598,5,0)),"",(VLOOKUP(C29,Items!C$6:G$598,5,0))),"")),IF('Customer Base'!$I$17="Super Dealer",IF($K$14="USD",IF(ISNA(VLOOKUP(C29,Items!C$6:I$598,6,0)),"",(VLOOKUP(C29,Items!C$6:I$598,6,0))),IF($K$14="GH₵",IF(ISNA(VLOOKUP(C29,Items!C$6:I$598,7,0)),"",(VLOOKUP(C29,Items!C$6:I$598,7,0))),"")),"")),IF('Customer Base'!I$12="DO NOT DISPLAY TAX",IF('Customer Base'!$I$17="Retail",IF($K$14="USD",IF(ISNA(VLOOKUP(C29,Items!C$6:F$598,2,0)),"",(VLOOKUP(C29,Items!C$6:F$598,2,0))),IF($K$14="GH₵",IF(ISNA(VLOOKUP(C29,Items!C$6:G$598,2,0)),"",'Customer Base'!J$5*(VLOOKUP(C29,Items!C$6:G$598,2,0))),"")),IF('Customer Base'!$I$17="Super Dealer",IF($K$14="USD",IF(ISNA(VLOOKUP(C29,Items!C$6:I$598,3,0)),"",(VLOOKUP(C29,Items!C$6:I$598,3,0))),IF($K$14="GH₵",IF(ISNA(VLOOKUP(C29,Items!C$6:I$598,3,0)),"",'Customer Base'!J$5*(VLOOKUP(C29,Items!C$6:I$598,3,0))),"")),"")),"")) -> 75.651 | K29: =IFERROR(SUM(B29*J29),"") -> 4539.06
B30: {=IF('Customer Base'!$I$15="MANUAL",IFERROR(INDEX(Items!B$6:B$679,SMALL(IF(Items!B$6:B$679<>"",ROW(Items!B$6:B$679)-MIN(ROW(Items!B$6:B$679))+1),Items!N18)),""),IF('Customer Base'!$I$15="AUTOMATE",IFERROR(INDEX(Items!A$6:A$679,SMALL(IF(Items!A$6:A$679<>"",ROW(Items!A$6:A$679)-MIN(ROW(Items!A$6:A$679))+1),Items!N18)),""),""))} -> 15 | C30: {=IFERROR(INDEX(Items!O:O,SMALL(IF(Items!$O$6:$O$676<>"",ROW(Items!$O$6:$O$676)),Items!N18)),"")} -> Hikra Sol DC Solar cable 1x25mm2 1500V H1Z2Z2 | J30: =IF('Customer Base'!I$12="DISPLAY TAX",IF('Customer Base'!$I$17="Retail",IF($K$14="USD",IF(ISNA(VLOOKUP(C30,Items!C$6:F$598,4,0)),"",(VLOOKUP(C30,Items!C$6:F$598,4,0))),IF($K$14="GH₵",IF(ISNA(VLOOKUP(C30,Items!C$6:G$598,5,0)),"",(VLOOKUP(C30,Items!C$6:G$598,5,0))),"")),IF('Customer Base'!$I$17="Super Dealer",IF($K$14="USD",IF(ISNA(VLOOKUP(C30,Items!C$6:I$598,6,0)),"",(VLOOKUP(C30,Items!C$6:I$598,6,0))),IF($K$14="GH₵",IF(ISNA(VLOOKUP(C30,Items!C$6:I$598,7,0)),"",(VLOOKUP(C30,Items!C$6:I$598,7,0))),"")),"")),IF('Customer Base'!I$12="DO NOT DISPLAY TAX",IF('Customer Base'!$I$17="Retail",IF($K$14="USD",IF(ISNA(VLOOKUP(C30,Items!C$6:F$598,2,0)),"",(VLOOKUP(C30,Items!C$6:F$598,2,0))),IF($K$14="GH₵",IF(ISNA(VLOOKUP(C30,Items!C$6:G$598,2,0)),"",'Customer Base'!J$5*(VLOOKUP(C30,Items!C$6:G$598,2,0))),"")),IF('Customer Base'!$I$17="Super Dealer",IF($K$14="USD",IF(ISNA(VLOOKUP(C30,Items!C$6:I$598,3,0)),"",(VLOOKUP(C30,Items!C$6:I$598,3,0))),IF($K$14="GH₵",IF(ISNA(VLOOKUP(C30,Items!C$6:I$598,3,0)),"",'Customer Base'!J$5*(VLOOKUP(C30,Items!C$6:I$598,3,0))),"")),"")),"")) -> 137.775 | K30: =IFERROR(SUM(B30*J30),"") -> 2066.625
... B56: {=IF('Customer Base'!$I$15="MANUAL",IFERROR(INDEX(Items!B$6:B$679,SMALL(IF(Items!B$6:B$679<>"",ROW(Items!B$6:B$679)-MIN(ROW(Items!B$6:B$679))+1),Items!N44)),""),IF('Customer Base'!$I$15="AUTOMATE",IFERROR(INDEX(Items!A$6:A$679,SMALL(IF(Items!A$6:A$679<>"",ROW(Items!A$6:A$679)-MIN(ROW(Items!A$6:A$679))+1),Items!N44)),""),""))} | C56: {=IFERROR(INDEX(Items!O:O,SMALL(IF(Items!$O$6:$O$676<>"",ROW(Items!$O$6:$O$676)),Items!N44)),"")} | J56: =IF('Customer Base'!I$12="DISPLAY TAX",IF('Customer Base'!$I$17="Retail",IF($K$14="USD",IF(ISNA(VLOOKUP(C56,Items!C$6:F$598,4,0)),"",(VLOOKUP(C56,Items!C$6:F$598,4,0))),IF($K$14="GH₵",IF(ISNA(VLOOKUP(C56,Items!C$6:G$598,5,0)),"",(VLOOKUP(C56,Items!C$6:G$598,5,0))),"")),IF('Customer Base'!$I$17="Super Dealer",IF($K$14="USD",IF(ISNA(VLOOKUP(C56,Items!C$6:I$598,6,0)),"",(VLOOKUP(C56,Items!C$6:I$598,6,0))),IF($K$14="GH₵",IF(ISNA(VLOOKUP(C56,Items!C$6:I$598,7,0)),"",(VLOOKUP(C56,Items!C$6:I$598,7,0))),"")),"")),IF('Customer Base'!I$12="DO NOT DISPLAY TAX",IF('Customer Base'!$I$17="Retail",IF($K$14="USD",IF(ISNA(VLOOKUP(C56,Items!C$6:F$598,2,0)),"",(VLOOKUP(C56,Items!C$6:F$598,2,0))),IF($K$14="GH₵",IF(ISNA(VLOOKUP(C56,Items!C$6:G$598,2,0)),"",'Customer Base'!J$5*(VLOOKUP(C56,Items!C$6:G$598,2,0))),"")),IF('Customer Base'!$I$17="Super Dealer",IF($K$14="USD",IF(ISNA(VLOOKUP(C56,Items!C$6:I$598,3,0)),"",(VLOOKUP(C56,Items!C$6:I$598,3,0))),IF($K$14="GH₵",IF(ISNA(VLOOKUP(C56,Items!C$6:I$598,3,0)),"",'Customer Base'!J$5*(VLOOKUP(C56,Items!C$6:I$598,3,0))),"")),"")),"")) | K56: =IFERROR(SUM(B56*J56),"")
C57: Terms of Sale: | J57: =IF('Customer Base'!I$12="DISPLAY TAX",IF('Customer Base'!$I$17="Retail",IF($K$14="USD",IF(ISNA(VLOOKUP(C57,Items!C$6:F$598,4,0)),"",(VLOOKUP(C57,Items!C$6:F$598,4,0))),IF($K$14="GH₵",IF(ISNA(VLOOKUP(C57,Items!C$6:G$598,5,0)),"",(VLOOKUP(C57,Items!C$6:G$598,5,0))),"")),IF('Customer Base'!$I$17="Super Dealer",IF($K$14="USD",IF(ISNA(VLOOKUP(C57,Items!C$6:I$598,6,0)),"",(VLOOKUP(C57,Items!C$6:I$598,6,0))),IF($K$14="GH₵",IF(ISNA(VLOOKUP(C57,Items!C$6:I$598,7,0)),"",(VLOOKUP(C57,Items!C$6:I$598,7,0))),"")),"")),IF('Customer Base'!I$12="DO NOT DISPLAY TAX",IF('Customer Base'!$I$17="Retail",IF($K$14="USD",IF(ISNA(VLOOKUP(C57,Items!C$6:F$598,2,0)),"",(VLOOKUP(C57,Items!C$6:F$598,2,0))),IF($K$14="GH₵",IF(ISNA(VLOOKUP(C57,Items!C$6:G$598,2,0)),"",'Customer Base'!J$5*(VLOOKUP(C57,Items!C$6:G$598,2,0))),"")),IF('Customer Base'!$I$17="Super Dealer",IF($K$14="USD",IF(ISNA(VLOOKUP(C57,Items!C$6:I$598,3,0)),"",(VLOOKUP(C57,Items!C$6:I$598,3,0))),IF($K$14="GH₵",IF(ISNA(VLOOKUP(C57,Items!C$6:I$598,3,0)),"",'Customer Base'!J$5*(VLOOKUP(C57,Items!C$6:I$598,3,0))),"")),"")),"")) | K57: =IFERROR(SUM(B57*J57),"")
C58: Delivery: Immediate upon confirmation of payment | J58: =IF('Customer Base'!I$12="DISPLAY TAX",IF('Customer Base'!$I$17="Retail",IF($K$14="USD",IF(ISNA(VLOOKUP(C58,Items!C$6:F$598,4,0)),"",(VLOOKUP(C58,Items!C$6:F$598,4,0))),IF($K$14="GH₵",IF(ISNA(VLOOKUP(C58,Items!C$6:G$598,5,0)),"",(VLOOKUP(C58,Items!C$6:G$598,5,0))),"")),IF('Customer Base'!$I$17="Super Dealer",IF($K$14="USD",IF(ISNA(VLOOKUP(C58,Items!C$6:I$598,6,0)),"",(VLOOKUP(C58,Items!C$6:I$598,6,0))),IF($K$14="GH₵",IF(ISNA(VLOOKUP(C58,Items!C$6:I$598,7,0)),"",(VLOOKUP(C58,Items!C$6:I$598,7,0))),"")),"")),IF('Customer Base'!I$12="DO NOT DISPLAY TAX",IF('Customer Base'!$I$17="Retail",IF($K$14="USD",IF(ISNA(VLOOKUP(C58,Items!C$6:F$598,2,0)),"",(VLOOKUP(C58,Items!C$6:F$598,2,0))),IF($K$14="GH₵",IF(ISNA(VLOOKUP(C58,Items!C$6:G$598,2,0)),"",'Customer Base'!J$5*(VLOOKUP(C58,Items!C$6:G$598,2,0))),"")),IF('Customer Base'!$I$17="Super Dealer",IF($K$14="USD",IF(ISNA(VLOOKUP(C58,Items!C$6:I$598,3,0)),"",(VLOOKUP(C58,Items!C$6:I$598,3,0))),IF($K$14="GH₵",IF(ISNA(VLOOKUP(C58,Items!C$6:I$598,3,0)),"",'Customer Base'!J$5*(VLOOKUP(C58,Items!C$6:I$598,3,0))),"")),"")),"")) | K58: =IFERROR(SUM(B58*J58),"")
C59: Payment: 100% Payment with order | J59: =IF('Customer Base'!I$12="DISPLAY TAX",IF('Customer Base'!$I$17="Retail",IF($K$14="USD",IF(ISNA(VLOOKUP(C59,Items!C$6:F$598,4,0)),"",(VLOOKUP(C59,Items!C$6:F$598,4,0))),IF($K$14="GH₵",IF(ISNA(VLOOKUP(C59,Items!C$6:G$598,5,0)),"",(VLOOKUP(C59,Items!C$6:G$598,5,0))),"")),IF('Customer Base'!$I$17="Super Dealer",IF($K$14="USD",IF(ISNA(VLOOKUP(C59,Items!C$6:I$598,6,0)),"",(VLOOKUP(C59,Items!C$6:I$598,6,0))),IF($K$14="GH₵",IF(ISNA(VLOOKUP(C59,Items!C$6:I$598,7,0)),"",(VLOOKUP(C59,Items!C$6:I$598,7,0))),"")),"")),IF('Customer Base'!I$12="DO NOT DISPLAY TAX",IF('Customer Base'!$I$17="Retail",IF($K$14="USD",IF(ISNA(VLOOKUP(C59,Items!C$6:F$598,2,0)),"",(VLOOKUP(C59,Items!C$6:F$598,2,0))),IF($K$14="GH₵",IF(ISNA(VLOOKUP(C59,Items!C$6:G$598,2,0)),"",'Customer Base'!J$5*(VLOOKUP(C59,Items!C$6:G$598,2,0))),"")),IF('Customer Base'!$I$17="Super Dealer",IF($K$14="USD",IF(ISNA(VLOOKUP(C59,Items!C$6:I$598,3,0)),"",(VLOOKUP(C59,Items!C$6:I$598,3,0))),IF($K$14="GH₵",IF(ISNA(VLOOKUP(C59,Items!C$6:I$598,3,0)),"",'Customer Base'!J$5*(VLOOKUP(C59,Items!C$6:I$598,3,0))),"")),"")),"")) | K59: =IFERROR(SUM(B59*J59),"")
C60: Validity: 2 weeks from date of invoice | K60: =IFERROR(SUM(B60*J60),"") -> 0
C61: Warranty: 10 years for battery, 5 years for inverter and accessories, 10 years for solar panels | K61: =IFERROR(SUM(B61*J61),"") -> 0
C62: System Design: Hybrid Solar system to supply power to commercial facility | K62: =IFERROR(SUM(B62*J62),"") -> 0
C64: Scope: Solar to cater for all gadgets in facility
K65: =IF(C65="","",B65*J65)
C66: Bank Name: ECOBANK (GH) LTD | J66: SubTotal | K66: =IF(NOW()>Q13,"",IF(SUM(K17:K65)>0,ROUND(SUM(K17:K65),2),"")) -> 113039.88
C67: =IFERROR(VLOOKUP(C$66,Items!AD:AJ,2,0),"") -> Account No: 1441002237313 (GHS) | J67: =IF('Customer Base'!I12="DISPLAY TAX","6% NHIL/GETFUND/COVID19 Levy",IF('Customer Base'!I12="DO NOT DISPLAY TAX","")) | K67: =IF(J67="","",IFERROR(6%*K66,0))
C68: =IFERROR(VLOOKUP(C$66,Items!AD:AJ,3,0),"") -> Account No: 3441002198840 (USD) | J68: =IF(J67="","","SubTotal ") | K68: =IF(K67="","",ROUND(SUM(K66:K67),2))
C69: =IFERROR(VLOOKUP(C$66,Items!AD:AJ,4,0),"") -> Account Name: Tino Solutions Limited | J69: =IF('Customer Base'!I12="DISPLAY TAX","15% VAT",IF('Customer Base'!I12="DO NOT DISPLAY TAX","")) | K69: =IF(J69="","",IFERROR(15%*K68,0))
C70: =IFERROR(VLOOKUP(C$66,Items!AD:AJ,5,0),"") -> Swift Code: ECOCGHACXXX | J70: TOTAL | K70: =IF(K69="",K14&" "&TEXT(K66,"#,##0.00"),K14&" "&TEXT(ROUND(SUM(K68:K69),2),"#,##0.00")) -> GH₵ 113,039.88
C71: =IFERROR(VLOOKUP(C$66,Items!AD:AJ,6,0),"") -> Sort Code: 130111
C72: =IFERROR(VLOOKUP(C$66,Items!AD:AJ,7,0),"") -> Bank Branch: Abeka Lapaz
C74: Mobile Money Number: 0247671755
B77: Tax Identification Number (TIN): C0003648001
B78: Physical address: 38 Amrahia-Katamanso Road, Opposite East-Amarahia, off the Adenta-Dodowa Road, Accra, Ghana ; Email: info@tinosolutions.com

Sheet Customer Base
I2: Discount | K2: %
C3: TINO SOLUTIONS INVOICE PREPARATION QUESTIONNAIRE
I4: Price/kWp | J4: =IFERROR(INVOICE!K14&" "&TEXT(IF(I12="DISPLAY TAX",ROUND(SUM(INVOICE!K68:K69)/J9,2),ROUND(INVOICE!K66/J9,2)),"#,##0.00"),"") -> GH₵ 22,230.06 | U4: =IF(NOW()>INVOICE!Q13,"","AUTOMATE") -> AUTOMATE
C5: =IF(OR(D$7="Hybrid",D$7="Mini-grid"),D$7&" Solar System with "&'Customer Base'!$J$7&"kVA inverter, ",IF(D$7="Grid-Tied","Grid-Tied Solar System with "&'Customer Base'!$J$7&"kVA inverter, ",IF(D$7="Mini-Grid","Mini-Grid Solar System with ",IF(D$7="Backup","Backup System with "&'Customer Base'!$J$7&"kVA inverter, ",""))))&IF(OR(D$7="Hybrid",D$7="Mini-grid"),'Customer Base'!$J$8&"kWh Battery, ","")&IF(D$7="Backup","and "&'Customer Base'!$J$8&"kWh Battery","")&IF(AND(OR(D19="Lithium",D34="Yes"),OR(D$7="Hybrid",D$7="Mini-grid",D$7="Grid-Tied")),'Customer Base'!$J$9&"kWp Solar Panels and Remote Monitoring","")&IF(AND(D19<>"Lithium",D34="No",OR(D$7="Hybrid",D$7="Mini-grid",D$7="Grid-Tied")),"and "&'Customer Base'!$J$9&"kWp Solar Panels","")&IF(D7="",INVOICE!C17,"") -> Hybrid Solar System with 5kVA inverter, 10kWh Battery, 5.085kWp Solar Panels and Remote Monitoring | I5: Exchange Rate | J5: 16.7 | U5: MANUAL
C7: System Type: | D7: Hybrid | I7: Inverter Capacity | J7: ='Customer Base'!D$14*'Customer Base'!D$15 -> 5 | K7: kVA | M7: Victron Type | N7: System Type | O7: System Voltage | P7: Number of Phases | Q7: Inverter Brand | R7: 1st Inverter Rating | S7: 2nd Inverter Rating | T7: Battery Type | U7: Battery Brand | V7: Battery Capacity | W7: Solar Panel Brand | X7: Solar Panel Rating | Y7: Remote Monitoring | Z7: Mounting Structure:
C8: System Voltage: | D8: 48 | I8: Battery Capacity | J8: =SUM(Items!AO205:AO236) -> 10 | K8: kWh | M8: Phoenix | N8: Grid-Tied | O8: {=IF(OR(ISNUMBER(SEARCH({"Hybrid","Backup","Mini-Grid"},D$7))),48,"")} -> 48 | P8: 1 | Q8: {=IF(OR(ISNUMBER(SEARCH({"Mini-Grid","Hybrid","Backup"},D$7))),"Victron","")} -> Victron | R8: {=IF(OR(AND(ISNUMBER(SEARCH({"Victron"},D$13)),ISNUMBER(SEARCH({"Phoenix"},E$13)),OR(ISNUMBER(SEARCH({12,24,48},D$8)))),AND(ISNUMBER(SEARCH({"Victron"},D$13)),ISNUMBER(SEARCH({"Multiplus"},E$13)),OR(ISNUMBER(SEARCH({12,24,48},D$8))))),0.25,"")} -> 0.25 | S8: {=IF(OR(AND(ISNUMBER(SEARCH({"Victron"},F$13)),ISNUMBER(SEARCH({"Phoenix"},E$13)),OR(ISNUMBER(SEARCH({12,24,48},D$8)))),AND(ISNUMBER(SEARCH({"Victron"},F$13)),ISNUMBER(SEARCH({"Multiplus"},E$13)),OR(ISNUMBER(SEARCH({12,24,48},D$8))))),0.25,"")} | T8: {=IF(AND(OR(ISNUMBER(SEARCH({"Hybrid","Backup","Mini-Grid"},D$7))),D8=48),"Lithium","")} -> Lithium | U8: {=IF(AND(OR(ISNUMBER(SEARCH({"Lithium"},D$19))),D$7<>"Grid-Tied"),"BYD","")} -> BYD | V8: =IF(AND(D$19="12V Lead-Acid",D$20="Victron"),8,"") | W8: JA Solar | X8: =IF(D$25="Victron",115,"") | Y8: Yes | Z8: Roof Mount
C9: Number of Phases | D9: 1 | I9: Solar Panel Capacity | J9: =SUM(Items!AO242:AO254) -> 5.085 | K9: kWp | M9: Multiplus | N9: Mini-Grid | O9: {=IF(OR(ISNUMBER(SEARCH({"Hybrid","Backup","Mini-Grid"},D$7))),24,"")} -> 24 | P9: 3 | Q9: {=IF(OR(ISNUMBER(SEARCH({"Hybrid","Backup"},D$7))),"Deye","")} -> Deye | S9: {=IF(OR(AND(ISNUMBER(SEARCH({"Victron"},F$13)),ISNUMBER(SEARCH({"Phoenix"},E$13)),OR(ISNUMBER(SEARCH({12,24,48},D$8)))),AND(ISNUMBER(SEARCH({"Victron"},F$13)),ISNUMBER(SEARCH({"Multiplus"},E$13)),OR(ISNUMBER(SEARCH({12,24,48},D$8))))),0.375,"")} | T9: {=IF(AND(OR(ISNUMBER(SEARCH({"Hybrid","Backup","Mini-Grid"},D$7)))),"12V Lead-Acid","")} -> 12V Lead-Acid | U9: {=IF(AND(OR(ISNUMBER(SEARCH({"Lithium"},D$19))),D$7<>"Grid-Tied"),"Jinko","")} -> Jinko | V9: =IF(AND(D$19="12V Lead-Acid",D$20="Victron"),14,"") | W9: Jinko | X9: =IF(D$25="Victron",270,"") | Y9: No | Z9: Ground Mount
M10: Quattro | N10: Hybrid | O10: {=IF(OR(ISNUMBER(SEARCH({"Hybrid","Backup","Mini-Grid"},D$7))),12,"")} -> 12 | Q10: {=IF(OR(ISNUMBER(SEARCH({"Hybrid","Backup"},D$7))),"Phocos","")} -> Phocos | R10: {=IF(OR(AND(ISNUMBER(SEARCH({"Victron"},D$13)),ISNUMBER(SEARCH({"Phoenix"},E$13)),OR(ISNUMBER(SEARCH({12,24,48},D$8)))),AND(ISNUMBER(SEARCH({"Victron"},D$13)),ISNUMBER(SEARCH({"Multiplus"},E$13)),OR(ISNUMBER(SEARCH({12,24,48},D$8))))),0.5,"")} -> 0.5 | S10: {=IF(OR(AND(ISNUMBER(SEARCH({"Victron"},F$13)),ISNUMBER(SEARCH({"Phoenix"},E$13)),OR(ISNUMBER(SEARCH({12,24,48},D$8)))),AND(ISNUMBER(SEARCH({"Victron"},F$13)),ISNUMBER(SEARCH({"Multiplus"},E$13)),OR(ISNUMBER(SEARCH({12,24,48},D$8))))),0.5,"")} | T10: {=IF(AND(OR(ISNUMBER(SEARCH({"Hybrid","Backup","Mini-Grid"},D$7)))),"2V OPzS","")} -> 2V OPzS | U10: {=IF(AND(OR(ISNUMBER(SEARCH({"12V Lead-Acid","2V OPzS","2V OPzV"},D$19))),D$7<>"Grid-Tied"),"Victron","")} | V10: =IF(AND(D$19="12V Lead-Acid",D$20="Victron"),22,"") | W10: BYD | X10: =IF(D$25="Victron",305,"") | Z10: Carport
N11: Backup | O11: {=IF(OR(ISNUMBER(SEARCH({"Grid-Tied"},D$7))),"230/400","")} | Q11: {=IF(OR(ISNUMBER(SEARCH({"Mini-Grid","Grid-Tied"},D$7))),"Fronius","")} | R11: {=IF(OR(AND(ISNUMBER(SEARCH({"Victron"},D$13)),ISNUMBER(SEARCH({"Phoenix"},E$13)),OR(ISNUMBER(SEARCH({12,24,48},D$8)))),AND(ISNUMBER(SEARCH({"Victron"},D$13)),ISNUMBER(SEARCH({"Multiplus"},E$13)),OR(ISNUMBER(SEARCH({12,24,48},D$8))))),0.8,"")} -> 0.8 | S11: {=IF(OR(AND(ISNUMBER(SEARCH({"Victron"},F$13)),ISNUMBER(SEARCH({"Phoenix"},E$13)),OR(ISNUMBER(SEARCH({12,24,48},D$8)))),AND(ISNUMBER(SEARCH({"Victron"},F$13)),ISNUMBER(SEARCH({"Multiplus"},E$13)),OR(ISNUMBER(SEARCH({12,24,48},D$8))))),0.8,"")} | T11: {=IF(AND(OR(ISNUMBER(SEARCH({"Hybrid","Backup","Mini-Grid"},D$7)))),"2V OPzV","")} -> 2V OPzV | U11: {=IF(AND(OR(ISNUMBER(SEARCH({"12V Lead-Acid","2V OPzS","2V OPzV"},D$19))),D$7<>"Grid-Tied"),"Hoppecke","")} | V11: =IF(AND(D$19="12V Lead-Acid",D$20="Victron"),38,"") | W11: Victron | X11: =IF(D$25="Victron",330,"")
I12: DO NOT DISPLAY TAX | Q12: {=IF(OR(ISNUMBER(SEARCH({"Mini-Grid","Grid-Tied"},D$7))),"Huawei","")} | R12: {=IF(OR(AND(ISNUMBER(SEARCH({"Victron"},D$13)),ISNUMBER(SEARCH({"Phoenix"},E$13)),OR(ISNUMBER(SEARCH({12,24,48},D$8)))),AND(ISNUMBER(SEARCH({"Victron"},D$13)),ISNUMBER(SEARCH({"Multiplus"},E$13)),OR(ISNUMBER(SEARCH({12,24,48},D$8))))),1.2,"")} -> 1.2 | S12: {=IF(OR(AND(ISNUMBER(SEARCH({"Victron"},F$13)),ISNUMBER(SEARCH({"Phoenix"},E$13)),OR(ISNUMBER(SEARCH({12,24,48},D$8)))),AND(ISNUMBER(SEARCH({"Victron"},F$13)),ISNUMBER(SEARCH({"Multiplus"},E$13)),OR(ISNUMBER(SEARCH({12,24,48},D$8))))),1.2,"")} | U12: {=IF(AND(OR(ISNUMBER(SEARCH({"Lithium"},D$19))),D$7<>"Grid-Tied"),"Freedom Won","")} -> Freedom Won | V12: =IF(AND(D$19="12V Lead-Acid",D$20="Victron"),60,"") | W12: Sharp | X12: =IF(D$25="Sharp",415,"")
C13: Inverter Brand: | D13: Victron | E13: Multiplus | F13: Fronius | R13: {=IF(OR(AND(ISNUMBER(SEARCH({"Victron"},D$13)),ISNUMBER(SEARCH({"Phoenix"},E$13)),ISNUMBER(SEARCH({48},D$8))),AND(ISNUMBER(SEARCH({"Victron"},D$13)),ISNUMBER(SEARCH({"Multiplus"},E$13)),OR(ISNUMBER(SEARCH({12,24,48},D$8))))),1.6,"")} -> 1.6 | S13: {=IF(OR(AND(ISNUMBER(SEARCH({"Victron"},F$13)),ISNUMBER(SEARCH({"Phoenix"},E$13)),OR(ISNUMBER(SEARCH({12,24,48},D$8)))),AND(ISNUMBER(SEARCH({"Victron"},F$13)),ISNUMBER(SEARCH({"Multiplus"},E$13)),OR(ISNUMBER(SEARCH({12,24,48},D$8))))),1.6,"")} | V13: =IF(AND(D$19="12V Lead-Acid",D$20="Victron"),90,"") | X13: =IF(D$25="BYD",530,"")
C14: =IF(AND(D7<>"Mini-Grid",D13="Victron"),"Inverter Rating (kVA):",IF(AND(D7<>"Mini-Grid",D13<>"Victron"),"Inverter Rating (kW):",IF(D7="Mini-Grid","Inverter Rating (kVA + kW):",""))) -> Inverter Rating (kVA): | D14: 5 | F14: 15 | R14: {=IF(OR(AND(ISNUMBER(SEARCH({"Victron"},D$13)),ISNUMBER(SEARCH({"Phoenix"},E$13)),ISNUMBER(SEARCH({48},D$8))),AND(ISNUMBER(SEARCH({"Victron"},D$13)),ISNUMBER(SEARCH({"Multiplus"},E$13)),OR(ISNUMBER(SEARCH({12,24,48},D$8)))),AND(OR(ISNUMBER(SEARCH({"Fronius","Huawei"},D$13))),ISNUMBER(SEARCH({"230/400"},D$8)))),2,"")} -> 2 | S14: {=IF(OR(AND(ISNUMBER(SEARCH({"Victron"},F$13)),ISNUMBER(SEARCH({"Phoenix"},E$13)),OR(ISNUMBER(SEARCH({12,24,48},D$8)))),AND(ISNUMBER(SEARCH({"Victron"},F$13)),ISNUMBER(SEARCH({"Multiplus"},E$13)),OR(ISNUMBER(SEARCH({12,24,48},D$8)))),AND(OR(ISNUMBER(SEARCH({"Fronius","Huawei"},F$13))),ISNUMBER(SEARCH({"Mini-Grid"},D$7)))),2,"")} | V14: =IF(AND(D$19="12V Lead-Acid",D$20="Victron"),110,"") | X14: =IF(D$25="BYD",545,"")
C15: Inverter Quantity: | D15: 1 | F15: 1 | I15: MANUAL | J15: No. of Workers | R15: {=IF(OR(AND(ISNUMBER(SEARCH({"Victron"},D$13)),ISNUMBER(SEARCH({"Phoenix"},E$13)),ISNUMBER(SEARCH({48},D$8))),AND(ISNUMBER(SEARCH({"Victron"},D$13)),ISNUMBER(SEARCH({"Multiplus"},E$13)),OR(ISNUMBER(SEARCH({24,48},D$8)))),AND(OR(ISNUMBER(SEARCH({"Deye","Phocos"},D$13))),ISNUMBER(SEARCH({48},D$8))),AND(ISNUMBER(SEARCH({"Phocos"},D$13)),ISNUMBER(SEARCH({24},D$8))),AND(OR(ISNUMBER(SEARCH({"Fronius","Huawei"},D$13))),ISNUMBER(SEARCH({"230/400"},D$8)))),3,"")} -> 3 | S15: {=IF(OR(AND(ISNUMBER(SEARCH({"Victron"},F$13)),ISNUMBER(SEARCH({"Phoenix"},E$13)),OR(ISNUMBER(SEARCH({12,24,48},D$8)))),AND(ISNUMBER(SEARCH({"Victron"},F$13)),ISNUMBER(SEARCH({"Multiplus"},E$13)),OR(ISNUMBER(SEARCH({12,24,48},D$8)))),AND(OR(ISNUMBER(SEARCH({"Deye","Phocos"},F$13))),ISNUMBER(SEARCH({48},D$8))),AND(ISNUMBER(SEARCH({"Phocos"},F$13)),ISNUMBER(SEARCH({24},D$8))),AND(OR(ISNUMBER(SEARCH({"Fronius","Huawei"},F$13))),ISNUMBER(SEARCH({"Mini-Grid"},D$7)))),3,"")} | V15: =IF(AND(D$19="12V Lead-Acid",D$20="Victron"),200,"") | X15: =IF(D$25="Jinko",555,"")
R16: {=IF(OR(AND(ISNUMBER(SEARCH({"Victron"},D$13)),ISNUMBER(SEARCH({"Phoenix"},E$13)),ISNUMBER(SEARCH({48},D$8))),AND(ISNUMBER(SEARCH({"Victron"},D$13)),ISNUMBER(SEARCH({"Multiplus"},E$13)),ISNUMBER(SEARCH({48},D$8))),AND(ISNUMBER(SEARCH({"Victron"},D$13)),ISNUMBER(SEARCH({"Quattro"},E$13)),ISNUMBER(SEARCH({48},D$8))),AND(OR(ISNUMBER(SEARCH({"Deye","Phocos"},D$13))),ISNUMBER(SEARCH({48},D$8))),AND(OR(ISNUMBER(SEARCH({"Fronius","Huawei"},D$13))),ISNUMBER(SEARCH({"230/400"},D$8)))),5,"")} -> 5 | S16: {=IF(OR(AND(ISNUMBER(SEARCH({"Victron"},F$13)),ISNUMBER(SEARCH({"Phoenix"},E$13)),OR(ISNUMBER(SEARCH({24,48},D$8)))),AND(ISNUMBER(SEARCH({"Victron"},F$13)),ISNUMBER(SEARCH({"Multiplus"},E$13)),OR(ISNUMBER(SEARCH({24,48},D$8)))),AND(OR(ISNUMBER(SEARCH({"Deye","Phocos"},F$13))),ISNUMBER(SEARCH({48},D$8))),AND(OR(ISNUMBER(SEARCH({"Fronius","Huawei"},F$13))),ISNUMBER(SEARCH({"Mini-Grid"},D$7)))),5,"")} | V16: =IF(AND(D$19="12V Lead-Acid",D$20="Victron"),220,"") | X16: =IF(D$25="JA Solar",565,"") -> 565
I17: Retail | J17: No. of Nights | R17: {=IF(OR(AND(ISNUMBER(SEARCH({"Victron"},D$13)),ISNUMBER(SEARCH({"Multiplus"},E$13)),ISNUMBER(SEARCH({48},D$8))),AND(ISNUMBER(SEARCH({"Deye"},D$13)),ISNUMBER(SEARCH({48},D$8))),AND(ISNUMBER(SEARCH({"Fronius"},D$13)),ISNUMBER(SEARCH({"230/400"},D$8)))),6,"")} -> 6 | S17: {=IF(OR(AND(ISNUMBER(SEARCH({"Victron"},F$13)),ISNUMBER(SEARCH({"Multiplus"},E$13)),ISNUMBER(SEARCH({48},D$8))),AND(ISNUMBER(SEARCH({"Deye"},F$13)),ISNUMBER(SEARCH({48},D$8))),AND(ISNUMBER(SEARCH({"Fronius"},F$13)),ISNUMBER(SEARCH({"Mini-Grid"},D$7)))),6,"")} | V17: =IF(AND(D$19="12V Lead-Acid",D$20="Hoppecke"),150,"")
R18: {=IF(OR(AND(ISNUMBER(SEARCH({"Victron"},D$13)),ISNUMBER(SEARCH({"Multiplus"},E$13)),ISNUMBER(SEARCH({48},D$8))),AND(ISNUMBER(SEARCH({"Victron"},D$13)),ISNUMBER(SEARCH({"Quattro"},E$13)),ISNUMBER(SEARCH({48},D$8))),AND(ISNUMBER(SEARCH({"Deye"},D$13)),ISNUMBER(SEARCH({48},D$8))),AND(ISNUMBER(SEARCH({"Phocos"},D$13)),ISNUMBER(SEARCH({48},D$8))),AND(ISNUMBER(SEARCH({"Fronius"},D$13)),ISNUMBER(SEARCH({"230/400"},D$8)))),8,"")} -> 8 | S18: {=IF(OR(AND(ISNUMBER(SEARCH({"Victron"},F$13)),ISNUMBER(SEARCH({"Multiplus"},E$13)),ISNUMBER(SEARCH({48},D$8))),AND(ISNUMBER(SEARCH({"Victron"},F$13)),ISNUMBER(SEARCH({"Quattro"},E$13)),ISNUMBER(SEARCH({48},D$8))),AND(ISNUMBER(SEARCH({"Deye"},F$13)),ISNUMBER(SEARCH({48},D$8))),AND(ISNUMBER(SEARCH({"Phocos"},F$13)),ISNUMBER(SEARCH({48},D$8))),AND(ISNUMBER(SEARCH({"Fronius"},F$13)),ISNUMBER(SEARCH({"Mini-Grid"},D$7)))),8,"")} | V18: =IF(AND(D$19="12V Lead-Acid",D$20="Hoppecke"),250,"")
C19: Battery Type | D19: Lithium | R19: {=IF(OR(AND(ISNUMBER(SEARCH({"Victron"},D$13)),ISNUMBER(SEARCH({"Multiplus"},E$13)),ISNUMBER(SEARCH({48},D$8))),AND(ISNUMBER(SEARCH({"Victron"},D$13)),ISNUMBER(SEARCH({"Quattro"},E$13)),ISNUMBER(SEARCH({48},D$8))),AND(ISNUMBER(SEARCH({"Deye"},D$13)),ISNUMBER(SEARCH({48},D$8))),AND(OR(ISNUMBER(SEARCH({"Fronius","Huawei"},D$13))),ISNUMBER(SEARCH({"230/400"},D$8)))),10,"")} -> 10 | S19: {=IF(OR(AND(ISNUMBER(SEARCH({"Victron"},F$13)),ISNUMBER(SEARCH({"Multiplus"},E$13)),ISNUMBER(SEARCH({48},D$8))),AND(ISNUMBER(SEARCH({"Victron"},F$13)),ISNUMBER(SEARCH({"Quattro"},E$13)),ISNUMBER(SEARCH({48},D$8))),AND(ISNUMBER(SEARCH({"Deye"},F$13)),ISNUMBER(SEARCH({48},D$8))),AND(OR(ISNUMBER(SEARCH({"Fronius","Huawei"},F$13))),ISNUMBER(SEARCH({"Mini-Grid"},D$7)))),10,"")} | V19: =IF(AND(D$19="2V OPzV",D$20="Hoppecke"),1250,"")
C20: Battery Brand & per unit capacity | D20: BYD | E20: 5 | F20: =IF(OR(D20="Jinko",D20="BYD"),"kWh",IF(OR(D20="Victron",D20="Hoppecke"),"Ah","")) -> kWh | R20: {=IF(AND(ISNUMBER(SEARCH({"Deye"},D$13)),ISNUMBER(SEARCH({48},D$8))),12,"")} | S20: {=IF(AND(ISNUMBER(SEARCH({"Deye"},F$13)),ISNUMBER(SEARCH({48},D$8))),12,"")} | V20: =IF(AND(D$19="2V OPzS",D$20="Hoppecke"),1520,"")
C21: Battery Quantity: | D21: 2 | R21: {=IF(OR(AND(ISNUMBER(SEARCH({"Victron"},D$13)),ISNUMBER(SEARCH({"Multiplus"},E$13)),ISNUMBER(SEARCH({48},D$8))),AND(ISNUMBER(SEARCH({"Victron"},D$13)),ISNUMBER(SEARCH({"Quattro"},E$13)),ISNUMBER(SEARCH({48},D$8))),AND(ISNUMBER(SEARCH({"Fronius"},D$13)),ISNUMBER(SEARCH({"230/400"},D$8)))),15,"")} -> 15 | S21: {=IF(OR(AND(ISNUMBER(SEARCH({"Victron"},F$13)),ISNUMBER(SEARCH({"Multiplus"},E$13)),ISNUMBER(SEARCH({48},D$8))),AND(ISNUMBER(SEARCH({"Victron"},F$13)),ISNUMBER(SEARCH({"Quattro"},E$13)),ISNUMBER(SEARCH({48},D$8))),AND(ISNUMBER(SEARCH({"Fronius"},F$13)),ISNUMBER(SEARCH({"Mini-Grid"},D$7)))),15,"")} | V21: =IF(AND(D$19="2V OPzS",D$20="Victron"),900,"")
R22: {=IF(AND(ISNUMBER(SEARCH({"Deye"},D$13)),ISNUMBER(SEARCH({48},D$8))),16,"")} | S22: {=IF(AND(ISNUMBER(SEARCH({"Deye"},F$13)),ISNUMBER(SEARCH({48},D$8))),16,"")} | V22: =IF(AND(D$19="2V OPzV",D$20="Victron"),1200,"")
R23: {=IF(AND(ISNUMBER(SEARCH({"Fronius"},D$13)),ISNUMBER(SEARCH({"230/400"},D$8))),17.5,"")} | S23: {=IF(AND(ISNUMBER(SEARCH({"Fronius"},F$13)),ISNUMBER(SEARCH({"Mini-Grid"},D$7))),17.5,"")} | V23: =IF(AND(D$19="Lithium",D$20="BYD"),5,"") -> 5
R24: {=IF(AND(OR(ISNUMBER(SEARCH({"Fronius","Huawei"},D$13))),ISNUMBER(SEARCH({"230/400"},D$8))),20,"")} | S24: {=IF(AND(OR(ISNUMBER(SEARCH({"Fronius","Huawei"},F$13))),ISNUMBER(SEARCH({"Mini-Grid"},D$7))),20,"")} | V24: =IF(AND(D$19="Lithium",D$20="BYD"),15,"") -> 15
C25: Solar Panel Brand: | D25: JA Solar | E25: =IF(D13="Victron",SUM(Items!A242:A254)-IF('Client List'!IL474="",0,'Client List'!IL474),SUM(Items!A242:A254)) -> 9 | F25: Recommended (Pcs) | R25: {=IF(AND(ISNUMBER(SEARCH({"Fronius"},D$13)),ISNUMBER(SEARCH({"230/400"},D$8))),25,"")} | S25: {=IF(AND(ISNUMBER(SEARCH({"Fronius"},F$13)),ISNUMBER(SEARCH({"Mini-Grid"},D$7))),25,"")} | V25: =IF(AND(D$19="Lithium",D$20="Jinko"),4.8,"")
